Workbook

Sheet Inicio2
A1: InicioID | B1: InicioNombre | C1: IncioLogo
A2: ¡Hola!, debes inciar sesión | B2: App Visitador Médico | C2: Inicio2_Images/¡Hola!, debes inciar sesión.IncioLogo.022910.png

Sheet Principal
A1: PrincipalID | B1: PrincipalNombre | C1: PrincipalLogo | D1: PrincipalMensaje
A2: ¡Te damos la bienvenida a esta aplicación que te ayudara a tener los procesos referentes a la visita médica y el área comercial ordenados! | B2: App Visitador Médico | C2: Principal_Images/¡Te damos la bienvenida a esta apli_3999718207737642358.PrincipalLogo.png | D2: ¿Contamos contigo?

Sheet Farmacias
A1: ID_Farmacia | B1: Nombre | C1: RIF | D1: Dirección | E1: Ciudad | F1: Sector | G1: Estado | H1: ZonaID | I1: Teléfono | J1: ID_RepresentanteAsignado | K1: Teléfono Contacto | L1: Contacto | M1: Email | N1: Horario | O1: Productos Promocionados | P1: Producto_Interes | Q1: Segmentacion | R1: Potencial | S1: ContactoPrincipal | T1: CargoContacto | U1: Acción de Seguimiento | V1: Horario_Atención | W1: Instagram | X1: Última_Visita | Y1: Status | Z1: ID_Usuario | AA1: SUBMITTED BY
A2: 2 | B2: Farmacia Mas x Menos | C2: J-50449243-4 | D2: Automercado Más x Menos C.C. Maracay Plaza | E2: MCY | F2: Av. Bermudez Sur | G2: ARA | H2: 3 | I2: 0414-3434641 | J2: dispositivosbiofarco@gmail.com | K2: 0414-3434641 | L2: Dra. Angelica Pérez | Q2: Cadena | R2: Alto | U2: TRUE | X2: 45981.964 | Y2: Activa | Z2: repbiofarco | AA2: dispositivosbiofarco@gmail.com
A3: 3 | B3: Locatel Las Delicias | C3: J-50202212-0 | D3: La Floresta, Maracay | E3: MCY | F3: Las Delicias | G3: ARA | H3: 1 | J3: dispositivosbiofarco@gmail.com | K3: 0424-3388016 | L3: Dr. Vidal Ruiz | M3: farmaciallasdelicias@locatelve.com | Q3: Cadena | R3: Alto | U3: TRUE | X3: 45910 | Y3: Activa | Z3: repbiofarco | AA3: dispositivosbiofarco@gmail.com
A4: 5 | B4: Farma Shop Solidaria Ayacucho | C4: J-29773464-3 | D4: Av. Ayacucho, Maracay 2103, Aragua, Venezuela | E4: MCY | F4: El Centro | G4: ARA | H4: 5 | I4: 0412-9975205 | J4: dispositivosbiofarco@gmail.com | K4: 0412-1496651 | L4: Glenis López | Q4: Mini Cadena | R4: Medio | S4: Glenis López | T4: Encargada | U4: TRUE | W4: @farmashopgrupo | X4: 45981.903 | Y4: Activa | Z4: repbiofarco | AA4: dispositivosbiofarco@gmail.com
A5: 8 | B5: Farma Uno Plus | D5: Calle Los Jabillos con 106 local 105 Sector La Coromoto Maracay | E5: MCY | F5: La Coromoto | G5: ARA | H5: 5 | I5: 0424-3498998 | J5: dispositivosbiofarco@gmail.com | Q5: Independiente | R5: Bajo | U5: TRUE | W5: @farmaunoplus | X5: 45987.796 | Y5: Inactiva | Z5: repbiofarco | AA5: dispositivosbiofarco@gmail.com
A6: 12 | B6: Farmacia Brisas del Lago | D6: Brisas del Lago, Maracay | E6: MCY | F6: Brisas del Lago | G6: ARA | H6: 3 | J6: dispositivosbiofarco@gmail.com | Q6: Independiente | R6: Bajo | U6: TRUE | X6: 45987.796 | Y6: Inactiva | Z6: repbiofarco | AA6: dispositivosbiofarco@gmail.com
A7: 13 | B7: Farmacia Cajigal | C7: J-30791467-0 | D7: Los Olivos Nuevos, Maracay | E7: MCY | F7: Los Olivos Nuevos | G7: ARA | H7: 1 | J7: dispositivosbiofarco@gmail.com | K7: 0426-8338574 | M7: jsching4@gmail.com | Q7: Independiente | R7: Bajo | U7: TRUE | X7: 45933 | Y7: Activa | Z7: repbiofarco | AA7: dispositivosbiofarco@gmail.com
A8: 14 | B8: Farmacia Ciudad Jardín | C8: J-07548214-0 | D8: Av. Miranda, Maracay, Aragua, Venezuela | E8: MCY | F8: San Agustin | G8: ARA | H8: 2 | I8: 0243-2379965 | J8: dispositivosbiofarco@gmail.com | K8: 0243-2379965 | L8: Edith Guillen | M8: farmaciaciudadjardin@gmail.com | Q8: Independiente | R8: Bajo | S8: Edith Guillen | T8: Encargada | U8: TRUE | V8: Lun , Mar , Mie , Jue , Vie , Sab , Dom | X8: 45987.819 | Y8: Activa | Z8: repbiofarco | AA8: dispositivosbiofarco@gmail.com
A9: 16 | B9: Farmacia Farmadía | D9: El Piñonal, Maracay | E9: MCY | F9: El Piñonal | G9: ARA | H9: 4 | I9: 0414-0471853 | J9: dispositivosbiofarco@gmail.com | Q9: Mini Cadena | R9: Medio | U9: TRUE | X9: 45918 | Y9: Activa | Z9: repbiofarco | AA9: dispositivosbiofarco@gmail.com
A10: 17 | B10: Farmacia Gran Vía | C10: J-07509720-3 | D10: 70 Av. Miranda, Maracay 2101, Aragua, Venezuela | E10: MCY | F10: El Carmen | G10: ARA | H10: 2 | I10: 0243-2335512 | J10: dispositivosbiofarco@gmail.com | K10: 0414-1479994 | L10: Ana Matute | M10: farmaciagranviamcy@gmail.com | Q10: Independiente | R10: Bajo | U10: TRUE | X10: 45904 | Y10: Activa | Z10: repbiofarco | AA10: dispositivosbiofarco@gmail.com
A11: 19 | B11: Farmacia La Cooperativa del Norte | D11: La Cooperativa, Maracay | E11: MCY | F11: La Cooperativa | G11: ARA | H11: 1 | I11: 0243-2417887 | J11: dispositivosbiofarco@gmail.com | K11: 0414-4454909 | Q11: Independiente | R11: Bajo | U11: TRUE | W11: @lacooperativadelnorte | X11: 45930 | Y11: Activa | Z11: repbiofarco | AA11: dispositivosbiofarco@gmail.com
A12: 20 | B12: FARMACIAS EUROSALUD | D12: Local 5, Av miranda oeste, Maracay | E12: MCY | F12: La Romana | G12: ARA | I12: 0424-3105949 | J12: dispositivosbiofarco@gmail.com | Q12: Independiente | R12: Bajo | U12: TRUE | X12: 45930 | Y12: Inactiva | Z12: repbiofarco | AA12: dispositivosbiofarco@gmail.com
A13: 21 | B13: Farmacia Grupo VTF | C13: J-29660754-0 | D13: Av. Ayacucho esquina con calle Cajigal Número 45, Maracay | E13: MCY | F13: Av. Ayachucho | G13: ARA | H13: 5 | I13: 0412-9630293 | J13: dispositivosbiofarco@gmail.com | K13: 0412-8363029 | L13: Jesús Hidalgo | Q13: Independiente | R13: Bajo | U13: TRUE | X13: 45981.879 | Y13: Activa | Z13: repbiofarco | AA13: dispositivosbiofarco@gmail.com
A14: 22 | B14: Farmacia Lincoln | C14: J-30146726-4 | D14: Av. Bolívar, Maracay, Aragua, Venezuela | E14: MCY | F14: Centro | G14: ARA | H14: 2 | I14: 0414-5880833 | J14: dispositivosbiofarco@gmail.com | K14: 0412-398327 | L14: Rubexi Magallanes | Q14: Mini Cadena | R14: Medio | U14: TRUE | W14: @farmacialincoln | X14: 45981.851 | Y14: Activa | Z14: repbiofarco | AA14: dispositivosbiofarco@gmail.com
A15: 25 | B15: Farmacia Orinoco | C15: J-07548164-0 | D15: Av. principal de San José, Frente al IVSS, Maracay | E15: MCY | F15: San Jose | G15: ARA | H15: 4 | I15: 0412-4929888 | J15: dispositivosbiofarco@gmail.com | Q15: Independiente | R15: Bajo | U15: TRUE | W15: @farmaciaorinoco_mcy | X15: 45987.81 | Y15: Inactiva | Z15: repbiofarco | AA15: dispositivosbiofarco@gmail.com
A16: 26 | B16: Farmacia María de Jesús | D16: Avenida Constitución Centro comercial Colonial local B7, Santa Ana, Maracay | E16: MCY | F16: Santa Ana | G16: ARA | I16: 0424-3576470 | J16: dispositivosbiofarco@gmail.com | Q16: Independiente | R16: Bajo | U16: TRUE | W16: @farmaciamariadejesus0411 | X16: 45930 | Y16: Inactiva | Z16: repbiofarco | AA16: dispositivosbiofarco@gmail.com
A17: 28 | B17: Farmacia Paseo Las Delicias | C17: J-30377598-5 | D17: Las Delicias, Maracay | E17: MCY | F17: Las Delicias | G17: ARA | H17: 1 | I17: 0424-3005978 | J17: dispositivosbiofarco@gmail.com | K17: 0424-3005978 | L17: Mariela Gómez | Q17: Independiente | R17: Bajo | S17: Mariela Gómez | T17: Encargada | U17: TRUE | X17: 45981.962 | Y17: Activa | Z17: repbiofarco | AA17: dispositivosbiofarco@gmail.com
A18: 29 | B18: Farmacia Punto Blanco | C18: J-29334494-2 | D18: Centro comercial residencial White Point PB, Av. Fuerzas Aéreas, Parque Aragua, Maracay | E18: MCY | F18: Parque Aragua | G18: ARA | H18: 2 | I18: 0424-3202632 | J18: dispositivosbiofarco@gmail.com | Q18: Independiente | R18: Bajo | U18: TRUE | W18: @farmaciapuntoblancoca | X18: 45981.845 | Y18: Activa | Z18: repbiofarco | AA18: dispositivosbiofarco@gmail.com
A19: 32 | B19: Farmacia Rio Blanco | C19: J-07518491-2 | D19: Rio Blanco, Sector San Pedro Alejandro, Maracay | E19: STR | F19: Rio Blanco | G19: ARA | H19: 3 | I19: 0424-3370967 | J19: dispositivosbiofarco@gmail.com | K19: 0424-3370967 | L19: Mirla | Q19: Independiente | R19: Bajo | S19: Mirla | T19: Encargada | U19: TRUE | X19: 45981.798 | Y19: Activa | Z19: repbiofarco | AA19: dispositivosbiofarco@gmail.com
A20: 33 | B20: Farmacia Samán de Güere | C20: J-30285453-4 | D20: Sector, Intercomunal Maracay, Turmero, Maracay | E20: TUR | F20: Intercomunal | G20: ARA | H20: 4 | I20: 0412-9302356 | J20: dispositivosbiofarco@gmail.com | K20: 0412-9302356 | L20: José Navas | Q20: Mini Cadena | R20: Medio | U20: TRUE | V20: Lun , Mar , Mie , Jue , Vie , Sab , Dom | W20: @farmaciacentralturmero | X20: 45981.77 | Y20: Activa | Z20: repbiofarco | AA20: dispositivosbiofarco@gmail.com
A21: 36 | B21: Farmacia San Juan de Dios | D21: Barrio la Democracia, Calle Boyaca, Maracay | E21: MCY | F21: Barrio la Democracia | G21: ARA | I21: 0412-4410320 | J21: dispositivosbiofarco@gmail.com | Q21: Independiente | U21: TRUE | X21: 45987.811 | Y21: Inactiva | Z21: repbiofarco | AA21: dispositivosbiofarco@gmail.com
A22: 37 | B22: Farmacias Nuevo Siglo y Santo Remedio | C22: J-30927929-0 | D22: Edificio Mariño, Calle Rivas Con, Locales C, D Y E C. Sucre, Turmero | E22: TUR | F22: Turmero | G22: ARA | I22: 0244-6618043 | J22: dispositivosbiofarco@gmail.com | Q22: Cadena | R22: Alto | U22: TRUE | W22: @farmaciasnuevosiglo | X22: 45953 | Y22: Activa | Z22: repbiofarco | AA22: dispositivosbiofarco@gmail.com
A23: 46 | B23: Farmatodo Zuly | C23: J-00020200-1 | D23: Las Delicias 2101, Aragua, Venezuela | E23: MCY | F23: Las Delicias | G23: ARA | I23: 0243-2424540 | J23: dispositivosbiofarco@gmail.com | K23: 0416-3454987 | L23: Dra. Rosangela Montenegro | Q23: Cadena | U23: TRUE | X23: 45909 | Y23: Activa | Z23: repbiofarco | AA23: dispositivosbiofarco@gmail.com
A24: 47 | B24: Farmayor Av. Miranda | C24: J-41262894-4 | D24: Calle Páez entre calle Soublette y Boulevard Pérez Almarza, Maracay | E24: MCY | F24: Centro | G24: ARA | I24: 0243-2455689 | J24: dispositivosbiofarco@gmail.com | K24: 0414-4606599 | L24: Yamaris Rodríguez | M24: farmaciayalimentosfarmayor@gmail.com | Q24: Mini Cadena | U24: TRUE | X24: 45981.912 | Y24: Activa | Z24: repbiofarco | AA24: dispositivosbiofarco@gmail.com
A25: 48 | B25: Farmacia LaFarma C.C. Las Américas | C25: J-31116593-2 | D25: Avenida Las Delicias, Maracay 2101, Aragua, Venezuela | E25: MCY | F25: Las Delicias | G25: ARA | I25: 0412-4660774 | J25: dispositivosbiofarco@gmail.com | K25: 0412-4660774 | L25: Alejandra Franco | Q25: Mini Cadena | U25: TRUE | W25: @lafarmacclasamericas | X25: 45806 | Y25: Activa | Z25: repbiofarco | AA25: dispositivosbiofarco@gmail.com
A26: 50 | B26: Farmacia SAAS Av. Los Aviadores | C26: J-50265214-0 | D26: Av. Los Aviadores, Palo Negro, Maracay, Edo. Aragua. | E26: PLN | F26: Av. Los Aviadores | G26: ARA | I26: 0424-3080504 | J26: dispositivosbiofarco@gmail.com | K26: 0424-3774424 | L26: Briscarlet Romero | Q26: Cadena | U26: TRUE | W26: @farmaciasaas_aviadores | X26: 45922 | Y26: Activa | Z26: repbiofarco | AA26: dispositivosbiofarco@gmail.com
A27: 51 | B27: Farmacia El Sol II | C27: J-3083246-5 | D27: Local 1, C.C Hormiga Center, Av Bolivar, Nivel 1 Calle Sanchez Carrero, Maracay 2101, Aragua | E27: MCY | F27: Centro | G27: ARA | I27: 0412-1443505 | J27: dispositivosbiofarco@gmail.com | K27: 0412-1443505 | L27: Geisy | Q27: Mini Cadena | U27: TRUE | X27: 45981.92 | Y27: Activa | Z27: repbiofarco | AA27: dispositivosbiofarco@gmail.com
A28: 52 | B28: Farmacia El Sol | C28: J-00132395-3 | D28: Local #58, Av Miranda, 2101 Calle Sanchez Carrero, Maracay 2101, Aragua | E28: MCY | F28: Av Miranda | G28: ARA | H28: 2 | I28: 0424-3612060 | J28: dispositivosbiofarco@gmail.com | K28: 0412-4304678 | L28: Elizabeth Duran | Q28: Mini Cadena | R28: Medio | U28: TRUE | X28: 45902 | Y28: Activa | Z28: repbiofarco | AA28: dispositivosbiofarco@gmail.com
A29: 53 | B29: Farmacia SAAS Las Delicias | C29: J-07000750-8 | D29: 8C6Q+PXF, Av Principal El Castaño, Maracay 2101, Aragua, Venezuela | E29: MCY | F29: Delicias | G29: ARA | I29: 0424-3823338 | J29: dispositivosbiofarco@gmail.com | K29: 0424-3053065 | L29: Dulce García | Q29: Cadena | U29: TRUE | V29: Lun , Mar , Mie , Jue , Vie , Sab , Dom | W29: @saasav.lasdelicias | X29: 45917 | Y29: Activa | Z29: repbiofarco | AA29: dispositivosbiofarco@gmail.com
A30: 54 | B30: Farma Vital I | C30: J-2952214-9 | D30: Avenida Universidad, El Limón, Aragua, Venezuela | E30: MCY | F30: El Limón | G30: ARA | I30: 0414-0531788 | J30: dispositivosbiofarco@gmail.com | K30: 0412-4427134 | L30: Jenxy | Q30: Mini Cadena | U30: TRUE | X30: 45909 | Y30: Activa | Z30: repbiofarco | AA30: dispositivosbiofarco@gmail.com
A31: 55 | B31: Farma Vital Terminal Central | C31: J-07521484-6 | D31: Terminal de Pasajeros | E31: MCY | F31: Terminal | G31: ARA | I31: 0414-4751430 | J31: dispositivosbiofarco@gmail.com | K31: 0412-4170868 | L31: Betsamar | Q31: Mini Cadena | R31: Medio | U31: TRUE | X31: 45981.897 | Y31: Activa | Z31: repbiofarco | AA31: dispositivosbiofarco@gmail.com
A32: 56 | B32: Farma Vital, C. A | C32: J-29396399-0 | D32: Diagonal Clinica Lugo, C.C Vista Lago, Avenida 19 de Abril, Maracay 2101, Aragua | E32: MCY | F32: 19 de Abril | G32: ARA | H32: 2 | I32: 0412-8948596 | J32: dispositivosbiofarco@gmail.com | K32: 0424-3533959 | L32: Dilimary | M32: farmavitalmaracay@gmail.com | Q32: Mini Cadena | R32: Alto | U32: TRUE | X32: 45905 | Y32: Activa | Z32: repbiofarco | AA32: dispositivosbiofarco@gmail.com
A33: 57 | B33: Farma Vital Campo Alegre | C33: J-31072776-7 | D33: Av. Bermudez, Maracay 2103, Aragua, Venezuela | E33: MCY | F33: Sur de Aragua | G33: ARA | I33: 0412-4837874 | J33: dispositivosbiofarco@gmail.com | K33: 0424-3074961 | L33: Kariana Alfonso | Q33: Mini Cadena | U33: TRUE | X33: 45782 | Y33: Activa | Z33: repbiofarco | AA33: dispositivosbiofarco@gmail.com
A34: 65 | B34: Distufar Av. Bermudez | C34: J-50125197-5 | D34: Av. Bermudez, Maracay 2103, Aragua, Venezuela | E34: MCY | F34: Av. Bermudez Sur | G34: ARA | I34: 0412-8956128 | J34: dispositivosbiofarco@gmail.com | K34: 0412-5979880 | L34: Andrea Gutierrez | Q34: Mini Cadena | R34: Bajo | U34: TRUE | V34: Lun , Mar , Mie , Jue , Vie , Sab , Dom | X34: 45981.758 | Y34: Activa | Z34: repbiofarco | AA34: dispositivosbiofarco@gmail.com
A35: 66 | B35: Distufar Santa Ines | D35: Santa Ines, Maracay 2106, Aragua, Venezuela | E35: STR | F35: Santa Ines | G35: ARA | H35: 4 | I35: 0412-3982006 | J35: dispositivosbiofarco@gmail.com | K35: 0412-3982006 | L35: Yasmin | Q35: Mini Cadena | R35: Medio | U35: TRUE | X35: 45929 | Y35: Activa | Z35: repbiofarco | AA35: dispositivosbiofarco@gmail.com
A36: 67 | B36: Farmacia La Ganadera | C36: J-4028240-9 | D36: Av. Constitución, Maracay, Aragua, Venezuela | E36: MCY | F36: Santa Rosa | G36: ARA | I36: 0414-1518972 | J36: dispositivosbiofarco@gmail.com | K36: 0414-5340201 | L36: Jose Torres | Q36: Mini Cadena | U36: TRUE | W36: @farmacia_la_ganadera | X36: 45919 | Y36: Activa | Z36: repbiofarco | AA36: dispositivosbiofarco@gmail.com
A37: 69 | B37: Farma Milán Santa Rita | C37: J-50220672-8 | D37: Santa Rita, Aragua, Venezuela | E37: STR | F37: Santa Rita | G37: ARA | I37: 0414-9479464 | J37: dispositivosbiofarco@gmail.com | K37: 0412-7118891 | L37: Deisy Zar | M37: farmamilansantarita@gmail.com | Q37: Mini Cadena | U37: TRUE | X37: 45922 | Y37: Activa | Z37: repbiofarco | AA37: dispositivosbiofarco@gmail.com
A38: 70 | B38: Farma Milán La Morita | E38: STR | F38: La Morita | G38: ARA | I38: 0414-4636195 | J38: dispositivosbiofarco@gmail.com | K38: 0414-4636195 | L38: Fatima Fernandez | Q38: Mini Cadena | R38: Medio | U38: TRUE | X38: 45922 | Y38: Activa | Z38: repbiofarco | AA38: dispositivosbiofarco@gmail.com
A39: 71 | B39: Farmacia Farma Store | E39: MCY | F39: La Cooperativa | G39: ARA | I39: 0414-4907867 | J39: dispositivosbiofarco@gmail.com | K39: 0414-4907867 | L39: Veronica Olmos | Q39: Mini Cadena | U39: TRUE | X39: 45912 | Y39: Activa | Z39: repbiofarco | AA39: dispositivosbiofarco@gmail.com
A40: 72 | B40: Farmacia Policlinico Turmero | C40: J-31252864-3 | E40: TUR | F40: Turmero | G40: ARA | I40: 0244-6636742 | J40: dispositivosbiofarco@gmail.com | K40: 0424-3680773 | L40: Carolina Rodríguez | M40: farmaciapoliclinicoturmero@hotmail.com | Q40: Independiente | U40: TRUE | X40: 45981.861 | Y40: Activa | Z40: repbiofarco | AA40: dispositivosbiofarco@gmail.com
A41: 73 | B41: Farmacia Central 19 | C41: J-07575790-4 | D41: CALLE MARIÑO CON CALLE SUCRE N°18 SECTOR 19 DE ABRIL TURMERO | E41: TUR | F41: 19 de Abril | G41: ARA | I41: 0412-9932540 | J41: dispositivosbiofarco@gmail.com | K41: 0424-3037296 | L41: Jose Navas | Q41: Mini Cadena | U41: TRUE | W41: @farmaciacentralturmero | X41: 45924 | Y41: Activa | Z41: repbiofarco | AA41: dispositivosbiofarco@gmail.com
A42: 75 | B42: Farmacia Farma Vista | D42: C.C. Paseo Cagua | E42: CGA | F42: Cagua | G42: ARA | I42: 0412-8686043 | J42: dispositivosbiofarco@gmail.com | K42: 0412-8686043 | L42: Katy | Q42: Independiente | U42: TRUE | X42: 45929 | Y42: Activa | Z42: repbiofarco | AA42: dispositivosbiofarco@gmail.com
A43: 80 | B43: Farmacia Las Mercedes | C43: J-07515583-1 | D43: C. Independencia, Cagua | E43: CGA | F43: Cagua | G43: ARA | I43: 0412-4534734 | J43: dispositivosbiofarco@gmail.com | K43: 0414-4749193 | L43: Odeisa Olmedo | Q43: Independiente | U43: TRUE | X43: 45929 | Y43: Activa | Z43: repbiofarco | AA43: dispositivosbiofarco@gmail.com
A44: 81 | B44: Farmacia Bendición Sucre | D44: CALLE BOLIVAR, CON C. Froilán Correa, Cagua | E44: CGA | F44: Cagua | G44: ARA | I44: 0416-6430952 | J44: dispositivosbiofarco@gmail.com | K44: 0412-8954493 | L44: Wilberky | Q44: Independiente | U44: TRUE | X44: 45929 | Y44: Activa | Z44: repbiofarco | AA44: dispositivosbiofarco@gmail.com
A45: 83 | B45: Farmacia Far Centro | E45: STC | F45: Santa Cruz | G45: ARA | I45: 0414-4430816 | J45: dispositivosbiofarco@gmail.com | K45: 0414-4430816 | L45: Luis | Q45: Independiente | U45: TRUE | Y45: Activa | Z45: repbiofarco | AA45: dispositivosbiofarco@gmail.com
A46: 84 | B46: Farmacia María de San José | E46: VLL | F46: Villa de Cura | G46: ARA | I46: 0426-1453117 | J46: dispositivosbiofarco@gmail.com | K46: 0426-1453117 | L46: Yepyiza | Q46: Independiente | U46: TRUE | Y46: Activa | Z46: repbiofarco | AA46: dispositivosbiofarco@gmail.com
A47: 85 | B47: Farmacia Santa Inés | E47: VLL | F47: Villa de Cura | G47: ARA | I47: 0424-3482385 | J47: dispositivosbiofarco@gmail.com | K47: 0424-3482385 | Q47: Independiente | U47: TRUE | Y47: Activa | Z47: repbiofarco | AA47: dispositivosbiofarco@gmail.com
A48: 90 | B48: Farmacia Jose Gregorio Hernandez | D48: Barrio José Gregorio Hernandez | E48: MCY | F48: Av. Fuerzas Aéreas Sur | G48: ARA | I48: 0414-5905389 | J48: dispositivosbiofarco@gmail.com | K48: 0414-5905389 | L48: Pablo Segundo | Q48: Independiente | U48: TRUE | X48: 45918 | Y48: Activa | Z48: repbiofarco | AA48: dispositivosbiofarco@gmail.com
A49: 93 | B49: Farma VIP Administración | E49: VIC | F49: La Victoria | G49: ARA | I49: 0414-4906644 | J49: dispositivosbiofarco@gmail.com | K49: 0414-4906644 | L49: Aikon | Q49: Independiente | U49: TRUE | Y49: Activa | Z49: repbiofarco | AA49: dispositivosbiofarco@gmail.com
A50: 94 | B50: Farma Ballenas ISPFA | C50: J-50342625-0 | D50: IPSFA Av. Bolívar Este, Maracay 2101, Aragua, Venezuela | E50: MCY | F50: IPSFA | G50: ARA | J50: dispositivosbiofarco@gmail.com | K50: 0414-5988540 | L50: Norielkis Rovachevich | Q50: Mini Cadena | U50: TRUE | X50: 45903 | Y50: Activa | Z50: repbiofarco | AA50: dispositivosbiofarco@gmail.com
A51: 96 | B51: Farmacia SAAS Maracay Plaza | C51: J-07000750-8 | D51: Av Aragua C/ Av Bermudez C.C. Maracay Plaza Nivel PB LOCAL 45C Y | E51: MCY | F51: C.C. Maracay Plaza | G51: ARA | I51: 0412-8905442 | J51: dispositivosbiofarco@gmail.com | K51: 0424-3089344 | L51: Emily Nuñez | Q51: Cadena | U51: TRUE | X51: 45925 | Y51: Activa | Z51: repbiofarco | AA51: dispositivosbiofarco@gmail.com
A52: 97 | B52: Farmatodo Cristal | C52: J-00020200-1 | D52: Urb San Carlos entre Av Los Samanes y Av. Fuerzas Aereas | E52: MCY | F52: Av. Fuerzas Aéreas Sur | G52: ARA | I52: 0243-2157912 | J52: dispositivosbiofarco@gmail.com | K52: 0424-8821075 | L52: Dra. Ana Quiaro | Q52: Cadena | U52: TRUE | X52: 45981.827 | Y52: Activa | Z52: repbiofarco | AA52: dispositivosbiofarco@gmail.com
A53: 98 | B53: DLS Medical Aragua | C53: J-50617620-3 | D53: Av. 19 de Abril, Maracay 2101, Aragua, Venezuela | E53: MCY | F53: Calicanto | G53: ARA | J53: dispositivosbiofarco@gmail.com | K53: 0424-4242233 | M53: dlsaragua@gmail.com | Q53: Independiente | U53: TRUE | X53: 45797 | Y53: Activa | Z53: repbiofarco | AA53: dispositivosbiofarco@gmail.com
A54: 2f00830e | B54: Farmacia Farma Vero II | C54: J-50144550-8 | D54: Urbanizacion la Soledad, Maracay 2101, Aragua, Venezuela | E54: MCY | F54: La Soledad | G54: ARA | I54: 0424-3240664 | J54: dispositivosbiofarco@gmail.com | K54: 0424-3460625 | L54: Dra. Tahaimy Blanco | Q54: Mini Cadena | U54: TRUE | X54: 45805 | Y54: Activa | Z54: repbiofarco | AA54: dispositivosbiofarco@gmail.com
A55: 67a0121b | B55: FarmaSol Santos Michelena II | C55: J-50564708-3 | D55: Calle Santos Michelena, Maracay 2101, Aragua, Venezuela | E55: MCY | F55: Centro | G55: ARA | H55: 2 | I55: 0424-3043832 | J55: dispositivosbiofarco@gmail.com | K55: 0414-0483164 | L55: Genesis Dalma | Q55: Mini Cadena | R55: Medio | S55: Genesis Devonish | T55: Encargada | U55: TRUE | W55: @farmasol_ve | X55: 45981.917 | Y55: Activa | Z55: repbiofarco | AA55: dispositivosbiofarco@gmail.com
A56: 6d5f7cb2 | B56: Farmacia Farmadito | C56: J-50086841-3 | D56: Urb. Calicanto, Maracay, Aragua, Venezuela | E56: MCY | F56: Urb. Calicanto | G56: ARA | I56: 04243113763 | J56: dispositivosbiofarco@gmail.com | K56: 04243113763 | L56: Ramón Martínez | Q56: Mini Cadena | U56: TRUE | X56: 45981.928 | Y56: Activa | Z56: repbiofarco | AA56: dispositivosbiofarco@gmail.com
A57: 99 | B57: Farmatodo Umbral | C57: J-00020200-1 | D57: AV PPAL LAS DELICIAS CALLE VICENTE LECUNA C/CALLE JUAN V. GONZALEZ ZONA COMERC 1 | E57: MCY | F57: Las Delicias | G57: ARA | J57: dispositivosbiofarco@gmail.com | K57: 0412-8481323 | L57: Dra. Gerardin Gallango | Q57: Cadena | U57: TRUE | X57: 45981.827 | Y57: Activa | Z57: repbiofarco | AA57: dispositivosbiofarco@gmail.com
A58: 100 | B58: Farmatodo Araguaney | C58: J-00020200-1 | D58: Cc Unicentro Maracay, Nivel Pb, Locales Pb-33, Pb-34, Pb-35, Pb-36 Y Pb-37 | E58: MCY | F58: Base Aragua | G58: ARA | J58: dispositivosbiofarco@gmail.com | K58: 0414-9710197 | L58: Dra. Yasnel Alvarez | Q58: Cadena | U58: TRUE | X58: 45903 | Y58: Activa | Z58: repbiofarco | AA58: dispositivosbiofarco@gmail.com
A59: 101 | B59: Farmatodo Gregorio | C59: J-00020200-1 | D59: Av Bermudez, Jurisdicción del Municipio Maracay, Distrito Girardot | E59: MCY | F59: Av. Bermúdez | G59: ARA | J59: dispositivosbiofarco@gmail.com | Q59: Cadena | U59: TRUE | X59: 45981.827 | Y59: Activa | Z59: repbiofarco | AA59: dispositivosbiofarco@gmail.com
A60: 102 | B60: Farmatodo Daysi | C60: J-00020200-1 | D60: Calle Mariño con Calle Páez Sector Centro Sur Oeste III Municipio Girardot | E60: MCY | F60: Centro | G60: ARA | J60: dispositivosbiofarco@gmail.com | K60: 0424-3793446 | L60: Dra. Loira Fonseca | Q60: Cadena | R60: Alto | U60: TRUE | X60: 45981.827 | Y60: Activa | Z60: repbiofarco | AA60: dispositivosbiofarco@gmail.com
A61: 103 | B61: Farmatodo Cedro | C61: J-00020200-1 | D61: CALLE 2 C/4TA AV. MANZANA J LOCAL 1 LA SOLEDAD | E61: MCY | F61: Las Delicias | G61: ARA | J61: dispositivosbiofarco@gmail.com | Q61: Independiente | U61: TRUE | X61: 45981.828 | Y61: Activa | Z61: repbiofarco | AA61: dispositivosbiofarco@gmail.com
A62: 18ea49b4 | B62: Farmacial Real 2022 | C62: J-50246703-3 | D62: Av. Casanova Godoy Cruce en la Funeraria Valles en las instalaciones del CAFMA, al frente de la emergencia del Hospital Militar Cnel. Elbano Paredes Vivas | E62: MCY | F62: La Barraca | G62: ARA | I62: 0243-2337072 | J62: dispositivosbiofarco@gmail.com | K62: 0412-9883919 | L62: José Sulbarán | N62: L - V | Q62: Independiente | U62: TRUE | W62: @farmaciareal2022 | X62: 45909 | Y62: Activa | Z62: repbiofarco | AA62: dispositivosbiofarco@gmail.com
A63: af0758a4 | B63: Farmacia Diga Center | C63: J-30015410-5 | D63: AV. DR. MONTOYA CC DIGA CENTER SEGUNDA ETAPA NIVEL 2 LOCAL L35 L36 SECTOR, Turmero 2115, Aragua, Venezuela | E63: STR | F63: Linares Alcantara | G63: ARA | I63: 0243-2694066 | J63: dispositivosbiofarco@gmail.com | K63: 0424-3505639 | L63: Barbara Gonzalez | M63: genesis.compras@equipopadilla.com | Q63: Independiente | U63: TRUE | X63: 45922 | Y63: Activa | Z63: repbiofarco | AA63: dispositivosbiofarco@gmail.com
A64: af0758a5 | B64: Farmacia SAAS Boulevvart Páez | C64: J-40254084-1 | D64: C. Paez, Maracay, Aragua, Venezuela | E64: MCY | F64: Centro | G64: ARA | I64: 0412-0319636 | J64: dispositivosbiofarco@gmail.com | K64: 0412-4345095 | L64: Pedro Ramírez | M64: farmaciaboulebardpaez@gmail.com | Q64: Cadena | U64: TRUE | W64: @saasmaracay | X64: 45910 | Y64: Activa | Z64: repbiofarco | AA64: dispositivosbiofarco@gmail.com
A65: c3aaef31 | B65: Farmacias Multimed | C65: J-50366838-5 | D65: Av. 19 de Abril, Maracay 2101, Aragua, Venezuela | E65: MCY | F65: Centro | G65: ARA | H65: 2 | I65: 0412-2805515 | J65: dispositivosbiofarco@gmail.com | K65: 0412-2805515 | L65: Ani Suarez | M65: farmaciasfarmed@gmail.com | N65: L-V | Q65: Independiente | R65: Medio | U65: TRUE | W65: @farmaciasmultimed.ve | X65: 45981.87 | Y65: Activa | Z65: repbiofarco | AA65: dispositivosbiofarco@gmail.com
A66: 110 | B66: Farma Vital Caña de Azucar | D66: 2101, Maracay 2101, Aragua | E66: MCY | F66: Caña de Azucar | G66: ARA | I66: 0424-3537172 | J66: dispositivosbiofarco@gmail.com | K66: 0414-3463701 | L66: Gley Rujano | Q66: Mini Cadena | U66: TRUE | X66: 45987.818 | Y66: Activa | Z66: repbiofarco | AA66: dispositivosbiofarco@gmail.com
A67: 111 | B67: Farma Vital Los Olivos "Farmacia Unión" | C67: J-07538782-1 | D67: Los Olivos | E67: MCY | F67: Terminal | G67: ARA | H67: 2 | I67: 0424-3065450 | J67: dispositivosbiofarco@gmail.com | K67: 0424-3065450 | L67: Mayerit Mora | Q67: Mini Cadena | R67: Medio | S67: Mayerit Mora | T67: Encargada | U67: TRUE | X67: 45981.961 | Y67: Activa | Z67: repbiofarco | AA67: dispositivosbiofarco@gmail.com
A68: 112 | B68: Farma Vital Al Kosto | C68: J-50069130-0 | D68: 6CC7+6F8, Maracay 2103, Aragua | E68: MCY | F68: Cuartelito | G68: ARA | H68: 3 | I68: 0243-2354968 | J68: dispositivosbiofarco@gmail.com | K68: 0243-2354968 | M68: farma.kostoca@gmail.com | Q68: Mini Cadena | U68: TRUE | X68: 45987.838 | Y68: Activa | Z68: repbiofarco | AA68: dispositivosbiofarco@gmail.com
A69: 113 | B69: Farma Vital Rosario de Paya | D69: Granja el Naranjal, Av. Ppal Rosario de Paya. C.C Valle de Paya. Sector, Turmero 2115, Aragua | E69: TUR | F69: Rosario de Paya | G69: ARA | I69: 0424-3447303 | J69: dispositivosbiofarco@gmail.com | Q69: Mini Cadena | U69: TRUE | X69: 45929 | Y69: Activa | Z69: repbiofarco | AA69: dispositivosbiofarco@gmail.com
A70: 115 | B70: Farma Vital Coromoto Farco | C70: J-07527826-7 | D70: Av. Ayacucho, con Av. Miranda, Maracay 2103, Aragua | E70: MCY | F70: Centro | G70: ARA | H70: 9 | I70: 0412-4427131 | J70: dispositivosbiofarco@gmail.com | K70: 0412-4427131 | L70: Dilmary Ostos | M70: farmacia.coromotofarco@gmail.com | Q70: Mini Cadena | U70: TRUE | X70: 45981.879 | Y70: Activa | Z70: repbiofarco | AA70: dispositivosbiofarco@gmail.com
A71: 116 | B71: Farma Vital Centro JV | C71: J-40286612-7 | D71: Palo Negro, Aragua, Venezuela | E71: PLN | F71: Centro | G71: ARA | H71: 2 | I71: 0424-3730080 | J71: dispositivosbiofarco@gmail.com | K71: 0412-4740408 | L71: Elaine Flores | Q71: Mini Cadena | R71: Medio | S71: Elaine Flores | T71: Encargada | U71: TRUE | V71: Lun , Mar , Mie , Jue , Vie , Sab , Dom | X71: 45981.816 | Y71: Activa | Z71: repbiofarco | AA71: dispositivosbiofarco@gmail.com
A72: 117 | B72: Farma Vital 23 de Enero | C72: J-50163706-7 | D72: 69XM+W96, Av. Constitución, Maracay 2103, Aragua, Venezuela | E72: MCY | F72: 23 de Enero | G72: ARA | H72: 9 | I72: 0424-3730070 | J72: dispositivosbiofarco@gmail.com | K72: 0424-4923531 | L72: Maria Celeste | M72: farmacenter23enero@gmail.com | Q72: Mini Cadena | R72: Medio | S72: Maria Celeste | T72: Encargada | U72: TRUE | X72: 45981.921 | Y72: Activa | Z72: repbiofarco | AA72: dispositivosbiofarco@gmail.com
A73: 118 | B73: Farma Vital Santa Rita "Inversora Carfa" | C73: J-30310739-7 | D73: 2103 Av. Francisco de Miranda, Maracay 2103, Aragua, Venezuela | E73: STR | F73: Santa Rita | G73: ARA | I73: 0424-3097024 | J73: dispositivosbiofarco@gmail.com | K73: 0424-3046949 | L73: Romer Rojas | Q73: Mini Cadena | U73: TRUE | X73: 45981.951 | Y73: Activa | Z73: repbiofarco | AA73: dispositivosbiofarco@gmail.com
A74: 119 | B74: Farma Vital Piñonal | C74: J-50487693-3 | D74: Av. Los Chaguaramos. Calle 15. Barrio San José, Maracay 2103, Aragua | E74: MCY | F74: San José | G74: ARA | H74: 8 | I74: 0424-3572026 | J74: dispositivosbiofarco@gmail.com | Q74: Mini Cadena | R74: Medio | U74: TRUE | X74: 45981.89 | Y74: Activa | Z74: repbiofarco | AA74: dispositivosbiofarco@gmail.com
A75: 77ecf9b7 | B75: Farmacia Farmavero | C75: J-30823400-1 | D75: C.C. Parque San Jacinto, Al Lado de la Panaderia Los Golfeados de San Jacinto, Maracay, Estado Aragua. | E75: MCY | F75: San Jacinto | G75: ARA | I75: 0414-1467867 | J75: dispositivosbiofarco@gmail.com | K75: 0424-3383645 | Q75: Mini Cadena | R75: Medio | U75: TRUE | V75: Lun , Mar , Mie , Jue , Vie , Sab , Dom | W75: @farmacia_farmavero | X75: 45981.801 | Y75: Activa | Z75: repbiofarco | AA75: dispositivosbiofarco@gmail.com
A76: 0644ac34 | B76: Facitodo San Jacinto | C76: J-50285133-0 | D76: Urbanizacion San Jacinto, Maracay, Aragua, Venezuela | E76: MCY | F76: San Jacinto | G76: ARA | H76: 4 | I76: 0424-3257945 | J76: dispositivosbiofarco@gmail.com | K76: 0424-3257945 | L76: Monica Alvarez | Q76: Mini Cadena | R76: Medio | U76: TRUE | X76: 45987.824 | Y76: Activa | Z76: repbiofarco | AA76: dispositivosbiofarco@gmail.com
A77: 265f80f8 | B77: Facitodo 23 de Enero | C77: J-31504395-5 | D77: 23 de Enero | E77: MCY | F77: 23 de Enero | G77: ARA | I77: 0424-3171324 | J77: dispositivosbiofarco@gmail.com | K77: 0424-4244910 | L77: Danny | Q77: Mini Cadena | U77: TRUE | X77: 45981.923 | Y77: Activa | Z77: repbiofarco | AA77: dispositivosbiofarco@gmail.com
A78: 67a6b823 | B78: Inversiones Facifarma Norte "Facitodo" | C78: J-50111397-1 | D78: 7CF8+8CV, C. La Cooperativa, Maracay 2101, Aragua, Venezuela | E78: MCY | F78: Las Delicias | G78: ARA | H78: 1 | I78: 0424-3161277 | J78: dispositivosbiofarco@gmail.com | K78: 0424-3161277 | L78: Ivana Gutierrez | Q78: Mini Cadena | U78: TRUE | X78: 45987.833 | Y78: Activa | Z78: repbiofarco | AA78: dispositivosbiofarco@gmail.com
A79: 8a8c02f5 | B79: Facitodo Boulevard | C79: J-50207420-1 | D79: Av. Miranda c/c Boulevard Pérez Almarza | E79: MCY | F79: Centro | G79: ARA | H79: 2 | I79: 0424-3129857 | J79: dispositivosbiofarco@gmail.com | K79: 0424-3129857 | L79: Monica Alvarez | Q79: Mini Cadena | R79: Medio | S79: Monica Alvarez | T79: Encargada | U79: TRUE | X79: 45981.907 | Y79: Activa | Z79: repbiofarco | AA79: dispositivosbiofarco@gmail.com
A80: dcebf3b6 | B80: Facitodo La Mulera | D80: C.C. La Mulera | E80: MCY | F80: Los Samanes | G80: ARA | J80: dispositivosbiofarco@gmail.com | Q80: Mini Cadena | U80: TRUE | X80: 45987.596 | Y80: Inactiva | Z80: repbiofarco | AA80: dispositivosbiofarco@gmail.com
A81: bfc69afe | B81: Facitodo Av. Mariño | C81: J-50093878-6 | D81: Av. Miranda & Blvd. Pérez Almarza, Maracay 2103, Aragua, Venezuela | E81: MCY | F81: Centro | G81: ARA | I81: 0424-3209426 | J81: dispositivosbiofarco@gmail.com | K81: 0424-3209426 | L81: Monica Alvarez | Q81: Mini Cadena | U81: TRUE | X81: 45987.832 | Y81: Activa | Z81: repbiofarco | AA81: dispositivosbiofarco@gmail.com
A82: 5d3542f7 | B82: Farmavida Intercomunal | C82: J-50562826-7 | D82: Avenida Intercomunal Santiago Mariño, Turmero 2115, Aragua, Venezuela | E82: TUR | F82: La Providencia | G82: ARA | I82: 0412-4959996 | J82: dispositivosbiofarco@gmail.com | K82: 0412-1447804 | L82: Nai | Q82: Mini Cadena | U82: TRUE | X82: 45918 | Y82: Activa | Z82: repbiofarco | AA82: dispositivosbiofarco@gmail.com
A83: 369efdb8 | B83: Farmavida La Victoria | D83: C. Páez, La Victoria 2121, Aragua, Venezuela | E83: VIC | F83: Centro | G83: ARA | I83: 0424-3447609 | J83: dispositivosbiofarco@gmail.com | K83: 04125955454 | M83: farmavida.prov@gmail.com | Q83: Mini Cadena | U83: TRUE | W83: @farmavidavzla_ | Y83: Activa | Z83: repbiofarco | AA83: dispositivosbiofarco@gmail.com
A84: 0be7a23b | B84: Eurofarmacia Las Americas | C84: J-31221441-4 | D84: Avenida Las Delicias, Maracay 2101, Aragua, Venezuela | E84: MCY | F84: Las Delicias | G84: ARA | H84: 1 | I84: 0414-4740694 | J84: dispositivosbiofarco@gmail.com | K84: 0414-4740694 | L84: Dayana Mujica | M84: eurofarmacia135@gmail.com | Q84: Mini Cadena | R84: Alto | U84: TRUE | W84: @euromercadoca | X84: 45981.949 | Y84: Activa | Z84: repbiofarco | AA84: dispositivosbiofarco@gmail.com
A85: f6a4018b | B85: Farmacia Solidaria y Popular | C85: J-07579872-4 | D85: C. Mariño, Maracay, Aragua, Venezuela | E85: MCY | F85: Centro | G85: ARA | J85: dispositivosbiofarco@gmail.com | L85: Ilda Guerra | M85: farmasp@gmail.com | Q85: Independiente | U85: TRUE | X85: 45905 | Y85: Activa | Z85: repbiofarco | AA85: dispositivosbiofarco@gmail.com
A86: 69b36f13 | B86: Farmasol Boulevard 2020 | C86: J-50031230-0 | D86: Blvd. Pérez Almarza, Maracay 2103, Aragua, Venezuela | E86: MCY | F86: Centro | G86: ARA | H86: 2 | I86: 0414-4631620 | J86: dispositivosbiofarco@gmail.com | K86: 0414-4631620 | L86: Genesis Dalma | P86: PRO-021 , PRO-034 , eeac8176 , 71df8880269341fce19e2043 | Q86: Mini Cadena | R86: Medio | S86: Genesis Devonish | T86: Encargada | U86: TRUE | V86: Lun , Mar , Mie , Jue , Vie , Sab , Dom | W86: @farmasol_ve | X86: 45981.917 | Y86: Activa | Z86: repbiofarco | AA86: dispositivosbiofarco@gmail.com
A87: 703e8e46 | B87: Farmacia Las Ballenas 2020 | C87: J-50038918-3 | D87: 7C74+RHV Parque Las Ballenas, Maracay 2101, Aragua, Venezuela | E87: MCY | F87: Las Delicias | G87: ARA | H87: 1 | J87: dispositivosbiofarco@gmail.com | L87: Amarelis | Q87: Mini Cadena | R87: Medio | S87: Amarelis | U87: TRUE | W87: @farmaballenas | X87: 45981.902 | Y87: Activa | Z87: repbiofarco | AA87: dispositivosbiofarco@gmail.com
A88: f6786eba | B88: Farma Ven | C88: J-50254125-0 | D88: Parada Bus El Samán, Av. Los Jabillos, Maracay 2105, Aragua, Venezuela | E88: MCY | F88: José Felix Ribas | G88: ARA | I88: 0424-3564637 | J88: dispositivosbiofarco@gmail.com | K88: 0412-4109208 | L88: Angel Cillo | Q88: Independiente | U88: TRUE | X88: 45901 | Y88: Activa | Z88: repbiofarco | AA88: dispositivosbiofarco@gmail.com
A89: cfaf6844 | B89: Farmasol Vargas | C89: J-50564759-8 | D89: Calle Vargas, Maracay 2101, Aragua, Venezuela | E89: MCY | F89: Centro | G89: ARA | H89: 2 | I89: 0424-3466685 | J89: dispositivosbiofarco@gmail.com | K89: 0424-3466685 | L89: Genesis Dalma | Q89: Mini Cadena | R89: Medio | S89: Genesis Devonish | T89: Encargada | U89: TRUE | X89: 45981.918 | Y89: Activa | Z89: repbiofarco | AA89: dispositivosbiofarco@gmail.com
A90: 708d54e0 | B90: Farmacia Mi Esperanza 2424 | C90: J-50671898-7 | D90: Av. Bolívar, Maracay, Aragua, Venezuela | E90: MCY | F90: Centro | G90: ARA | I90: 0424-3093104 | J90: dispositivosbiofarco@gmail.com | K90: 0414-9474793 | L90: Andrea Rodriguez | M90: farmaciamiesperanza2424@gmail.com | Q90: Independiente | U90: TRUE | X90: 45901 | Y90: Activa | Z90: repbiofarco | AA90: dispositivosbiofarco@gmail.com
A91: 40c45c41 | B91: FARMACENTER CENTRO II C.A | C91: J-412283471-4 | D91: Av. Bolivar, C/ Vargas con Av Bolívar Diagonal a la U.E Republica de México | E91: MCY | F91: Centro | G91: ARA | H91: 2 | I91: 0412-1469168 | J91: dispositivosbiofarco@gmail.com | K91: 0424-3288704 | L91: Lisbeth | M91: farmacentercentroii@gmail.com | Q91: Independiente | U91: TRUE | W91: @farmacenterca | X91: 45981.849 | Y91: Activa | Z91: repbiofarco | AA91: dispositivosbiofarco@gmail.com
A92: b7896ff6 | B92: Farmatodo Amatista | C92: J-00020200-1 | D92: Av. Intercomunal Santiago Mariño, Turmero, Aragua, Venezuela | E92: TUR | F92: La Providencia | G92: ARA | J92: dispositivosbiofarco@gmail.com | Q92: Cadena | U92: TRUE | X92: 45905 | Y92: Activa | Z92: repbiofarco | AA92: dispositivosbiofarco@gmail.com
A93: 2cb82336 | B93: Mc Time Farmacia | C93: J-31584521-0 | D93: Av. Bolívar, Maracay, Aragua, Venezuela | E93: MCY | F93: Parque Aragua | G93: ARA | J93: dispositivosbiofarco@gmail.com | K93: 0412-466596 | L93: Daniel | Q93: Independiente | U93: TRUE | X93: 45901 | Y93: Activa | Z93: repbiofarco | AA93: dispositivosbiofarco@gmail.com
A94: 0be7a231 | B94: Eurofarmacia | C94: J-30071273-7 | D94: Av. Intercomunal Santiago Mariño, Turmero, Aragua, Venezuela | E94: TUR | F94: La Providencia | G94: ARA | H94: 4 | I94: 0414-4476076 | J94: dispositivosbiofarco@gmail.com | K94: 0414-4476076 | L94: Wilmer | M94: farmaeuro2023@gmail.com | Q94: Mini Cadena | R94: Alto | S94: Wilmer | T94: Comprador | U94: TRUE | W94: @euromercadoca | X94: 45981.949 | Y94: Activa | Z94: repbiofarco | AA94: dispositivosbiofarco@gmail.com
A95: e8805231 | B95: Farmacia Lincoln Las Delicias | C95: J-50569819-2 | D95: Av. Las Delicias, Maracay 2101, Aragua, Venezuela | E95: MCY | F95: Las Delicias | G95: ARA | H95: 1 | I95: 0414-9782614 | J95: dispositivosbiofarco@gmail.com | K95: 0414-9782614 | L95: Francis Quevedo | Q95: Mini Cadena | U95: TRUE | X95: 45981.869 | Y95: Activa | Z95: repbiofarco | AA95: dispositivosbiofarco@gmail.com
A96: b510b7c9 | B96: FarmaDia Santa María | C96: J-30341278-5 | D96: Avenida bolivar diagonal Parque Aragua al lado de C.C Pacífico Maracay-Edo.Aragua | E96: MCY | F96: Parque Aragua | G96: ARA | I96: 0243-2328297 | J96: dispositivosbiofarco@gmail.com | K96: 0412-6693059 | Q96: Mini Cadena | U96: TRUE | X96: 45903 | Y96: Activa | Z96: repbiofarco | AA96: dispositivosbiofarco@gmail.com
A97: 79ec5a99 | B97: Farmadia Fundación Mendoza "Farmacia San Pedro" | C97: J-30179207-6 | D97: C.C. Fundación Mendoza, Local 1 y 7, Urb. La Fundación Mendoza | E97: MCY | F97: Fuerzas Aereas | G97: ARA | H97: 3 | I97: 0243-2358972 | J97: dispositivosbiofarco@gmail.com | K97: 0243-2358972 | M97: farmacialafundacion@hotmail.com | Q97: Independiente | R97: Bajo | U97: TRUE | W97: @F_FarmaDia | X97: 45981.819 | Y97: Activa | Z97: repbiofarco | AA97: dispositivosbiofarco@gmail.com
A98: 0c65c6ca | B98: Farma Emergencia | C98: J-50137868-1 | D98: Hospital Central de Maracay | E98: MCY | F98: La Delicias | G98: ARA | H98: 1 | I98: 0414-4480577 | J98: dispositivosbiofarco@gmail.com | K98: 0414-4480577 | L98: Raizelys Suarez | Q98: Mini Cadena | U98: TRUE | W98: @farma_emergencia | X98: 45981.925 | Y98: Activa | Z98: repbiofarco | AA98: dispositivosbiofarco@gmail.com
A99: 1f6ac248 | B99: Farmacia SAAS Galería Plaza | C99: J-50077240-8 | D99: Av. Bolívar, Maracay 2103, Aragua, Venezuela | E99: MCY | F99: Centro | G99: ARA | I99: 0424-3530268 | J99: dispositivosbiofarco@gmail.com | K99: 0424-3530268 | L99: María Fernanda | Q99: Cadena | U99: TRUE | W99: @saas_galeriaplaza | X99: 45981.944 | Y99: Activa | Z99: repbiofarco | AA99: dispositivosbiofarco@gmail.com
A100: 91b26bae | B100: Locatel Los Aviadores | C100: J-50202212-0 | D100: Av los Aviadores CC Parque los Aviadores, Palo Negro 2117, Aragua, Venezuela | E100: PLN | F100: C.C. Aviadores | G100: ARA | J100: dispositivosbiofarco@gmail.com | K100: 0426-5193139 | L100: Tahiri Carpio | Q100: Cadena | U100: TRUE | X100: 45930 | Y100: Activa | Z100: repbiofarco | AA100: dispositivosbiofarco@gmail.com
...

Sheet ContactosClave
A1: ID_Contacto | B1: ID_Farmacia | C1: NombreContacto | D1: RolEnFarmacia | E1: Telefono | F1: Email | G1: ID_Usuario | H1: SUBMITTED BY
G2: repbiofarco | H2: dispositivosbiofarco@gmail.com
A3: 2 | B3: 2 | C3: Dra. Angelica Pérez | E3: 0414-3434641 | G3: repbiofarco | H3: dispositivosbiofarco@gmail.com
A4: 3 | B4: 3 | C4: Dr. Vidal Ruiz | E4: 0424-3388016 | F4: farmaciallasdelicias@locatelve.com | G4: repbiofarco | H4: dispositivosbiofarco@gmail.com
G5: repbiofarco | H5: dispositivosbiofarco@gmail.com
A6: 5 | B6: 5 | E6: 0412-9975205 | G6: repbiofarco | H6: dispositivosbiofarco@gmail.com
G7: repbiofarco | H7: dispositivosbiofarco@gmail.com
G8: repbiofarco | H8: dispositivosbiofarco@gmail.com
A9: 8 | B9: 8 | G9: repbiofarco | H9: dispositivosbiofarco@gmail.com
G10: repbiofarco | H10: dispositivosbiofarco@gmail.com
G11: repbiofarco | H11: dispositivosbiofarco@gmail.com
G12: repbiofarco | H12: dispositivosbiofarco@gmail.com
A13: 12 | B13: 12 | G13: repbiofarco | H13: dispositivosbiofarco@gmail.com
A14: 13 | B14: 13 | G14: repbiofarco | H14: dispositivosbiofarco@gmail.com
A15: 14 | B15: 14 | G15: repbiofarco | H15: dispositivosbiofarco@gmail.com
G16: repbiofarco | H16: dispositivosbiofarco@gmail.com
A17: 16 | B17: 16 | G17: repbiofarco | H17: dispositivosbiofarco@gmail.com
A18: 17 | B18: 17 | C18: Ana Matute | E18: 0414-1479994 | F18: farmaciagranviamcy@gmail.com | G18: repbiofarco | H18: dispositivosbiofarco@gmail.com
G19: repbiofarco | H19: dispositivosbiofarco@gmail.com
A20: 19 | B20: 19 | E20: 0414-4454909 | G20: repbiofarco | H20: dispositivosbiofarco@gmail.com
A21: 20 | B21: 20 | G21: repbiofarco | H21: dispositivosbiofarco@gmail.com
A22: 21 | B22: 21 | G22: repbiofarco | H22: dispositivosbiofarco@gmail.com
A23: 22 | B23: 22 | C23: Rubexi Magallanes | E23: 0412-398327 | G23: repbiofarco | H23: dispositivosbiofarco@gmail.com
G24: repbiofarco | H24: dispositivosbiofarco@gmail.com
G25: repbiofarco | H25: dispositivosbiofarco@gmail.com
A26: 25 | B26: 25 | G26: repbiofarco | H26: dispositivosbiofarco@gmail.com
A27: 26 | B27: 26 | G27: repbiofarco | H27: dispositivosbiofarco@gmail.com
G28: repbiofarco | H28: dispositivosbiofarco@gmail.com
A29: 28 | B29: 28 | G29: repbiofarco | H29: dispositivosbiofarco@gmail.com
A30: 29 | B30: 29 | G30: repbiofarco | H30: dispositivosbiofarco@gmail.com
G31: repbiofarco | H31: dispositivosbiofarco@gmail.com
G32: repbiofarco | H32: dispositivosbiofarco@gmail.com
A33: 32 | B33: 32 | G33: repbiofarco | H33: dispositivosbiofarco@gmail.com
A34: 33 | B34: 33 | G34: repbiofarco | H34: dispositivosbiofarco@gmail.com
G35: repbiofarco | H35: dispositivosbiofarco@gmail.com
G36: repbiofarco | H36: dispositivosbiofarco@gmail.com
A37: 36 | B37: 36 | G37: repbiofarco | H37: dispositivosbiofarco@gmail.com
A38: 37 | B38: 37 | G38: repbiofarco | H38: dispositivosbiofarco@gmail.com
G39: repbiofarco | H39: dispositivosbiofarco@gmail.com
G40: repbiofarco | H40: dispositivosbiofarco@gmail.com
G41: repbiofarco | H41: dispositivosbiofarco@gmail.com
G42: repbiofarco | H42: dispositivosbiofarco@gmail.com
G43: repbiofarco | H43: dispositivosbiofarco@gmail.com
G44: repbiofarco | H44: dispositivosbiofarco@gmail.com
G45: repbiofarco | H45: dispositivosbiofarco@gmail.com
A46: 45 | B46: 46 | G46: repbiofarco | H46: dispositivosbiofarco@gmail.com
A47: 46 | B47: 47 | G47: repbiofarco | H47: dispositivosbiofarco@gmail.com
A48: 47 | B48: 48 | C48: Alejandra Franco | E48: 0412-4660774 | G48: repbiofarco | H48: dispositivosbiofarco@gmail.com
A49: 48 | B49: 50 | C49: Briscarlet Romero | E49: 0424-3774424 | G49: repbiofarco | H49: dispositivosbiofarco@gmail.com
A50: 49 | B50: 51 | C50: Geisy | E50: 0412-1443505 | G50: repbiofarco | H50: dispositivosbiofarco@gmail.com
A51: 50 | B51: 52 | C51: Helecky | E51: 0424-3612060 | G51: repbiofarco | H51: dispositivosbiofarco@gmail.com
A52: 51 | B52: 53 | C52: Dulce García | E52: 0424-3053065 | G52: repbiofarco | H52: dispositivosbiofarco@gmail.com
A53: 52 | B53: 54 | C53: Jenxy | E53: 0412-4427134 | G53: repbiofarco | H53: dispositivosbiofarco@gmail.com
A54: 53 | B54: 55 | C54: Pedro Bravo | E54: 0424-3448938 | G54: repbiofarco | H54: dispositivosbiofarco@gmail.com
A55: 54 | B55: 56 | C55: Dilimary | E55: 0424-3533959 | F55: farmavitalmaracay@gmail.com | G55: repbiofarco | H55: dispositivosbiofarco@gmail.com
A56: 55 | B56: 57 | C56: Kariana Alfonso | E56: 0424-3074961 | G56: repbiofarco | H56: dispositivosbiofarco@gmail.com
A57: 56 | B57: 65 | C57: Andrea Gutierrez | E57: 0412-5979880 | G57: repbiofarco | H57: dispositivosbiofarco@gmail.com
A58: 57 | B58: 66 | C58: Yasmin | E58: 0412-3982006 | G58: repbiofarco | H58: dispositivosbiofarco@gmail.com
A59: 58 | B59: 67 | C59: Jose Torres | E59: 0414-5340201 | G59: repbiofarco | H59: dispositivosbiofarco@gmail.com
A60: 59 | B60: 69 | C60: Deisy Zar | E60: 0414-9479464 | G60: repbiofarco | H60: dispositivosbiofarco@gmail.com
A61: 60 | B61: 70 | C61: Fatima Fernandez | E61: 0414-4636195 | G61: repbiofarco | H61: dispositivosbiofarco@gmail.com
A62: 61 | B62: 71 | C62: Veronica Olmos | E62: 0414-4907867 | G62: repbiofarco | H62: dispositivosbiofarco@gmail.com
A63: 62 | B63: 72 | C63: Carolina | E63: 0424-3680773 | G63: repbiofarco | H63: dispositivosbiofarco@gmail.com
A64: 63 | B64: 73 | C64: Lcdo. Jose Narval | E64: 0412-9932540 | G64: repbiofarco | H64: dispositivosbiofarco@gmail.com
G65: repbiofarco | H65: dispositivosbiofarco@gmail.com
A66: 65 | B66: 75 | C66: Katy | E66: 0412-8686043 | G66: repbiofarco | H66: dispositivosbiofarco@gmail.com
G67: repbiofarco | H67: dispositivosbiofarco@gmail.com
G68: repbiofarco | H68: dispositivosbiofarco@gmail.com
A69: 68 | B69: 80 | C69: Odeisa Olmedo | E69: 0414-4749193 | G69: repbiofarco | H69: dispositivosbiofarco@gmail.com
A70: 69 | B70: 81 | C70: Wilberky | E70: 0412-8954493 | G70: repbiofarco | H70: dispositivosbiofarco@gmail.com
A71: 70 | B71: 83 | C71: Luis | E71: 0414-4430816 | G71: repbiofarco | H71: dispositivosbiofarco@gmail.com
A72: 71 | B72: 84 | C72: Yepyiza | E72: 0426-1453117 | G72: repbiofarco | H72: dispositivosbiofarco@gmail.com
A73: 72 | B73: 85 | E73: 0424-3482385 | G73: repbiofarco | H73: dispositivosbiofarco@gmail.com
A74: 73 | B74: 90 | C74: Pablo Segundo | E74: 0414-5905389 | G74: repbiofarco | H74: dispositivosbiofarco@gmail.com
G75: repbiofarco | H75: dispositivosbiofarco@gmail.com
A76: 75 | B76: 93 | C76: Aikon | E76: 0414-4906644 | G76: repbiofarco | H76: dispositivosbiofarco@gmail.com
A77: 76 | B77: 94 | C77: Norielkis Rovachevich | E77: 0414-5988540 | G77: repbiofarco | H77: dispositivosbiofarco@gmail.com
G78: repbiofarco | H78: dispositivosbiofarco@gmail.com
A79: 78 | B79: 96 | C79: Emily Nuñez | E79: 0424-3089344 | G79: repbiofarco | H79: dispositivosbiofarco@gmail.com
A80: 79 | B80: 97 | G80: repbiofarco | H80: dispositivosbiofarco@gmail.com
A81: 80 | B81: 98 | E81: 0424-4242233 | F81: dlsaragua@gmail.com | G81: repbiofarco | H81: dispositivosbiofarco@gmail.com
G82: repbiofarco | H82: dispositivosbiofarco@gmail.com
A83: 82 | B83: 2f00830e | C83: Dra. Tahaimy Blanco | E83: 0424-3460625 | G83: repbiofarco | H83: dispositivosbiofarco@gmail.com
A84: 83 | B84: 67a0121b | C84: Elvis | E84: 0414-0483164 | G84: repbiofarco | H84: dispositivosbiofarco@gmail.com
A85: 84 | B85: 6d5f7cb2 | C85: Ramón Martínez | E85: 04243113763 | G85: repbiofarco | H85: dispositivosbiofarco@gmail.com
A86: 85 | B86: 99 | G86: repbiofarco | H86: dispositivosbiofarco@gmail.com
A87: 86 | B87: 100 | G87: repbiofarco | H87: dispositivosbiofarco@gmail.com
A88: 87 | B88: 101 | G88: repbiofarco | H88: dispositivosbiofarco@gmail.com
A89: 88 | B89: 102 | C89: Dra. Loira Fonseca | E89: 0424-3793446 | G89: repbiofarco | H89: dispositivosbiofarco@gmail.com
A90: 89 | B90: 103 | G90: repbiofarco | H90: dispositivosbiofarco@gmail.com
A91: 90 | B91: 18ea49b4 | C91: José Sulbarán | E91: 0412-9883919 | G91: repbiofarco | H91: dispositivosbiofarco@gmail.com
A92: 91 | B92: af0758a4 | C92: Joselin | E92: 0424-3505639 | G92: repbiofarco | H92: dispositivosbiofarco@gmail.com
A93: 92 | B93: af0758a5 | C93: Pedro Ramírez | E93: 0412-4345095 | F93: farmaciaboulebardpaez@gmail.com | G93: repbiofarco | H93: dispositivosbiofarco@gmail.com
A94: 93 | B94: c3aaef31 | C94: María Gabriela Yamour | E94: 0412-2805515 | F94: farmaciasfarmed@gmail.com | G94: repbiofarco | H94: dispositivosbiofarco@gmail.com
A95: 94 | B95: 110 | G95: repbiofarco | H95: dispositivosbiofarco@gmail.com
A96: 95 | B96: 111 | G96: repbiofarco | H96: dispositivosbiofarco@gmail.com
A97: 96 | B97: 112 | G97: repbiofarco | H97: dispositivosbiofarco@gmail.com
A98: 97 | B98: 113 | G98: repbiofarco | H98: dispositivosbiofarco@gmail.com
A99: 98 | B99: 115 | F99: farmacia.coromotofarco@gmail.com | G99: repbiofarco | H99: dispositivosbiofarco@gmail.com
A100: 99 | B100: 116 | G100: repbiofarco | H100: dispositivosbiofarco@gmail.com
...

Sheet Fichero Farmacias
A1: ID_Farmacia | B1: Nombre | C1: RIF | D1: Ciudad | E1: Estado | F1: Productos Promocionados | G1: Dirección | H1: Sector | I1: Teléfono | J1: Teléfono Contacto | K1: Contacto | L1: Email | M1: Horario | N1: Producto_Interes | O1: Acción de Seguimiento | P1: Producto Existente | Q1: Cantidad | R1: Drogueria | S1: Prioridad | T1: Horario_Atención | U1: Instagram | V1: Última_Visita | W1: ID_Usuario | X1: SUBMITTED BY
A2: 1 | B2: Farmacia Mas x Menos | C2: 0414-3434641 | D2: Maracay | E2: Aragua | F2: Limonada Laxante , Zincosol , Fleryfol , NeuroVital Kids , Acetafen , Calzinc D , Vitacon C | G2: Automercado Más x Menos C.C. Maracay Plaza | H2: Av. Bermudez Sur | I2: 0414-3434641 | J2: 0414-3434641 | K2: Dra. Angelica Pérez | O2: Visitar para coodinar con la Dra. Angelica Perez regente de la farmacia | Q2: 1 | S2: Media | T2: 0.54166667 | V2: 45779 | W2: repbiofarco | X2: dispositivosbiofarco@gmail.com
A3: 2 | B3: Locatel Las Delicias | C3: J-50202212-0 | D3: Maracay | E3: Aragua | G3: La Floresta, Maracay | H3: Las Delicias | J3: 0424-3388016 | K3: Dr. Vidal Ruiz | L3: farmaciallasdelicias@locatel.com | W3: repbiofarco | X3: dispositivosbiofarco@gmail.com
A4: 3 | B4: Farma Salud | C4: 0424-3388016 | D4: Maracay | E4: Aragua | G4: Av. Jose Maria Vargas, La Floresta | H4: La Floresta | J4: 0414-3456070 | K4: Anni Suárez | S4: Alta | V4: 45803 | W4: repbiofarco | X4: dispositivosbiofarco@gmail.com
A5: 4 | B5: Farmacia Farmadía | C5: 0414-3456070 | D5: Maracay | E5: Aragua | G5: El Piñonal, Maracay | H5: El Piñonal | I5: 0414-0471853 | W5: repbiofarco | X5: dispositivosbiofarco@gmail.com
A6: 5 | B6: Farmacia Gran Vía | C6: J-07509720-3 | D6: Maracay | E6: Aragua | G6: 70 Av. Miranda, Maracay 2101, Aragua, Venezuela | H6: El Carmen | I6: 0243-2335512 | J6: 0414-1479994 | K6: Ana Matute | L6: farmaciagranviamcy@gmail.com | O6: TRUE | S6: Baja | V6: 45785 | W6: repbiofarco | X6: dispositivosbiofarco@gmail.com
A7: 6 | B7: Farmacia Lincoln | C7: J-30296726-4 | D7: Maracay | E7: Aragua | G7: Av. Bolívar, Maracay, Aragua, Venezuela | H7: Centro | I7: 0414-5880833 | J7: 0412-398327 | K7: Rubexi Magallanes | O7: TRUE | S7: Media | U7: @farmacialincoln | V7: 45806 | W7: repbiofarco | X7: dispositivosbiofarco@gmail.com
A8: 7 | B8: Farmacia LaFarma C.C. Las Américas | C8: J-31116593-2 | D8: Maracay | E8: Aragua | G8: Avenida Las Delicias, Maracay 2101, Aragua, Venezuela | H8: Las Delicias | I8: 0412-4660774 | J8: 0412-4660774 | K8: Alejandra Franco | O8: TRUE | S8: Media | U8: @lafarmacclasamericas | V8: 45806 | W8: repbiofarco | X8: dispositivosbiofarco@gmail.com
A9: 8 | B9: Farmacia SAAS Av. Los Aviadores | C9: J-50265214-0 | D9: Palo Negro | E9: Aragua | G9: Av. Los Aviadores, Palo Negro, Maracay, Edo. Aragua. | H9: Av. Los Aviadores | I9: 0424-3080504 | J9: 0424-3774424 | K9: Briscarlet Romero | U9: @farmaciasaas_aviadores | W9: repbiofarco | X9: dispositivosbiofarco@gmail.com
A10: 9 | B10: Farmacia El Sol | C10: 0412-1443505 | D10: Maracay | E10: Aragua | G10: Local 1, C.C Hormiga Center, Av Bolivar, Nivel 1 Calle Sanchez Carrero, Maracay 2101, Aragua | H10: C.C. Hormiga Center | I10: 0412-1443505 | J10: 0412-1443505 | K10: Geisy | W10: repbiofarco | X10: dispositivosbiofarco@gmail.com
A11: 10 | B11: Farmacia El Sol II | C11: 0424-3612060 | D11: Maracay | E11: Aragua | G11: Local #58, Av Miranda, 2101 Calle Sanchez Carrero, Maracay 2101, Aragua | H11: Av Miranda | I11: 0424-3612060 | J11: 0424-3612060 | K11: Helecky | W11: repbiofarco | X11: dispositivosbiofarco@gmail.com
A12: 11 | B12: Farmacia SAAS Las Delicias | C12: J-07000750-8 | D12: Maracay | E12: Aragua | G12: 8C6Q+PXF, Av Principal El Castaño, Maracay 2101, Aragua, Venezuela | H12: Delicias | I12: 0424-3823338 | J12: 0424-3053065 | K12: Dulce García | S12: Alta | T12: 0.33333333 | U12: @saasav.lasdelicias | V12: 45824 | W12: repbiofarco | X12: dispositivosbiofarco@gmail.com
A13: 12 | B13: Farma Vital El Limón | C13: 0414-0531788 | D13: Maracay | E13: Aragua | G13: Av. Universidad | H13: El Limón | I13: 0414-0531788 | J13: 0412-4427134 | K13: Jenxy | W13: repbiofarco | X13: dispositivosbiofarco@gmail.com
A14: 13 | B14: Farma Vital Terminal Central | C14: 0414-4751430 | D14: Maracay | E14: Aragua | G14: Terminal de Pasajeros | H14: Terminal | I14: 0414-4751430 | J14: 0424-3448938 | K14: Pedro Bravo | W14: repbiofarco | X14: dispositivosbiofarco@gmail.com
A15: 14 | B15: Farma Vital 19 de Abril | C15: 0412-8948596 | D15: Maracay | E15: Aragua | G15: Diagonal Clinica Lugo, C.C Vista Lago, Avenida 19 de Abril, Maracay 2101, Aragua | H15: 19 de Abril | I15: 0412-8948596 | J15: 0424-3533959 | K15: Dilimary | L15: farmavitalmaracay@gmail.com | W15: repbiofarco | X15: dispositivosbiofarco@gmail.com
A16: 15 | B16: Farma Vital Campo Alegre | C16: J-31072776-7 | D16: Maracay | E16: Aragua | G16: Av. Bermudez, Maracay 2103, Aragua, Venezuela | H16: Sur de Aragua | I16: 0412-4837874 | J16: 0424-3074961 | K16: Kariana Alfonso | O16: TRUE | S16: Media | V16: 45782 | W16: repbiofarco | X16: dispositivosbiofarco@gmail.com
A17: 16 | B17: Distufar Av. Bermudez | C17: 0412-5979880 | E17: Aragua | I17: 0412-5979880 | J17: 0412-5979880 | K17: Andrea Gutierrez | W17: repbiofarco | X17: dispositivosbiofarco@gmail.com
A18: 17 | B18: Distufar Santa Ines | C18: 0412-3982006 | E18: Aragua | I18: 0412-3982006 | J18: 0412-3982006 | K18: Yasmin | W18: repbiofarco | X18: dispositivosbiofarco@gmail.com
A19: 18 | B19: Farmacia La Ganadera | C19: J-4028240-9 | D19: Maracay | E19: Aragua | G19: Av. Constitución, Maracay, Aragua, Venezuela | H19: Santa Rosa | I19: 0414-1518972 | J19: 0414-5340201 | K19: Jose Torres | O19: TRUE | S19: Media | U19: @farmacia_la_ganadera | V19: 45828 | W19: repbiofarco | X19: dispositivosbiofarco@gmail.com
A20: 19 | B20: Farma Milán Santa Rita | C20: 0414-9479464 | E20: Aragua | I20: 0414-9479464 | J20: 0414-9479464 | K20: Deisy Zar | W20: repbiofarco | X20: dispositivosbiofarco@gmail.com
A21: 20 | B21: Farma Milán La Morita | C21: 0414-4636195 | E21: Aragua | I21: 0414-4636195 | J21: 0414-4636195 | K21: Fatima Fernandez | W21: repbiofarco | X21: dispositivosbiofarco@gmail.com
A22: 21 | B22: Farmacia Farma Store | C22: 0414-4907867 | E22: Aragua | I22: 0414-4907867 | J22: 0414-4907867 | K22: Veronica Olmos | W22: repbiofarco | X22: dispositivosbiofarco@gmail.com
A23: 22 | B23: Farmacia Policlínico | C23: 0424-3680773 | E23: Aragua | I23: 0424-3680773 | J23: 0424-3680773 | K23: Carolina | W23: repbiofarco | X23: dispositivosbiofarco@gmail.com
A24: 23 | B24: Farmacia Central 19 | C24: 0412-9932540 | E24: Aragua | I24: 0412-9932540 | J24: 0412-9932540 | K24: Lcdo. Jose Narval | W24: repbiofarco | X24: dispositivosbiofarco@gmail.com
A25: 24 | B25: Farmacia Fartodo Amor, Salud y Vida | C25: 0424-3245936 | E25: Aragua | I25: 0424-3245936 | J25: 0424-3245936 | K25: Jhony | W25: repbiofarco | X25: dispositivosbiofarco@gmail.com
A26: 25 | B26: Farmacia Farma Vista | C26: 0412-8686043 | E26: Aragua | I26: 0412-8686043 | J26: 0412-8686043 | K26: Katy | W26: repbiofarco | X26: dispositivosbiofarco@gmail.com
A27: 26 | B27: Farmacia Farma Health | C27: 0414-4894502 | E27: Aragua | I27: 0414-4894502 | J27: 0414-4894502 | K27: Indira Infante | W27: repbiofarco | X27: dispositivosbiofarco@gmail.com
A28: 27 | B28: Farmacia Social El Gran Descuento | C28: 0414-4344133 | E28: Aragua | I28: 0414-4344133 | J28: 0414-4344133 | K28: Lisbeth Darchart | W28: repbiofarco | X28: dispositivosbiofarco@gmail.com
A29: 28 | B29: Farmacia Las Mercedes | C29: 0414-4749193 | E29: Aragua | I29: 0414-4749193 | J29: 0414-4749193 | K29: Odeisa Olmedo | W29: repbiofarco | X29: dispositivosbiofarco@gmail.com
A30: 29 | B30: Farmacia Bendición Sucre | C30: 0412-8954493 | E30: Aragua | I30: 0412-8954493 | J30: 0412-8954493 | K30: Wilberky | W30: repbiofarco | X30: dispositivosbiofarco@gmail.com
A31: 30 | B31: Farmacia Far Centro | C31: 0414-4430816 | E31: Aragua | I31: 0414-4430816 | J31: 0414-4430816 | K31: Luis | W31: repbiofarco | X31: dispositivosbiofarco@gmail.com
A32: 31 | B32: Farmacia María de San José | C32: 0426-1453117 | E32: Aragua | I32: 0426-1453117 | J32: 0426-1453117 | K32: Yepyiza | W32: repbiofarco | X32: dispositivosbiofarco@gmail.com
A33: 32 | B33: Farmacia Santa Inés | C33: 0424-3482385 | E33: Aragua | I33: 0424-3482385 | J33: 0424-3482385 | W33: repbiofarco | X33: dispositivosbiofarco@gmail.com
A34: 33 | B34: Farmacia Jose Gregorio Hernandez | C34: 0414-5905389 | E34: Aragua | I34: 0414-5905389 | J34: 0414-5905389 | K34: Pablo Segundo | W34: repbiofarco | X34: dispositivosbiofarco@gmail.com
A35: 34 | B35: Farmacia VIP | C35: 0414-4591967 | E35: Aragua | I35: 0414-4591967 | J35: 0414-4591967 | K35: Genesis Mendez | W35: repbiofarco | X35: dispositivosbiofarco@gmail.com
A36: 35 | B36: Farma VIP Administración | C36: 0414-4906644 | E36: Aragua | I36: 0414-4906644 | J36: 0414-4906644 | K36: Aikon | W36: repbiofarco | X36: dispositivosbiofarco@gmail.com
A37: 36 | B37: FarmaBallenas | D37: Maracay | E37: Aragua | G37: IPSFA Av. Bolívar Este, Maracay 2101, Aragua, Venezuela | H37: IPSFA | W37: repbiofarco | X37: dispositivosbiofarco@gmail.com
A38: 37 | B38: Farmacia SAAS San José | D38: Maracay | E38: Aragua | F38: Limonada Laxante , Zincosol , Fleryfol , NeuroVital Kids , Acetafen , Calzinc D , Vitacon C , Emulsión , NeutroX , Leche de Magnesia Original , Leche de Magnesia Menta , Calamina , Citrato de Potasio , Cloruro de Magnesio | G38: C. San José, Esquina Este del IVSS. Maracay 2103, Aragua, Venezuela | H38: IVSS San José | O38: Visita mensual | W38: repbiofarco | X38: dispositivosbiofarco@gmail.com
A39: 38 | B39: Farmacia SAAS Maracay Plaza | C39: 0412-8905442 | D39: Maracay | E39: Aragua | G39: Av Aragua C/ Av Bermudez C.C. Maracay Plaza Nivel PB LOCAL 45C Y | H39: C.C. Maracay Plaza | I39: 0412-8905442 | J39: 0424-3089344 | K39: Emily Nuñez | W39: repbiofarco | X39: dispositivosbiofarco@gmail.com
A40: 39 | B40: Farmatodo Cristal | C40: 0243-2157912 | D40: Maracay | E40: Aragua | G40: Urb San Carlos entre Av Los Samanes y Av. Fuerzas Aereas | H40: Av. Fuerzas Aéreas Sur | I40: 0243-2157912 | S40: Alta | W40: repbiofarco | X40: dispositivosbiofarco@gmail.com
A41: 40 | B41: DLS Medical Aragua | C41: J506176203 | D41: Maracay | E41: Aragua | F41: Zincosol , Fleryfol , NeuroVital Kids , Acetafen , Calzinc D , Vitacon C , Emulsión , NeutroX , Leche de Magnesia Original , Leche de Magnesia Menta | G41: Av. 19 de Abril, Maracay 2101, Aragua, Venezuela | H41: La maestranza | I41: 04244242233 | J41: 04244242233 | L41: dlsaragua@gmail.com | M41: 7am | O41: Monitorear | S41: Media | T41: 0.33958333 | V41: 45797 | W41: repbiofarco | X41: dispositivosbiofarco@gmail.com
A42: 41 | B42: Farmacia Cedro | C42: J-00020200-1 | D42: Maracay | E42: Aragua | F42: Limonada Laxante , Zincosol , Fleryfol , NeuroVital Kids , Acetafen , Calzinc D , Vitacon C , Emulsión , NeutroX , Leche de Magnesia Original , Leche de Magnesia Menta , Calamina , Citrato de Potasio , Cloruro de Magnesio | G42: La Soledad Calle 2 con Avenida 4 Manzana J | H42: La Soledad | M42: 24 horas | P42: a4d65f49 | Q42: 3 | S42: Alta | V42: 45805 | W42: repbiofarco | X42: dispositivosbiofarco@gmail.com
A43: 42 | B43: Farmacia Farma Vero II | C43: 0424-3240664 | D43: Maracay | E43: Aragua | F43: Limonada Laxante , Fleryfol , NeuroVital Kids , Acetafen , Calzinc D , Vitacon C , Emulsión , Calamina , Citrato de Potasio , Cloruro de Magnesio | H43: La Soledad | I43: 0424-3240664 | J43: 0424-3460625 | K43: Dra. Tahaimy Blanco | S43: Media | T43: 0.33333333 | V43: 45805 | W43: repbiofarco | X43: dispositivosbiofarco@gmail.com
A44: 43 | B44: FarmaSol Santos Michelena II | C44: J-50564708-3 | D44: Maracay | E44: Aragua | G44: Calle Santos Michelena, Maracay 2101, Aragua, Venezuela | H44: Centro | I44: 0424-3043832 | J44: 0414-0483164 | K44: Elvis | O44: TRUE | S44: Media | U44: @farmasol_ve | V44: 45804 | W44: repbiofarco | X44: dispositivosbiofarco@gmail.com
A45: 44 | B45: Farmacia Farmadito | C45: 04243113763 | D45: Maracay | E45: Aragua | G45: Urb. Calicanto, Maracay, Aragua, Venezuela | H45: Urb. Calicanto | I45: 04243113763 | J45: 04243113763 | K45: Ramón Martínez | S45: Media | W45: repbiofarco | X45: dispositivosbiofarco@gmail.com
A46: 45 | B46: Farmatodo Umbral | D46: Maracay | E46: Aragua | G46: AV PPAL LAS DELICIAS CALLE VICENTE LECUNA C/CALLE JUAN V. GONZALEZ ZONA COMERC 1 | H46: Las Delicias | S46: Alta | W46: repbiofarco | X46: dispositivosbiofarco@gmail.com
A47: 46 | B47: Farmatodo Araguaney | D47: Maracay | E47: Aragua | G47: Cc Unicentro Maracay, Nivel Pb, Locales Pb-33, Pb-34, Pb-35, Pb-36 Y Pb-37 | H47: Base Aragua | S47: Alta | W47: repbiofarco | X47: dispositivosbiofarco@gmail.com
A48: 47 | B48: Farmatodo Gregorio | D48: Maracay | E48: Aragua | G48: Av Bermudez, Jurisdicción del Municipio Maracay, Distrito Girardot | H48: Av. Bermúdez | S48: Alta | W48: repbiofarco | X48: dispositivosbiofarco@gmail.com
A49: 48 | B49: Farmatodo Daysi | D49: Maracay | E49: Aragua | G49: Calle Mariño con Calle Páez Sector Centro Sur Oeste III Municipio Girardot | H49: Centro | J49: 0424-3793446 | K49: Dra. Loira Fonseca | O49: TRUE | S49: Alta | W49: repbiofarco | X49: dispositivosbiofarco@gmail.com
A50: 49 | B50: Farmatodo Cedro | D50: Maracay | E50: Aragua | G50: CALLE 2 C/4TA AV. MANZANA J LOCAL 1 LA SOLEDAD | H50: Las Delicias | S50: Alta | W50: repbiofarco | X50: dispositivosbiofarco@gmail.com
A51: 50 | B51: Farmacial Real 2020 | C51: J-50246703-3 | D51: Maracay | E51: Aragua | F51: Limonada Laxante , Zincosol , Fleryfol , NeuroVital Kids , Acetafen , Calzinc D , Vitacon C , Emulsión , NeutroX , Leche de Magnesia Original , Leche de Magnesia Menta , Calamina , Citrato de Potasio , Cloruro de Magnesio | G51: Av. Casanova Godoy Cruce en la Funeraria Valles en las instalaciones del CAFMA, al frente de la emergencia del Hospital Militar Cnel. Elbano Paredes Vivas | H51: La Barraca | I51: 0243-2337072 | J51: 0412-9883919 | K51: José Sulbarán | M51: L - V | O51: TRUE | S51: Media | T51: 0.33333333 | U51: @farmaciareal2022 | V51: 45790 | W51: repbiofarco | X51: dispositivosbiofarco@gmail.com
A52: 51 | B52: Farmacia Diga Center, C.A. | C52: J-30015410-5 | D52: Maracay | E52: Aragua | F52: Limonada Laxante , Zincosol , Fleryfol , NeuroVital Kids , Acetafen , Calzinc D , Vitacon C , Emulsión , NeutroX , Leche de Magnesia Original , Leche de Magnesia Menta , Calamina , Citrato de Potasio , Cloruro de Magnesio | G52: AV. DR. MONTOYA CC DIGA CENTER SEGUNDA ETAPA NIVEL 2 LOCAL L35 L36 SECTOR, Turmero 2115, Aragua, Venezuela | H52: Linares Alcantara | I52: 0243-2694066 | J52: 0424-3505639 | K52: Joselin | O52: Si | S52: Media | T52: 0.33333333 | V52: 45828 | W52: repbiofarco | X52: dispositivosbiofarco@gmail.com
A53: 52 | B53: Farmacia SAAS Boulevvart Páez | C53: J-40254084-1 | D53: Maracay | E53: Aragua | G53: C. Paez, Maracay, Aragua, Venezuela | H53: Centro | I53: 0412-0319636 | J53: 0412-4345095 | K53: Pedro Ramírez | L53: farmaciaboulebardpaez@gmail.com | O53: TRUE | S53: Baja | U53: @saasmaracay | V53: 45791 | W53: repbiofarco | X53: dispositivosbiofarco@gmail.com
A54: 53 | B54: Farmacias Multimed, C.A. | C54: J-50366838-5 | D54: Maracay | E54: Aragua | F54: Limonada Laxante , Zincosol , Fleryfol , NeuroVital Kids , Acetafen , Calzinc D , Vitacon C , Emulsión , NeutroX , Leche de Magnesia Original , Leche de Magnesia Menta , Calamina , Citrato de Potasio , Cloruro de Magnesio | G54: Av. 19 de Abril, Maracay 2101, Aragua, Venezuela | H54: Centro | J54: 0412-2805515 | K54: María Gabriela Yamour | L54: farmaciasfarmed@gmail.com | M54: L-V | O54: TRUE | S54: Media | T54: 0.29166667 | U54: @farmaciasmultimed.ve | V54: 45805 | W54: repbiofarco | X54: dispositivosbiofarco@gmail.com
A55: 54 | B55: Farma Vital Caña de Azucar | C55: 0424-3537172 | D55: Maracay | E55: Aragua | G55: 2101, Maracay 2101, Aragua | H55: Caña de Azucar | I55: 0424-3537172 | W55: repbiofarco | X55: dispositivosbiofarco@gmail.com
A56: 55 | B56: Farma Vital Los Olivos | C56: 0424-3065450 | D56: Maracay | E56: Aragua | G56: Los Olivos | H56: Terminal | I56: 0424-3065450 | W56: repbiofarco | X56: dispositivosbiofarco@gmail.com
A57: 56 | B57: Farma Vital Al Kosto | D57: Maracay | E57: Aragua | G57: 6CC7+6F8, Maracay 2103, Aragua | H57: Jose Gregorio | W57: repbiofarco | X57: dispositivosbiofarco@gmail.com
A58: 57 | B58: Farma Vital Rosario de Paya | C58: 0424-3447303 | D58: Turmero | E58: Aragua | G58: Granja el Naranjal, Av. Ppal Rosario de Paya. C.C Valle de Paya. Sector, Turmero 2115, Aragua | H58: Rosario de Paya | I58: 0424-3447303 | W58: repbiofarco | X58: dispositivosbiofarco@gmail.com
A59: 58 | B59: Farma Vital Coromoto Farco | C59: 0412-4427131 | D59: Maracay | E59: Aragua | G59: Av. Ayacucho, con Av. Miranda, Maracay 2103, Aragua | H59: Centro | I59: 0412-4427131 | L59: farmacia.coromotofarco@gmail.com | W59: repbiofarco | X59: dispositivosbiofarco@gmail.com
A60: 59 | B60: Farma Vital Centro JV | C60: 0424-3730080 | D60: Palo Negro | E60: Aragua | G60: 5FC3+85R, C. Girardot, Palo Negro 2117, Aragua | H60: Centro | I60: 0424-3730080 | W60: repbiofarco | X60: dispositivosbiofarco@gmail.com
A61: 60 | B61: Farma Vital 23 de Enero | C61: 0424-3730070 | D61: Maracay | E61: Aragua | G61: Calle luisa caceres cruce con, local nro 33 Calle Infantil, Maracay 2104, Aragua | H61: 23 de Enero | I61: 0424-3730070 | W61: repbiofarco | X61: dispositivosbiofarco@gmail.com
A62: 61 | B62: Farma Vital Santa Rita | C62: 0424-3097024 | D62: Santa Rita | E62: Aragua | G62: CASA NRO 364 SECTOR Av. Francisco de Miranda, Santa Rita 2103, Aragua | H62: Francisco de MIranda | I62: 0424-3097024 | W62: repbiofarco | X62: dispositivosbiofarco@gmail.com
A63: 62 | B63: Farma Vital Piñonal | C63: 0424-3572026 | D63: Maracay | E63: Aragua | G63: Av. Los Chaguaramos. Calle 15. Barrio San José, Maracay 2103, Aragua | H63: San José | I63: 0424-3572026 | W63: repbiofarco | X63: dispositivosbiofarco@gmail.com
A64: 63 | B64: Farmacia Farmavero, C.A. | C64: J-30823400-1 | D64: Maracay | E64: Aragua | G64: C.C. Parque San Jacinto, Al Lado de la Panaderia Los Golfeados de San Jacinto, Maracay, Estado Aragua. | H64: San Jacinto | I64: 0414-1467867 | O64: TRUE | S64: Alta | U64: @farmacia_farmavero | V64: 45798 | W64: repbiofarco | X64: dispositivosbiofarco@gmail.com
A65: 64 | B65: Facitodo San Jacinto | C65: 0424-3257945 | D65: Maracay | E65: Aragua | H65: San Jacinto | I65: 0424-3257945 | O65: TRUE | S65: Media | V65: 45798 | W65: repbiofarco | X65: dispositivosbiofarco@gmail.com
A66: 65 | B66: Facitodo 23 de Enero | C66: 0424-3171324 | D66: Maracay | E66: Aragua | G66: 23 de Enero | H66: 23 de Enero | I66: 0424-3171324 | J66: 0424-4244910 | K66: Danny | O66: TRUE | S66: Media | V66: 45828 | W66: repbiofarco | X66: dispositivosbiofarco@gmail.com
A67: 66 | B67: Facitodo Norte | C67: 0424-3161277 | D67: Maracay | E67: Aragua | G67: Circulo Militar | H67: Las Delicias | I67: 0424-3161277 | O67: TRUE | S67: Media | W67: repbiofarco | X67: dispositivosbiofarco@gmail.com
A68: 67 | B68: Facitodo Boulevard | C68: J-50274200-1 | D68: Maracay | E68: Aragua | G68: Av. Miranda c/c Boulevard Pérez Almarza | H68: Centro | J68: 0424-3129857 | O68: TRUE | S68: Media | V68: 45807 | W68: repbiofarco | X68: dispositivosbiofarco@gmail.com
A69: 68 | B69: Facitodo La Mulera | D69: Maracay | E69: Aragua | G69: C.C. La Mulera | H69: Los Samanes | O69: TRUE | S69: Media | W69: repbiofarco | X69: dispositivosbiofarco@gmail.com
A70: 69 | B70: Facitodo Av. Mariño | C70: 0424-3209426 | D70: Maracay | E70: Aragua | G70: Av. Miranda & Blvd. Pérez Almarza, Maracay 2103, Aragua, Venezuela | H70: Centro | I70: 0424-3209426 | O70: TRUE | S70: Media | W70: repbiofarco | X70: dispositivosbiofarco@gmail.com
A71: 70 | B71: Farmavida Intercomunal | C71: J-50562826-7 | D71: Turmero | E71: Aragua | G71: Avenida Intercomunal Santiago Mariño, Turmero 2115, Aragua, Venezuela | H71: La Providencia | I71: 0412-4959996 | O71: TRUE | S71: Media | W71: repbiofarco | X71: dispositivosbiofarco@gmail.com
A72: 71 | B72: Farmavida La Victoria | C72: 0424-3447609 | D72: La Victoria | E72: Aragua | G72: C. Páez, La Victoria 2121, Aragua, Venezuela | H72: Centro | I72: 0424-3447609 | J72: 04125955454 | L72: farmavida.prov@gmail.com | O72: TRUE | S72: Media | U72: @farmavidavzla_ | W72: repbiofarco | X72: dispositivosbiofarco@gmail.com
A73: 72 | B73: Farmacia Policlinico Turmero | D73: Turmero | E73: Aragua | G73: Policlínico de Turmero Edo. Aragua | H73: Centro | W73: repbiofarco | X73: dispositivosbiofarco@gmail.com
A74: 73 | B74: Eurofarmacia Las Americas | C74: J-31221441-4 | D74: Maracay | E74: Aragua | G74: Avenida Las Delicias, Maracay 2101, Aragua, Venezuela | H74: Las Delicias | L74: eurofarmacia135@gmail.com | O74: TRUE | S74: Media | U74: @euromercadoca | V74: 45806 | W74: repbiofarco | X74: dispositivosbiofarco@gmail.com
A75: 74 | B75: Farmacia Solidaria y Popular | C75: J-07579872-4 | D75: Maracay | E75: Aragua | G75: C. Mariño, Maracay, Aragua, Venezuela | H75: Centro | K75: Ilda Guerra | L75: farmasp@gmail.com | O75: TRUE | S75: Baja | V75: 45807 | W75: repbiofarco | X75: dispositivosbiofarco@gmail.com
A76: 75 | B76: Farmasol Boulevard 2020 | C76: J-50031230-0 | D76: Maracay | E76: Aragua | G76: Blvd. Pérez Almarza, Maracay 2103, Aragua, Venezuela | H76: Centro | J76: 0414-4631620 | K76: Genesis | O76: TRUE | S76: Media | U76: @farmasol_ve | V76: 45806 | W76: repbiofarco | X76: dispositivosbiofarco@gmail.com
A77: 76 | B77: Farmacia Las Ballenas 2020 | C77: J-50038918-3 | D77: Maracay | E77: Aragua | H77: Las Delicias | O77: TRUE | S77: Media | U77: @farmaballenas | V77: 45806 | W77: repbiofarco | X77: dispositivosbiofarco@gmail.com
A78: 77 | B78: Farma Ven | C78: J-50254125-0 | D78: Maracay | E78: Aragua | G78: Parada Bus El Samán, Av. Los Jabillos, Maracay 2105, Aragua, Venezuela | H78: José Felix Ribas | I78: 0424-3564637 | J78: 0412-4109208 | K78: Angel Cillo | O78: TRUE | S78: Baja | V78: 45807 | W78: repbiofarco | X78: dispositivosbiofarco@gmail.com
A79: 78 | B79: Farmasol Santo Michelena | C79: J-50127793-1 | D79: Maracay | E79: Aragua | G79: Calle Santos Michelena, Maracay 2101, Aragua, Venezuela | H79: Centro | I79: 0424-3466685 | O79: TRUE | S79: Baja | V79: 45806 | W79: repbiofarco | X79: dispositivosbiofarco@gmail.com
A80: 79 | B80: Farmacia Mi Esperanza | C80: J-50671898-7 | D80: Maracay | E80: Aragua | G80: Av. Bolívar, Maracay, Aragua, Venezuela | H80: Centro | I80: 0424-3093104 | J80: 0414-9474793 | K80: Andrea Rodriguez | L80: farmaciamiesperanza2424@gmail.com | O80: TRUE | S80: Baja | V80: 45813 | W80: repbiofarco | X80: dispositivosbiofarco@gmail.com
A81: 80 | B81: FARMACENTER CENTRO II C.A | C81: J-412283471-4 | D81: Maracay | E81: Aragua | G81: Av. Bolivar, C/ Vargas con Av Bolívar Diagonal a la U.E Republica de México | H81: Centro | I81: 0412-1469168 | L81: farmacentercentroii@gmail.com | O81: TRUE | S81: Media | U81: @farmacenterca | V81: 45807 | W81: repbiofarco | X81: dispositivosbiofarco@gmail.com
A82: 81 | B82: Farmatodo Amatista | C82: J-00020200-1 | D82: Turmero | E82: Aragua | G82: Av. Intercomunal Santiago Mariño, Turmero, Aragua, Venezuela | H82: La Providencia | O82: TRUE | S82: Media | V82: 45807 | W82: repbiofarco | X82: dispositivosbiofarco@gmail.com
A83: 82 | B83: Mc Time Farmacia | C83: J-31584521-0 | D83: Maracay | E83: Aragua | G83: Av. Bolívar, Maracay, Aragua, Venezuela | H83: Parque Aragua | J83: 0412-466596 | K83: Daniel | O83: TRUE | S83: Baja | W83: repbiofarco | X83: dispositivosbiofarco@gmail.com
A84: 83 | B84: Eurofarmacia Intercomunal | C84: J-30071273-7 | D84: Turmero | E84: Aragua | G84: Av. Intercomunal Santiago Mariño, Turmero, Aragua, Venezuela | H84: La Providencia | J84: 0414-4476076 | K84: Wilmer | O84: TRUE | S84: Media | U84: @euromercadoca | V84: 45806 | W84: repbiofarco | X84: dispositivosbiofarco@gmail.com
A85: 84 | B85: Farmacia Lincoln Las Delicias | C85: J-50569819-2 | D85: Maracay | E85: Aragua | G85: Av. Las Delicias, Maracay 2101, Aragua, Venezuela | H85: Las Delicias | J85: 0414-9782614 | K85: Francis Quevedo | O85: TRUE | S85: Media | V85: 45824 | W85: repbiofarco | X85: dispositivosbiofarco@gmail.com
A86: 85 | B86: FarmaDia Santa María | C86: J-30341278-5 | D86: Maracay | E86: Aragua | G86: Avenida bolivar diagonal Parque Aragua al lado de C.C Pacífico Maracay-Edo.Aragua | H86: Parque Aragua | I86: 0243-2328297 | J86: 0412-6693059 | W86: repbiofarco | X86: dispositivosbiofarco@gmail.com
A87: 86 | B87: Farmadia Fundación Mendoza | C87: 0243-2358972 | D87: Maracay | E87: Aragua | G87: C.C. Fundación Mendoza, Local 1 y 7, Urb. La Fundación Mendoza | H87: Fuerzas Aereas | I87: 0243-2358972 | W87: repbiofarco | X87: dispositivosbiofarco@gmail.com
A88: 87 | B88: Farma Emergencia | C88: J-50137868-1 | D88: Maracay | E88: Aragua | G88: Hospital Central de Maracay | H88: La Delicias | J88: 0414-4480577 | K88: Raizelys Suarez | O88: TRUE | S88: Alta | U88: @farma_emergencia | V88: 45828 | W88: repbiofarco | X88: dispositivosbiofarco@gmail.com
A89: 88 | B89: Farmacia SAAS Galería Plaza | C89: J-50077240-8 | D89: Maracay | E89: Aragua | G89: Av. Bolívar, Maracay 2103, Aragua, Venezuela | H89: Centro | J89: 0424-3530268 | K89: María Fernanda | O89: TRUE | S89: Alta | U89: @saas_galeriaplaza | W89: repbiofarco | X89: dispositivosbiofarco@gmail.com
A90: 89 | B90: Locatel Los Aviadores | C90: J-50202212-0 | D90: Palo Negro | E90: Aragua | G90: Av los Aviadores CC Parque los Aviadores, Palo Negro 2117, Aragua, Venezuela | H90: C.C. Aviadores | J90: 0426-5193139 | K90: Tahiri Carpio | W90: repbiofarco | X90: dispositivosbiofarco@gmail.com
A91: 90 | B91: Farmedik | C91: J413023601 | D91: Maracay | E91: Aragua | G91: 19 de Abril, Clínica Lugo | H91: Centro | J91: 0424-3177077 | K91: Daniel García | O91: TRUE | S91: Media | W91: repbiofarco | X91: dispositivosbiofarco@gmail.com
A92: 91 | B92: Farmacia Grupo Medical Casa Salud, C.A. | C92: J-41280656-4 | D92: Maracay | E92: Aragua | G92: 7CF7+R2G, 2101, Aragua, Venezuela | H92: Las Delicias | I92: 0424- 3394960 | J92: 0424-3706335 | K92: Anny | L92: compras.casafarmamcy@gmail.com | O92: TRUE | S92: Alta | V92: 45848 | W92: repbiofarco | X92: dispositivosbiofarco@gmail.com
A93: 92 | B93: Farma Total | C93: J-31150127-8 | D93: Maracay | E93: Aragua | G93: Av. Bolívar, Maracay, Aragua, Venezuela | H93: Centro | O93: TRUE | S93: Media | V93: 45814 | W93: repbiofarco | X93: dispositivosbiofarco@gmail.com
A94: 93 | B94: Farmacia Mas x Menos CC Global | C94: J-50463307-0 | D94: Maracay | E94: Aragua | G94: C.C. El Global, Av. Bolivar Este, Maracay Edo Aragua | H94: La Barraca | O94: TRUE | S94: Media | V94: 45827 | W94: repbiofarco | X94: dispositivosbiofarco@gmail.com
A95: 94 | B95: FarmaCenter 23 de Enero | C95: J-50163706-7 | D95: Maracay | E95: Aragua | G95: Av. Principal de 23 de Enero Maraca Edo. Aragua | H95: 23 de Enero0424 | J95: 0424-3730070 | O95: TRUE | S95: Media | V95: 45828 | W95: repbiofarco | X95: dispositivosbiofarco@gmail.com

Sheet Inventario_Farmacia
A1: ID Inventario | B1: ID_Visita | C1: ID_Farmacia | D1: ID_Producto | E1: Cantidad Existente | F1: Precio Registrado | G1: Fecha Registro | H1: Lote | I1: FechaElaboracion | J1: FechaVencimiento | K1: Notas Inventario | L1: Caras_Exhibicion | M1: Caras_Competencia | N1: Personal_Capacitado | O1: POP_Visible | P1: Alerta_Sustitucion | Q1: Registrado Por | R1: ID_Usuario | S1: SUBMITTED BY
A2: a4d65f49 | D2: PRO-013 | E2: 3 | F2: 790 | G2: 45805.341 | Q2: dispositivosbiofarco@gmail.com | R2: repbiofarco | S2: dispositivosbiofarco@gmail.com
A3: a262dcb8 | C3: ac0b0b41 | D3: PRO-013 | E3: 3 | F3: 790 | G3: 45805.346 | Q3: dispositivosbiofarco@gmail.com | R3: repbiofarco | S3: dispositivosbiofarco@gmail.com
A4: 113f8d32 | C4: ac0b0b41 | D4: PRO-026 | E4: 3 | G4: 45805.349 | Q4: dispositivosbiofarco@gmail.com | R4: repbiofarco | S4: dispositivosbiofarco@gmail.com
A5: 8a55710b | C5: ac0b0b41 | D5: PRO-051 | E5: 2 | G5: 45805.352 | Q5: dispositivosbiofarco@gmail.com | R5: repbiofarco | S5: dispositivosbiofarco@gmail.com
A6: a397dd41 | C6: 2f00830e | D6: PRO-026 | E6: 1 | F6: 6.96 | G6: 45805.362 | Q6: dispositivosbiofarco@gmail.com | R6: repbiofarco | S6: dispositivosbiofarco@gmail.com
A7: 13776726 | C7: 2f00830e | D7: PRO-026 | E7: 2 | F7: 6.96 | G7: 45805.363 | K7: Menta | Q7: dispositivosbiofarco@gmail.com | R7: repbiofarco | S7: dispositivosbiofarco@gmail.com
A8: df38fde4 | C8: 2f00830e | D8: PRO-035 | E8: 1 | F8: 8.35 | G8: 45805.363 | K8: -0.4 | Q8: dispositivosbiofarco@gmail.com | R8: repbiofarco | S8: dispositivosbiofarco@gmail.com
A9: 82b8aa1e | C9: 2f00830e | D9: PRO-051 | E9: 2 | F9: 7.79 | G9: 45805.364 | Q9: dispositivosbiofarco@gmail.com | R9: repbiofarco | S9: dispositivosbiofarco@gmail.com
A10: 0cf4f2f8 | C10: 2f00830e | D10: PRO-015 | E10: 2 | F10: 11.23 | G10: 45805.368 | K10: De litro | Q10: dispositivosbiofarco@gmail.com | R10: repbiofarco | S10: dispositivosbiofarco@gmail.com
A11: c9e9de61 | C11: 2f00830e | D11: PRO-016 | E11: 1 | F11: 9.56 | G11: 45805.368 | K11: Medio en 5.20 | Q11: dispositivosbiofarco@gmail.com | R11: repbiofarco | S11: dispositivosbiofarco@gmail.com
A12: e891a81e | B12: 8fa2efef | D12: PRO-003 | E12: 2 | F12: 2.1 | G12: 45805.733 | Q12: dispositivosbiofarco@gmail.com | R12: repbiofarco | S12: dispositivosbiofarco@gmail.com
A13: bb3c40ee | B13: 43cb1656 | D13: PRO-003 | G13: 45813.317 | Q13: dispositivosbiofarco@gmail.com | R13: repbiofarco | S13: dispositivosbiofarco@gmail.com
A14: 933419ac | B14: 43cb1656 | D14: PRO-011 | G14: 45813.317 | Q14: dispositivosbiofarco@gmail.com | R14: repbiofarco | S14: dispositivosbiofarco@gmail.com
A15: dafd27fc | B15: 43cb1656 | D15: PRO-040 | G15: 45813.317 | Q15: dispositivosbiofarco@gmail.com | R15: repbiofarco | S15: dispositivosbiofarco@gmail.com
A16: 653c9ad7 | B16: b681a6af | D16: PRO-028 | E16: 1 | G16: 45813.318 | Q16: dispositivosbiofarco@gmail.com | R16: repbiofarco | S16: dispositivosbiofarco@gmail.com
A17: b392778c | C17: 46 | D17: PRO-035 | E17: 5 | F17: 1346.45 | G17: 45813.341 | Q17: dispositivosbiofarco@gmail.com | R17: repbiofarco | S17: dispositivosbiofarco@gmail.com
A18: 0dbfa633 | C18: 46 | D18: PRO-026 | E18: 8 | F18: 992.1 | G18: 45813.342 | K18: Sabor Natural | Q18: dispositivosbiofarco@gmail.com | R18: repbiofarco | S18: dispositivosbiofarco@gmail.com
A19: b91d6ec8 | C19: 46 | D19: PRO-026 | E19: 5 | F19: 992.1 | G19: 45813.342 | K19: Sabor Menta | Q19: dispositivosbiofarco@gmail.com | R19: repbiofarco | S19: dispositivosbiofarco@gmail.com
A20: fabc7cf9 | C20: 46 | D20: PRO-051 | E20: 1 | F20: 893.2 | G20: 45813.343 | Q20: dispositivosbiofarco@gmail.com | R20: repbiofarco | S20: dispositivosbiofarco@gmail.com
A21: de67ef3f | C21: 46 | D21: PRO-013 | E21: 5 | F21: 1119.7 | G21: 45813.343 | Q21: dispositivosbiofarco@gmail.com | R21: repbiofarco | S21: dispositivosbiofarco@gmail.com
A22: ecf50d22 | C22: 97 | D22: PRO-035 | E22: 3 | F22: 1023.1 | G22: 45813.344 | Q22: dispositivosbiofarco@gmail.com | R22: repbiofarco | S22: dispositivosbiofarco@gmail.com
A23: e5f9a180 | C23: 97 | D23: PRO-026 | E23: 8 | F23: 795.3 | G23: 45813.345 | K23: Sabor Natural | Q23: dispositivosbiofarco@gmail.com | R23: repbiofarco | S23: dispositivosbiofarco@gmail.com
A24: 8e6d7917 | C24: 97 | D24: PRO-026 | E24: 5 | F24: 795.3 | G24: 45813.345 | K24: Sabor Menta | Q24: dispositivosbiofarco@gmail.com | R24: repbiofarco | S24: dispositivosbiofarco@gmail.com
A25: 02de536b | C25: 97 | D25: PRO-051 | E25: 2 | F25: 685.3 | G25: 45813.346 | Q25: dispositivosbiofarco@gmail.com | R25: repbiofarco | S25: dispositivosbiofarco@gmail.com
A26: 98f20f1a | C26: 97 | D26: PRO-013 | E26: 4 | F26: 850.75 | G26: 45813.347 | Q26: dispositivosbiofarco@gmail.com | R26: repbiofarco | S26: dispositivosbiofarco@gmail.com
A27: dd91df1e | C27: 99 | D27: PRO-035 | E27: 3 | F27: 1023.1 | G27: 45813.347 | Q27: dispositivosbiofarco@gmail.com | R27: repbiofarco | S27: dispositivosbiofarco@gmail.com
A28: 848b5ab6 | C28: 99 | D28: PRO-026 | E28: 8 | F28: 795.3 | G28: 45813.347 | K28: Sabor Natural | Q28: dispositivosbiofarco@gmail.com | R28: repbiofarco | S28: dispositivosbiofarco@gmail.com
A29: c8271adf | C29: 99 | D29: PRO-026 | E29: 5 | F29: 795.3 | G29: 45813.348 | K29: Sabor a Menta | Q29: dispositivosbiofarco@gmail.com | R29: repbiofarco | S29: dispositivosbiofarco@gmail.com
A30: 706a3886 | C30: 99 | D30: PRO-051 | E30: 2 | F30: 685.75 | G30: 45813.394 | Q30: dispositivosbiofarco@gmail.com | R30: repbiofarco | S30: dispositivosbiofarco@gmail.com
A31: bd837d50 | C31: 99 | D31: PRO-013 | E31: 3 | F31: 850.75 | G31: 45813.395 | Q31: dispositivosbiofarco@gmail.com | R31: repbiofarco | S31: dispositivosbiofarco@gmail.com
A32: b371085e | C32: 100 | D32: PRO-035 | E32: 5 | F32: 1023.1 | G32: 45813.395 | Q32: dispositivosbiofarco@gmail.com | R32: repbiofarco | S32: dispositivosbiofarco@gmail.com
A33: 59f006af | C33: 100 | D33: PRO-026 | E33: 7 | F33: 795.3 | G33: 45813.396 | Q33: dispositivosbiofarco@gmail.com | R33: repbiofarco | S33: dispositivosbiofarco@gmail.com
A34: 4c72097a | C34: 100 | D34: PRO-026 | E34: 4 | F34: 795.3 | G34: 45813.396 | Q34: dispositivosbiofarco@gmail.com | R34: repbiofarco | S34: dispositivosbiofarco@gmail.com
A35: e49178d5 | C35: 100 | D35: PRO-013 | E35: 4 | F35: 850.75 | G35: 45813.396 | Q35: dispositivosbiofarco@gmail.com | R35: repbiofarco | S35: dispositivosbiofarco@gmail.com
A36: 92be3b8e | C36: 101 | D36: PRO-035 | E36: 4 | F36: 1023.1 | G36: 45813.397 | Q36: dispositivosbiofarco@gmail.com | R36: repbiofarco | S36: dispositivosbiofarco@gmail.com
A37: f8ee0ba0 | C37: 101 | D37: PRO-026 | E37: 7 | F37: 795.3 | G37: 45813.397 | Q37: dispositivosbiofarco@gmail.com | R37: repbiofarco | S37: dispositivosbiofarco@gmail.com
A38: 97cce3cd | C38: 101 | D38: PRO-026 | E38: 4 | F38: 793.3 | G38: 45813.397 | K38: Sabor Menta | Q38: dispositivosbiofarco@gmail.com | R38: repbiofarco | S38: dispositivosbiofarco@gmail.com
A39: 651bc22c | C39: 101 | D39: PRO-051 | E39: 1 | F39: 685.3 | G39: 45813.397 | Q39: dispositivosbiofarco@gmail.com | R39: repbiofarco | S39: dispositivosbiofarco@gmail.com
A40: b9ea7047 | C40: 101 | D40: PRO-013 | E40: 3 | F40: 850.5 | G40: 45813.398 | Q40: dispositivosbiofarco@gmail.com | R40: repbiofarco | S40: dispositivosbiofarco@gmail.com
A41: 6c556dc4 | C41: 102 | D41: PRO-035 | E41: 4 | F41: 1346.45 | G41: 45813.398 | K41: Lote 255402 E 02/25 V02/27 | Q41: dispositivosbiofarco@gmail.com | R41: repbiofarco | S41: dispositivosbiofarco@gmail.com
A42: 53fea15e | C42: 102 | D42: PRO-026 | E42: 7 | F42: 992.1 | G42: 45813.399 | K42: Sabor Natural Lote 152703 E 04/25 V 04/27 | Q42: dispositivosbiofarco@gmail.com | R42: repbiofarco | S42: dispositivosbiofarco@gmail.com
A43: 13ca242a | C43: 102 | D43: PRO-026 | E43: 6 | F43: 795.3 | G43: 45813.399 | K43: Sabor a Menta Lote 154701 E 02/25 V02/27 | Q43: dispositivosbiofarco@gmail.com | R43: repbiofarco | S43: dispositivosbiofarco@gmail.com
A44: be477c3f | C44: 102 | D44: PRO-013 | E44: 5 | F44: 1119.7 | G44: 45813.4 | K44: Lote 258005 E 07/25 V07/27 | Q44: dispositivosbiofarco@gmail.com | R44: repbiofarco | S44: dispositivosbiofarco@gmail.com
A45: 56a4f776 | C45: 103 | D45: PRO-026 | E45: 5 | F45: 795.3 | G45: 45813.4 | K45: Sabor Natural | Q45: dispositivosbiofarco@gmail.com | R45: repbiofarco | S45: dispositivosbiofarco@gmail.com
A46: bf30f0fd | C46: 103 | D46: PRO-051 | E46: 2 | F46: 685.3 | G46: 45813.401 | Q46: dispositivosbiofarco@gmail.com | R46: repbiofarco | S46: dispositivosbiofarco@gmail.com
A47: 5b414a74 | C47: 103 | D47: PRO-013 | E47: 5 | F47: 850.75 | G47: 45813.401 | Q47: dispositivosbiofarco@gmail.com | R47: repbiofarco | S47: dispositivosbiofarco@gmail.com
A48: b5ec6aaf | B48: 05f9e340 | D48: PRO-028 | E48: 1 | F48: 471.71 | G48: 45813.711 | Q48: dispositivosbiofarco@gmail.com | R48: repbiofarco | S48: dispositivosbiofarco@gmail.com
A49: 4af7cb2e | B49: 05f9e340 | D49: PRO-021 | E49: 3 | F49: 367.63 | G49: 45813.711 | Q49: dispositivosbiofarco@gmail.com | R49: repbiofarco | S49: dispositivosbiofarco@gmail.com
A50: 52d87a12 | B50: 05f9e340 | D50: PRO-035 | E50: 4 | F50: 754.47 | G50: 45813.712 | Q50: dispositivosbiofarco@gmail.com | R50: repbiofarco | S50: dispositivosbiofarco@gmail.com
A51: e38415f2 | B51: 05f9e340 | D51: PRO-026 | E51: 3 | F51: 402 | G51: 45813.712 | K51: Sabor Natural | Q51: dispositivosbiofarco@gmail.com | R51: repbiofarco | S51: dispositivosbiofarco@gmail.com
A52: 41887789 | B52: 05f9e340 | D52: PRO-026 | E52: 1 | F52: 402 | G52: 45813.713 | K52: Sabor a Menta | Q52: dispositivosbiofarco@gmail.com | R52: repbiofarco | S52: dispositivosbiofarco@gmail.com
A53: b4c99752 | B53: 05f9e340 | D53: PRO-015 | E53: 5 | F53: 967.8 | G53: 45813.713 | Q53: dispositivosbiofarco@gmail.com | R53: repbiofarco | S53: dispositivosbiofarco@gmail.com
A54: 02ea5aae | B54: 05f9e340 | D54: PRO-016 | E54: 2 | G54: 45813.713 | Q54: dispositivosbiofarco@gmail.com | R54: repbiofarco | S54: dispositivosbiofarco@gmail.com
A55: b83c9940 | B55: 05f9e340 | D55: PRO-013 | F55: 417 | G55: 45813.714 | Q55: dispositivosbiofarco@gmail.com | R55: repbiofarco | S55: dispositivosbiofarco@gmail.com
A56: 6a6804aa | B56: 5c8aefcd | D56: PRO-019 | F56: 445 | G56: 45813.717 | Q56: dispositivosbiofarco@gmail.com | R56: repbiofarco | S56: dispositivosbiofarco@gmail.com
A57: 422e5e0a | B57: 5c8aefcd | D57: PRO-013 | F57: 711 | G57: 45813.717 | Q57: dispositivosbiofarco@gmail.com | R57: repbiofarco | S57: dispositivosbiofarco@gmail.com
A58: a936c8a3 | B58: 5c8aefcd | D58: PRO-048 | F58: 331 | G58: 45813.717 | Q58: dispositivosbiofarco@gmail.com | R58: repbiofarco | S58: dispositivosbiofarco@gmail.com
A59: 6c0602b8 | B59: 48c86642 | D59: PRO-015 | E59: 3 | F59: 12.5 | G59: 45813.719 | K59: Medio Litro | Q59: dispositivosbiofarco@gmail.com | R59: repbiofarco | S59: dispositivosbiofarco@gmail.com
A60: 5bf2b474 | B60: 48c86642 | D60: PRO-015 | E60: 2 | F60: 14.8 | G60: 45813.719 | K60: Litro | Q60: dispositivosbiofarco@gmail.com | R60: repbiofarco | S60: dispositivosbiofarco@gmail.com
A61: 64c82e76 | B61: 48c86642 | D61: PRO-016 | E61: 3 | F61: 9.6 | G61: 45813.72 | K61: Litro | Q61: dispositivosbiofarco@gmail.com | R61: repbiofarco | S61: dispositivosbiofarco@gmail.com
A62: 03003d26 | B62: 48c86642 | D62: PRO-002 | E62: 2 | F62: 2 | G62: 45813.72 | Q62: dispositivosbiofarco@gmail.com | R62: repbiofarco | S62: dispositivosbiofarco@gmail.com
A63: 9ec74d9f | C63: 6d5f7cb2 | D63: PRO-002 | E63: 2 | F63: 2 | G63: 45815.411 | Q63: dispositivosbiofarco@gmail.com | R63: repbiofarco | S63: dispositivosbiofarco@gmail.com
A64: a0c762f0 | C64: c3aaef31 | D64: PRO-011 | E64: 1 | G64: 45836.52 | Q64: dispositivosbiofarco@gmail.com | R64: repbiofarco | S64: dispositivosbiofarco@gmail.com
A65: 9246d1f6 | C65: c3aaef31 | D65: PRO-003 | E65: 1 | G65: 45836.521 | Q65: dispositivosbiofarco@gmail.com | R65: repbiofarco | S65: dispositivosbiofarco@gmail.com
A66: d8026527 | C66: c3aaef31 | D66: PRO-036 | E66: 1 | F66: 911 | G66: 45836.521 | Q66: dispositivosbiofarco@gmail.com | R66: repbiofarco | S66: dispositivosbiofarco@gmail.com
A67: 22c0e25a | C67: c3aaef31 | D67: PRO-009 | E67: 1 | G67: 45836.521 | Q67: dispositivosbiofarco@gmail.com | R67: repbiofarco | S67: dispositivosbiofarco@gmail.com
A68: c47dc369 | C68: 18ea49b4 | D68: PRO-013 | E68: 2 | G68: 45836.526 | Q68: dispositivosbiofarco@gmail.com | R68: repbiofarco | S68: dispositivosbiofarco@gmail.com
A69: d7e25dca | C69: 18ea49b4 | D69: PRO-048 | E69: 10 | G69: 45836.526 | Q69: dispositivosbiofarco@gmail.com | R69: repbiofarco | S69: dispositivosbiofarco@gmail.com
A70: b2af1295 | C70: 18ea49b4 | D70: PRO-051 | E70: 1 | G70: 45836.526 | Q70: dispositivosbiofarco@gmail.com | R70: repbiofarco | S70: dispositivosbiofarco@gmail.com
A71: 2dc453d3 | C71: 18ea49b4 | D71: PRO-015 | E71: 2 | G71: 45836.526 | Q71: dispositivosbiofarco@gmail.com | R71: repbiofarco | S71: dispositivosbiofarco@gmail.com
A72: 910c3b75 | C72: 18ea49b4 | D72: PRO-035 | G72: 45836.527 | Q72: dispositivosbiofarco@gmail.com | R72: repbiofarco | S72: dispositivosbiofarco@gmail.com
A73: 20e9f2f7 | C73: 57 | D73: PRO-028 | E73: 2 | F73: 471 | G73: 45836.548 | Q73: dispositivosbiofarco@gmail.com | R73: repbiofarco | S73: dispositivosbiofarco@gmail.com
A74: e8e038ee | C74: 57 | D74: PRO-021 | E74: 4 | F74: 367 | G74: 45836.549 | Q74: dispositivosbiofarco@gmail.com | R74: repbiofarco | S74: dispositivosbiofarco@gmail.com
A75: 5e9fe156 | C75: 57 | D75: PRO-035 | E75: 4 | F75: 754 | G75: 45836.549 | Q75: dispositivosbiofarco@gmail.com | R75: repbiofarco | S75: dispositivosbiofarco@gmail.com
A76: 29f980af | C76: 57 | D76: PRO-026 | E76: 3 | F76: 402 | G76: 45836.549 | K76: Sabor Original | Q76: dispositivosbiofarco@gmail.com | R76: repbiofarco | S76: dispositivosbiofarco@gmail.com
A77: 582abc84 | C77: 57 | D77: PRO-026 | E77: 1 | F77: 402 | G77: 45836.55 | K77: Sabor Menta | Q77: dispositivosbiofarco@gmail.com | R77: repbiofarco | S77: dispositivosbiofarco@gmail.com
A78: 08907db0 | C78: 57 | D78: PRO-015 | E78: 5 | F78: 967 | G78: 45836.55 | Q78: dispositivosbiofarco@gmail.com | R78: repbiofarco | S78: dispositivosbiofarco@gmail.com
A79: 376f66b4 | C79: 57 | D79: PRO-016 | E79: 2 | G79: 45836.551 | Q79: dispositivosbiofarco@gmail.com | R79: repbiofarco | S79: dispositivosbiofarco@gmail.com
A80: 3fa60d49 | C80: 57 | D80: PRO-013 | F80: 418 | G80: 45836.551 | Q80: dispositivosbiofarco@gmail.com | R80: repbiofarco | S80: dispositivosbiofarco@gmail.com
A81: 83c67268 | C81: 95 | D81: PRO-019 | E81: 1 | F81: 445 | G81: 45836.555 | Q81: dispositivosbiofarco@gmail.com | R81: repbiofarco | S81: dispositivosbiofarco@gmail.com
A82: e212942a | C82: 95 | D82: PRO-013 | E82: 1 | F82: 711 | G82: 45836.555 | Q82: dispositivosbiofarco@gmail.com | R82: repbiofarco | S82: dispositivosbiofarco@gmail.com
A83: 923243df | C83: 95 | D83: PRO-048 | E83: 1 | F83: 351 | G83: 45836.556 | Q83: dispositivosbiofarco@gmail.com | R83: repbiofarco | S83: dispositivosbiofarco@gmail.com
A84: 322e60be | C84: 94 | D84: PRO-015 | E84: 3 | F84: 13.5 | G84: 45836.556 | K84: Medio | Q84: dispositivosbiofarco@gmail.com | R84: repbiofarco | S84: dispositivosbiofarco@gmail.com
A85: 1b34bb77 | C85: 94 | D85: PRO-015 | E85: 2 | F85: 14.8 | G85: 45836.557 | K85: Litro | Q85: dispositivosbiofarco@gmail.com | R85: repbiofarco | S85: dispositivosbiofarco@gmail.com
A86: c3860e20 | C86: 94 | D86: PRO-016 | E86: 3 | F86: 9.6 | G86: 45836.557 | K86: Litro | Q86: dispositivosbiofarco@gmail.com | R86: repbiofarco | S86: dispositivosbiofarco@gmail.com
A87: c05bf489 | C87: 94 | D87: PRO-002 | E87: 2 | F87: 2 | G87: 45836.559 | Q87: dispositivosbiofarco@gmail.com | R87: repbiofarco | S87: dispositivosbiofarco@gmail.com
A88: 10bbe00b | C88: 94 | D88: PRO-025 | E88: 1 | G88: 45836.56 | Q88: dispositivosbiofarco@gmail.com | R88: repbiofarco | S88: dispositivosbiofarco@gmail.com
A89: 26b8df61 | C89: 94 | D89: PRO-035 | E89: 1 | G89: 45836.56 | Q89: dispositivosbiofarco@gmail.com | R89: repbiofarco | S89: dispositivosbiofarco@gmail.com
A90: 4694f262 | C90: 94 | D90: PRO-036 | E90: 1 | G90: 45836.56 | Q90: dispositivosbiofarco@gmail.com | R90: repbiofarco | S90: dispositivosbiofarco@gmail.com
A91: 1bbf36df | C91: 94 | D91: PRO-043 | E91: 1 | G91: 45836.562 | Q91: dispositivosbiofarco@gmail.com | R91: repbiofarco | S91: dispositivosbiofarco@gmail.com
A92: 59a30483 | C92: 94 | D92: PRO-026 | E92: 1 | G92: 45836.562 | Q92: dispositivosbiofarco@gmail.com | R92: repbiofarco | S92: dispositivosbiofarco@gmail.com
A93: fa8fcdcd | C93: 94 | D93: PRO-028 | E93: 1 | G93: 45836.562 | Q93: dispositivosbiofarco@gmail.com | R93: repbiofarco | S93: dispositivosbiofarco@gmail.com
A94: fa9dbff4 | C94: 94 | D94: PRO-042 | E94: 1 | G94: 45836.563 | Q94: dispositivosbiofarco@gmail.com | R94: repbiofarco | S94: dispositivosbiofarco@gmail.com
A95: 3ef5bfc0 | C95: 94 | D95: PRO-003 | E95: 1 | G95: 45836.563 | Q95: dispositivosbiofarco@gmail.com | R95: repbiofarco | S95: dispositivosbiofarco@gmail.com
A96: c1558fbd | C96: 94 | D96: PRO-006 | E96: 1 | F96: 4.2 | G96: 45836.563 | Q96: dispositivosbiofarco@gmail.com | R96: repbiofarco | S96: dispositivosbiofarco@gmail.com
A97: bb3ed2ba | C97: 94 | D97: PRO-004 | E97: 1 | F97: 2.6 | G97: 45836.563 | Q97: dispositivosbiofarco@gmail.com | R97: repbiofarco | S97: dispositivosbiofarco@gmail.com
A98: 15093559 | C98: 48 | D98: PRO-021 | E98: 4 | F98: 650 | G98: 45806.679 | Q98: dispositivosbiofarco@gmail.com | R98: repbiofarco | S98: dispositivosbiofarco@gmail.com
A99: fa5e5141 | C99: 0be7a23b | D99: PRO-035 | E99: 1 | F99: 1473 | G99: 45836.688 | Q99: dispositivosbiofarco@gmail.com | R99: repbiofarco | S99: dispositivosbiofarco@gmail.com
A100: 3291013c | C100: 0be7a23b | D100: PRO-026 | E100: 1 | F100: 749 | G100: 45836.688 | K100: Sabor a Menta | Q100: dispositivosbiofarco@gmail.com | R100: repbiofarco | S100: dispositivosbiofarco@gmail.com
...

Sheet FiltrosRotacion
A1: ID_Filtro | B1: FarmaciaSeleccionada | C1: ProductoSeleccionado | D1: ID_Usuario | E1: SUBMITTED BY
A2: 1 | B2: 22 | C2: PRO-035 | D2: repbiofarco | E2: dispositivosbiofarco@gmail.com

Sheet Transferencias
A1: ID_Pedido | B1: Fecha | C1: ID_Cotizacion | D1: ID_Farmacia | E1: ID_Drogueria | F1: Estado | G1: Prioridad | H1: Notas | I1: Contador | J1: Reporte Transferencia | K1: ID_Usuario | L1: SUBMITTED BY
A2: e05a8a92 | B2: 45882 | D2: 18ea49b4 | E2: 1 | F2: Procesado | G2: Media | H2: Código Nena C686 | I2: 2 | J2: /Transferencias/Farmacial Real 2022-1.pdf | K2: repbiofarco | L2: dispositivosbiofarco@gmail.com
A3: 3425186a | B3: 45890 | D3: 964789a9 | E3: 1 | F3: Procesado | G3: Alta | H3: Codigo Nena D-006 | I3: 2 | J3: /Transferencias/Farmacia Far Todo Virgen del Valle-1.pdf | K3: repbiofarco | L3: dispositivosbiofarco@gmail.com
A4: 8ab9ba93 | B4: 45903 | D4: 137cdbda | E4: 1 | F4: Procesado | G4: Media | H4: Codigo Nena 6050 | I4: 1 | J4: /Transferencias/Farmacia La Barraca-1.pdf | K4: repbiofarco | L4: dispositivosbiofarco@gmail.com
A5: 80f366fc | B5: 45911 | D5: 4fde48bf | E5: 1 | F5: Procesado | G5: Alta | H5: DRONENA Codigo 7633, COBECA Codigo R28711 o DrovenCentro Codigo 600010. | I5: 1 | J5: /Transferencias/Farmacia Malanga-1.pdf | K5: repbiofarco | L5: dispositivosbiofarco@gmail.com
A6: e3a5eaff | B6: 45911 | D6: 708d54e0 | E6: 3 | F6: Procesado | G6: Media | H6: COBECA Codigo: 31560 | I6: 1 | J6: /Transferencias/Farmacia Mi Esperanza 2424-1.pdf | K6: repbiofarco | L6: dispositivosbiofarco@gmail.com
A7: fa842f90 | B7: 45911 | D7: 69b36f13 | E7: 3 | F7: Procesado | G7: Alta | H7: Código COBECA 28929 | I7: 1 | J7: /Transferencias/Farmasol Boulevard 2020-1.pdf | K7: repbiofarco | L7: dispositivosbiofarco@gmail.com
A8: 361fbffa | B8: 45922 | D8: c32e41f5 | E8: 6 | F8: Procesado | G8: Media | H8: Codigo CrisMedical FAR-03502 | I8: 1 | J8: /Transferencias/Farmacia FARMALEON-1.pdf | K8: repbiofarco | L8: dispositivosbiofarco@gmail.com
A9: c1598867 | B9: 45923 | D9: 5 | E9: 3 | F9: Procesado | G9: Media | H9: Codigo COBECA 26352 | I9: 1 | J9: /Transferencias/Farma Shop Solidaria Ayacucho-1.pdf | K9: repbiofarco | L9: dispositivosbiofarco@gmail.com
A10: 695f9aeb | B10: 45939 | D10: b7417481 | E10: 3 | F10: Procesado | G10: Media | H10: Codigo COBECA 31445 | I10: 2 | J10: /Transferencias/FarmaJumbo Turmero-1.pdf | K10: repbiofarco | L10: dispositivosbiofarco@gmail.com
A11: 007d6a2f | B11: 45979 | C11: 7582d0b8 | D11: 48e9fe71 | E11: 2 | F11: Procesado | G11: Media | H11: Codigo VitalClinic 1296 | I11: 2 | J11: /Transferencias/Farmacia Grupo Medical Casa Salud-1.pdf | K11: repbiofarco | L11: dispositivosbiofarco@gmail.com
A12: 3f29acaa | B12: 45932 | D12: 52 | E12: 1 | F12: Procesado | G12: Media | H12: Codigo Nena $132 | I12: 2 | J12: /Transferencias/Farmacia El Sol-1.pdf | K12: repbiofarco | L12: dispositivosbiofarco@gmail.com
A13: 80a01443 | B13: 45939 | D13: 0be7a231 | E13: 1 | F13: Procesado | G13: Media | H13: Codigo Nena C836 - Codigo COBECA 50538 o 30538 | I13: 1 | J13: /Transferencias/Eurofarmacia-.pdf | K13: repbiofarco | L13: dispositivosbiofarco@gmail.com
A14: 334faf19 | B14: 45951 | D14: 708d54e0 | E14: 2 | F14: Procesado | G14: Media | H14: Codigo VitalClinic 4393 ó COBECA 31560 | I14: 1 | J14: /Transferencias/Farmacia Mi Esperanza 2424-.pdf | K14: repbiofarco | L14: dispositivosbiofarco@gmail.com
A15: ee689f4a | B15: 45951 | D15: 69b36f13 | E15: 3 | F15: Procesado | G15: Alta | H15: Código COBECA 28929 | I15: 1 | J15: /Transferencias/Farmasol Boulevard 2020-.pdf | K15: repbiofarco | L15: dispositivosbiofarco@gmail.com
A16: 835aaea4 | B16: 45951 | D16: 67a0121b | E16: 1 | F16: Pendiente | G16: Alta | H16: Código Nena E542 | J16: /Transferencias/FarmaSol Santos Michelena II-.pdf | K16: repbiofarco | L16: dispositivosbiofarco@gmail.com
A17: 0f72910e | B17: 45951 | D17: cfaf6844 | E17: 1 | F17: Pendiente | G17: Alta | H17: Código Nena D635 | J17: /Transferencias/Farmasol Vargas-.pdf | K17: repbiofarco | L17: dispositivosbiofarco@gmail.com
A18: a40cde83 | B18: 45966 | C18: 465ce288 | D18: 2cb82336 | E18: 4 | F18: Procesado | G18: Media | H18: Código Drovencentro 600445 - Código Insuaminca 03345 | I18: 1 | J18: /Transferencias/Mc Time Farmacia-.pdf | K18: repbiofarco | L18: dispositivosbiofarco@gmail.com
A20: 846f7f35 | B20: 46147 | C20: ddb3bd3c | D20: 0b9ea836 | E20: 061dbd84 | F20: Aprobada | G20: Alta | H20: Gentionar inventario con fecha de vencimiento 2028 | J20: /Files/Stock_Reports/Harissa Droguería, C.A._0b9ea836.pdf | K20: repbiofarco | L20: dispositivosbiofarco@gmail.com

Sheet Productos_X_Transferencia
A1: ID_Detalle | B1: ID_Transferencia | C1: ID_Producto | D1: Cantidad | E1: Nota | F1: ID_Drogueria_Temp | G1: ID_Usuario | H1: SUBMITTED BY
A2: 9a652359 | B2: e05a8a92 | C2: f39ad541 | D2: 2 | G2: repbiofarco | H2: dispositivosbiofarco@gmail.com
A3: 60dba42a | B3: e05a8a92 | C3: 5676e0c6 | D3: 2 | G3: repbiofarco | H3: dispositivosbiofarco@gmail.com
A4: 6d590629 | B4: e05a8a92 | C4: 1f610f8d | D4: 2 | G4: repbiofarco | H4: dispositivosbiofarco@gmail.com
A5: 82768ca3 | B5: 3425186a | C5: PRO-005 | D5: 8 | G5: repbiofarco | H5: dispositivosbiofarco@gmail.com
A6: 14e74be3 | B6: 3425186a | C6: PRO-002 | D6: 6 | G6: repbiofarco | H6: dispositivosbiofarco@gmail.com
A7: 9fb8bd30 | B7: 3425186a | C7: PRO-007 | D7: 12 | G7: repbiofarco | H7: dispositivosbiofarco@gmail.com
A8: a558af8f | B8: 3425186a | C8: PRO-007 | D8: 6 | G8: repbiofarco | H8: dispositivosbiofarco@gmail.com
A9: deea8eac | B9: 3425186a | C9: PRO-008 | D9: 4 | G9: repbiofarco | H9: dispositivosbiofarco@gmail.com
A10: b112573e | B10: 3425186a | C10: PRO-028 | D10: 6 | G10: repbiofarco | H10: dispositivosbiofarco@gmail.com
A11: cb8b4aff | B11: 3425186a | C11: PRO-028 | D11: 6 | G11: repbiofarco | H11: dispositivosbiofarco@gmail.com
A12: c372de24 | B12: 3425186a | C12: PRO-015 | D12: 6 | G12: repbiofarco | H12: dispositivosbiofarco@gmail.com
A13: def9f42e | B13: 3425186a | C13: 51243510 | D13: 6 | G13: repbiofarco | H13: dispositivosbiofarco@gmail.com
... A24: 5d24747b | B24: 80f366fc | C24: PRO-017 | D24: 2 | G24: repbiofarco | H24: dispositivosbiofarco@gmail.com
A25: 1adb23a0 | B25: 80f366fc | C25: PRO-007 | D25: 3 | E25: 60 ml | G25: repbiofarco | H25: dispositivosbiofarco@gmail.com
A26: 498287b2 | B26: 80f366fc | C26: PRO-007 | D26: 3 | E26: 240 ml | G26: repbiofarco | H26: dispositivosbiofarco@gmail.com
A27: 986bc3ac | B27: 80f366fc | C27: PRO-053 | D27: 3 | E27: 120 ml | G27: repbiofarco | H27: dispositivosbiofarco@gmail.com
A28: 51194f44 | B28: 80f366fc | C28: PRO-008 | D28: 3 | E28: 120 ml | G28: repbiofarco | H28: dispositivosbiofarco@gmail.com
A29: 431eaa79 | B29: 80f366fc | C29: PRO-008 | D29: 3 | E29: 60 ml | G29: repbiofarco | H29: dispositivosbiofarco@gmail.com
A30: 9d2479df | B30: 80f366fc | C30: PRO-023 | D30: 1 | G30: repbiofarco | H30: dispositivosbiofarco@gmail.com
A31: fa343e8f | B31: 80f366fc | C31: PRO-013 | D31: 1 | G31: repbiofarco | H31: dispositivosbiofarco@gmail.com
A32: 3a07b176 | B32: 80f366fc | C32: PRO-016 | D32: 1 | E32: 500 ml | G32: repbiofarco | H32: dispositivosbiofarco@gmail.com
A33: 19551857 | B33: 80f366fc | C33: PRO-016 | D33: 1 | E33: 1000 ml | G33: repbiofarco | H33: dispositivosbiofarco@gmail.com
A34: 874a95a7 | B34: 80f366fc | C34: 51243510 | D34: 1 | G34: repbiofarco | H34: dispositivosbiofarco@gmail.com
A35: 8e3c773b | B35: 80f366fc | C35: PRO-021 | D35: 2 | G35: repbiofarco | H35: dispositivosbiofarco@gmail.com
A36: aae70791 | B36: 80f366fc | C36: f39ad541 | D36: 1 | E36: Coco | G36: repbiofarco | H36: dispositivosbiofarco@gmail.com
A37: 48fe5fee | B37: 80f366fc | C37: 5676e0c6 | D37: 1 | E37: Fresa | G37: repbiofarco | H37: dispositivosbiofarco@gmail.com
A38: f697d3e5 | B38: 80f366fc | C38: 1f610f8d | D38: 1 | E38: Uva | G38: repbiofarco | H38: dispositivosbiofarco@gmail.com
A39: 047c486f | B39: 80f366fc | C39: PRO-024 | D39: 3 | G39: repbiofarco | H39: dispositivosbiofarco@gmail.com
A40: 794754ec | B40: 80f366fc | C40: PRO-063 | D40: 1 | G40: repbiofarco | H40: dispositivosbiofarco@gmail.com
A41: 4e3f97ed | B41: 80f366fc | C41: PRO-027 | D41: 1 | G41: repbiofarco | H41: dispositivosbiofarco@gmail.com
A42: c051264d | B42: 80f366fc | C42: PRO-072 | D42: 1 | G42: repbiofarco | H42: dispositivosbiofarco@gmail.com
A43: a7994610 | B43: 80f366fc | C43: PRO-029 | D43: 1 | E43: Uguento | G43: repbiofarco | H43: dispositivosbiofarco@gmail.com
A44: 7a17cbb8 | B44: 80f366fc | C44: PRO-031 | D44: 1 | E44: Roll-on | G44: repbiofarco | H44: dispositivosbiofarco@gmail.com
A45: 77d98f0b | B45: 80f366fc | C45: PRO-030 | E45: Spray | G45: repbiofarco | H45: dispositivosbiofarco@gmail.com
A46: 4c1b7fd5 | B46: 80f366fc | C46: PRO-033 | D46: 1 | G46: repbiofarco | H46: dispositivosbiofarco@gmail.com
A47: 93ce2540 | B47: 80f366fc | C47: PRO-064 | D47: 2 | G47: repbiofarco | H47: dispositivosbiofarco@gmail.com
A48: dab961a3 | B48: 80f366fc | C48: PRO-034 | D48: 2 | G48: repbiofarco | H48: dispositivosbiofarco@gmail.com
A49: df94128f | B49: 80f366fc | C49: 71df8880269341fce19e2043 | D49: 1 | G49: repbiofarco | H49: dispositivosbiofarco@gmail.com
A50: 25a38fa1 | B50: 80f366fc | C50: eeac8176 | D50: 1 | G50: repbiofarco | H50: dispositivosbiofarco@gmail.com
A51: eba7f732 | B51: 80f366fc | C51: PRO-043 | D51: 2 | G51: repbiofarco | H51: dispositivosbiofarco@gmail.com
A52: 17493450 | B52: 80f366fc | C52: PRO-048 | D52: 1 | G52: repbiofarco | H52: dispositivosbiofarco@gmail.com
A53: 8b949ca7 | B53: e3a5eaff | C53: eeac8176 | D53: 1 | G53: repbiofarco | H53: dispositivosbiofarco@gmail.com
A54: fedaf718 | B54: e3a5eaff | C54: 71df8880269341fce19e2043 | D54: 1 | G54: repbiofarco | H54: dispositivosbiofarco@gmail.com
A55: d361437f | B55: fa842f90 | C55: PRO-021 | D55: 3 | G55: repbiofarco | H55: dispositivosbiofarco@gmail.com
A56: 3afeddb2 | B56: fa842f90 | C56: PRO-013 | D56: 3 | G56: repbiofarco | H56: dispositivosbiofarco@gmail.com
A57: 875c6179 | B57: fa842f90 | C57: PRO-051 | D57: 3 | G57: repbiofarco | H57: dispositivosbiofarco@gmail.com
... A63: 1daaccee | B63: fa842f90 | C63: PRO-033 | D63: 3 | G63: repbiofarco | H63: dispositivosbiofarco@gmail.com
A64: 7710f90a | B64: fa842f90 | C64: PRO-015 | D64: 3 | E64: 500 ml | G64: repbiofarco | H64: dispositivosbiofarco@gmail.com
A65: a4350998 | B65: fa842f90 | C65: PRO-015 | D65: 3 | E65: 1000 ml | G65: repbiofarco | H65: dispositivosbiofarco@gmail.com
A66: a8208d3f | B66: 361fbffa | C66: eeac8176 | D66: 2 | E66: 2 Cajas ó 20 Sobres | G66: repbiofarco | H66: dispositivosbiofarco@gmail.com
A67: ff2f70ea | B67: 361fbffa | C67: 71df8880269341fce19e2043 | D67: 2 | E67: 2 cajas ó 20 sobres | G67: repbiofarco | H67: dispositivosbiofarco@gmail.com
A68: b4e42ddf | B68: c1598867 | C68: PRO-043 | D68: 2 | E68: 200 gr | G68: repbiofarco | H68: dispositivosbiofarco@gmail.com
A69: ef48ec58 | B69: c1598867 | C69: PRO-043 | D69: 2 | E69: 90 gr | G69: repbiofarco | H69: dispositivosbiofarco@gmail.com
A70: 95b9583d | B70: c1598867 | C70: PRO-051 | D70: 1 | G70: repbiofarco | H70: dispositivosbiofarco@gmail.com
A71: daca55e7 | B71: c1598867 | C71: PRO-034 | D71: 1 | G71: repbiofarco | H71: dispositivosbiofarco@gmail.com
A72: f72a5a54 | B72: c1598867 | C72: PRO-026 | D72: 2 | E72: Original | G72: repbiofarco | H72: dispositivosbiofarco@gmail.com
A73: edd8799f | B73: c1598867 | C73: eeac8176 | D73: 2 | G73: repbiofarco | H73: dispositivosbiofarco@gmail.com
A74: 7b8c35de | B74: c1598867 | C74: 71df8880269341fce19e2043 | D74: 2 | G74: repbiofarco | H74: dispositivosbiofarco@gmail.com
A75: 8f0b2678 | B75: c1598867 | C75: PRO-028 | D75: 1 | E75: 110 ml | G75: repbiofarco | H75: dispositivosbiofarco@gmail.com
A76: 75278c73 | B76: c1598867 | C76: PRO-003 | D76: 6 | E76: Papeletas | G76: repbiofarco | H76: dispositivosbiofarco@gmail.com
A77: c3152a01 | B77: c1598867 | C77: PRO-048 | D77: 1 | G77: repbiofarco | H77: dispositivosbiofarco@gmail.com
A78: 658d753c | B78: 695f9aeb | C78: PRO-034 | D78: 1 | G78: repbiofarco | H78: dispositivosbiofarco@gmail.com
A79: 83241748 | B79: 695f9aeb | C79: PRO-064 | D79: 1 | G79: repbiofarco | H79: dispositivosbiofarco@gmail.com
A80: b56f8ae6 | B80: 695f9aeb | C80: eeac8176 | D80: 1 | G80: repbiofarco | H80: dispositivosbiofarco@gmail.com
A81: 31bed148 | B81: 695f9aeb | C81: 71df8880269341fce19e2043 | D81: 1 | G81: repbiofarco | H81: dispositivosbiofarco@gmail.com
A82: 494b82da | B82: 695f9aeb | C82: PRO-021 | D82: 1 | G82: repbiofarco | H82: dispositivosbiofarco@gmail.com
A83: 57693b1a | B83: 695f9aeb | C83: PRO-008 | D83: 3 | G83: repbiofarco | H83: dispositivosbiofarco@gmail.com
A84: dea6917f | B84: 8ab9ba93 | C84: f39ad541 | D84: 1 | G84: repbiofarco | H84: dispositivosbiofarco@gmail.com
A85: 8df0cc67 | B85: 8ab9ba93 | C85: 5676e0c6 | D85: 1 | G85: repbiofarco | H85: dispositivosbiofarco@gmail.com
A86: 6f66a870 | B86: 8ab9ba93 | C86: 1f610f8d | D86: 1 | G86: repbiofarco | H86: dispositivosbiofarco@gmail.com
A87: 9408e95d | B87: 007d6a2f | C87: PRO-059 | D87: 6 | G87: repbiofarco | H87: dispositivosbiofarco@gmail.com
A88: 382d74c7 | B88: 007d6a2f | C88: PRO-036 | D88: 3 | G88: repbiofarco | H88: dispositivosbiofarco@gmail.com
A89: 39f7b7bc | B89: 007d6a2f | C89: PRO-046 | D89: 6 | E89: 25 gr. | G89: repbiofarco | H89: dispositivosbiofarco@gmail.com
A90: d54b9d39 | B90: 3f29acaa | C90: PRO-002 | D90: 3 | G90: repbiofarco | H90: dispositivosbiofarco@gmail.com
A91: 4adb0dfe | B91: 3f29acaa | C91: f39ad541 | D91: 3 | G91: repbiofarco | H91: dispositivosbiofarco@gmail.com
A92: 264b8b48 | B92: 3f29acaa | C92: 5676e0c6 | D92: 3 | G92: repbiofarco | H92: dispositivosbiofarco@gmail.com
A93: c47baf41 | B93: 3f29acaa | C93: 1f610f8d | D93: 3 | G93: repbiofarco | H93: dispositivosbiofarco@gmail.com
A94: 0874f7b9 | B94: 3f29acaa | C94: PRO-043 | D94: 3 | E94: 90 gr. | G94: repbiofarco | H94: dispositivosbiofarco@gmail.com
A95: 9c5804e5 | B95: 80a01443 | C95: 51243510 | D95: 4 | G95: repbiofarco | H95: dispositivosbiofarco@gmail.com
A96: 048842bd | B96: 80a01443 | C96: PRO-015 | D96: 4 | E96: 1 litro | G96: repbiofarco | H96: dispositivosbiofarco@gmail.com
A97: c22fa8ca | B97: 80a01443 | C97: PRO-034 | D97: 2 | G97: repbiofarco | H97: dispositivosbiofarco@gmail.com
A98: 92aea2d1 | B98: 80a01443 | C98: PRO-064 | D98: 1 | G98: repbiofarco | H98: dispositivosbiofarco@gmail.com
A99: 934218ef | B99: 80a01443 | C99: PRO-051 | D99: 2 | G99: repbiofarco | H99: dispositivosbiofarco@gmail.com
A100: cc4f1032 | B100: 334faf19 | C100: eeac8176 | D100: 1 | G100: repbiofarco | H100: dispositivosbiofarco@gmail.com
A101: 81ff843b | B101: 334faf19 | C101: 71df8880269341fce19e2043 | D101: 1 | G101: repbiofarco | H101: dispositivosbiofarco@gmail.com
A102: 9b909154 | B102: ee689f4a | C102: PRO-051 | D102: 3 | G102: repbiofarco | H102: dispositivosbiofarco@gmail.com
A103: 6f23d145 | B103: ee689f4a | C103: PRO-021 | D103: 2 | G103: repbiofarco | H103: dispositivosbiofarco@gmail.com
A104: d8ccfee3 | B104: ee689f4a | C104: PRO-034 | D104: 3 | G104: repbiofarco | H104: dispositivosbiofarco@gmail.com
A105: efe8a009 | B105: ee689f4a | C105: eeac8176 | D105: 1 | G105: repbiofarco | H105: dispositivosbiofarco@gmail.com
A106: 84167d6d | B106: ee689f4a | C106: 71df8880269341fce19e2043 | D106: 1 | G106: repbiofarco | H106: dispositivosbiofarco@gmail.com
A107: a1af2c6b | B107: 835aaea4 | C107: PRO-051 | D107: 2 | G107: repbiofarco | H107: dispositivosbiofarco@gmail.com
A108: 70f4bbe8 | B108: 835aaea4 | C108: PRO-021 | D108: 1 | G108: repbiofarco | H108: dispositivosbiofarco@gmail.com
... A116: 751bd4f4 | B116: 0f72910e | C116: 71df8880269341fce19e2043 | D116: 1 | G116: repbiofarco | H116: dispositivosbiofarco@gmail.com
A117: 42702acf | C117: PRO-004 | D117: 24 | G117: repbiofarco | H117: dispositivosbiofarco@gmail.com
A118: d8bdbb31 | C118: PRO-013 | D118: 2 | G118: repbiofarco | H118: dispositivosbiofarco@gmail.com
A119: a6d91bdd | C119: PRO-033 | D119: 5 | G119: repbiofarco | H119: dispositivosbiofarco@gmail.com
A120: 1ec32752 | C120: PRO-057 | D120: 6 | G120: repbiofarco | H120: dispositivosbiofarco@gmail.com
A121: 6c8b86ad | C121: PRO-050 | D121: 2 | G121: repbiofarco | H121: dispositivosbiofarco@gmail.com
A122: 1b415f4e | C122: PRO-034 | D122: 1 | G122: repbiofarco | H122: dispositivosbiofarco@gmail.com
...

Sheet Cotizaciones
A1: ID_Cotizacion | B1: ID_Visita | C1: ID_Fichero | D1: ID_Farmacia | E1: ID_Drogueria | F1: CondicionCiclo | G1: FechaCreacion | H1: Prioridad | I1: Estado | J1: Archivo | K1: ID_Usuario | L1: SUBMITTED BY
A2: 465ce288 | B2: 58806e4b | D2: 2cb82336 | E2: 4 | G2: 45966 | H2: Media | I2: Aprobada | J2: 1 | K2: repbiofarco | L2: dispositivosbiofarco@gmail.com
A3: 7582d0b8 | B3: 858a5b55 | D3: 48e9fe71 | E3: 2 | G3: 45980 | H3: Media | I3: Aprobada | K3: repbiofarco | L3: dispositivosbiofarco@gmail.com
A4: 57484c41 | B4: bc287360 | D4: f470f649 | E4: 1 | G4: 45982 | H4: Media | I4: Aprobada | J4: 1 | K4: repbiofarco | L4: dispositivosbiofarco@gmail.com
A5: ddb3bd3c | B5: aaa533ec | D5: 0b9ea836 | E5: 061dbd84 | G5: 46148 | H5: Alta | I5: Aprobada | K5: repbiofarco | L5: dispositivosbiofarco@gmail.com

Sheet Productos_X_Cotizacion
A1: ID_Detalle_Cot | B1: ID_Cotizacion | C1: ID_Producto | D1: CantidadSolicitada | E1: PrecioUnitario | F1: Nota | G1: ID_Usuario | H1: SUBMITTED BY
A2: 42bea2b5 | B2: 1d6ae722 | C2: PRO-001 | D2: 2 | G2: repbiofarco | H2: dispositivosbiofarco@gmail.com
A3: 2d459ff2 | B3: 1d6ae722 | C3: PRO-006 | D3: 2 | G3: repbiofarco | H3: dispositivosbiofarco@gmail.com
A4: 1e5c27d8 | B4: 7195c106 | C4: PRO-017 | D4: 2 | G4: repbiofarco | H4: dispositivosbiofarco@gmail.com
A5: 49fa7c8d | B5: 7195c106 | C5: PRO-002 | D5: 5 | G5: repbiofarco | H5: dispositivosbiofarco@gmail.com
A6: 58f9665d | B6: 465ce288 | C6: PRO-013 | D6: 2 | G6: repbiofarco | H6: dispositivosbiofarco@gmail.com
A7: ce8cbb76 | B7: 465ce288 | C7: PRO-033 | D7: 5 | G7: repbiofarco | H7: dispositivosbiofarco@gmail.com
A8: 0036abf3 | B8: 465ce288 | C8: PRO-057 | D8: 6 | F8: Sabor Original | G8: repbiofarco | H8: dispositivosbiofarco@gmail.com
A9: 9ef828a7 | B9: 465ce288 | C9: PRO-050 | D9: 2 | G9: repbiofarco | H9: dispositivosbiofarco@gmail.com
A10: 3f95f2f5 | B10: 465ce288 | C10: PRO-034 | D10: 1 | G10: repbiofarco | H10: dispositivosbiofarco@gmail.com
A11: 6ebf3dce | B11: 57484c41 | C11: PRO-033 | D11: 3 | E11: 479.39 | G11: repbiofarco | H11: dispositivosbiofarco@gmail.com
A12: 9c0046d2 | B12: 57484c41 | C12: PRO-059 | D12: 2 | E12: 5568.42 | G12: repbiofarco | H12: dispositivosbiofarco@gmail.com
A13: df8643e3 | B13: 57484c41 | C13: f39ad541 | D13: 1 | E13: 786.18 | G13: repbiofarco | H13: dispositivosbiofarco@gmail.com
A14: 0dbc1045 | B14: 57484c41 | C14: 5676e0c6 | D14: 1 | E14: 786.18 | G14: repbiofarco | H14: dispositivosbiofarco@gmail.com
A15: 75dcfa0b | B15: 57484c41 | C15: 1f610f8d | D15: 1 | E15: 786.18 | G15: repbiofarco | H15: dispositivosbiofarco@gmail.com
A16: a8f3a790 | B16: 57484c41 | C16: eeac8176 | D16: 1 | E16: 1603.72 | G16: repbiofarco | H16: dispositivosbiofarco@gmail.com
A17: 94c7d409 | B17: 57484c41 | C17: 71df8880269341fce19e2043 | D17: 1 | E17: 1725.75 | G17: repbiofarco | H17: dispositivosbiofarco@gmail.com
A18: c695f7e4 | B18: ddb3bd3c | C18: PRO-026 | D18: 96 | E18: 4.4 | F18: 8% Descuento | G18: repbiofarco | H18: dispositivosbiofarco@gmail.com
A19: 8cc89ee9 | B19: ddb3bd3c | C19: PRO-026-1 | D19: 96 | E19: 4.4 | F19: 8% Descuento | G19: repbiofarco | H19: dispositivosbiofarco@gmail.com
A20: 5a436531 | B20: ddb3bd3c | C20: PRO-035 | D20: 24 | E20: 6 | F20: 7% Descuento | G20: repbiofarco | H20: dispositivosbiofarco@gmail.com
A21: 2a2eb983 | B21: ddb3bd3c | C21: PRO-015 | D21: 60 | E21: 7.5 | F21: 7% Descuento | G21: repbiofarco | H21: dispositivosbiofarco@gmail.com
A22: 1ddb7cf3 | B22: ddb3bd3c | C22: PRO-015-1 | D22: 24 | E22: 5.4 | F22: 8% Descuento | G22: repbiofarco | H22: dispositivosbiofarco@gmail.com
A23: d63fe6c2 | B23: ddb3bd3c | C23: PRO-052 | D23: 60 | E23: 2.3 | F23: 6% Descuento | G23: repbiofarco | H23: dispositivosbiofarco@gmail.com
A24: 4d01dbe5 | B24: ddb3bd3c | C24: PRO-006 | D24: 60 | E24: 2.9 | F24: 6% Descuento | G24: repbiofarco | H24: dispositivosbiofarco@gmail.com
A25: 6bb9b43d | B25: ddb3bd3c | C25: PRO-003 | D25: 60 | E25: 1.1 | F25: 6% Descuento | G25: repbiofarco | H25: dispositivosbiofarco@gmail.com
A26: 1b755bae | B26: ddb3bd3c | C26: PRO-009 | D26: 60 | E26: 0.9 | F26: 6% Descuento | G26: repbiofarco | H26: dispositivosbiofarco@gmail.com
A27: 26780a80 | B27: ddb3bd3c | C27: PRO-011 | D27: 48 | E27: 0.9 | F27: 6% Descuento | G27: repbiofarco | H27: dispositivosbiofarco@gmail.com
A28: 73daaec5 | B28: ddb3bd3c | C28: PRO-010 | D28: 48 | E28: 1.6 | F28: 6% Descuento | G28: repbiofarco | H28: dispositivosbiofarco@gmail.com
A29: 381a9317 | B29: ddb3bd3c | C29: PRO-059 | D29: 48 | E29: 1.9 | F29: 6% Descuento | G29: repbiofarco | H29: dispositivosbiofarco@gmail.com
... A32: 8285ca11 | B32: ddb3bd3c | C32: PRO-043 | D32: 24 | E32: 2.3 | F32: 6% Descuento | G32: repbiofarco | H32: dispositivosbiofarco@gmail.com

Sheet Productos del Pedido
A1: ID_Producto_Pedido | B1: ID_Farmacia | C1: ID_Pedido | D1: Producto | E1: Cantidad | F1: ID_Usuario | G1: SUBMITTED BY
A2: bee24f4a | B2: f470f649 | D2: 3366acf8 | E2: 1 | F2: repbiofarco | G2: dispositivosbiofarco@gmail.com
A3: 581028a9 | B3: f470f649 | D3: a13eb6b6 | E3: 1 | F3: repbiofarco | G3: dispositivosbiofarco@gmail.com
A4: 5b0a3114 | B4: f470f649 | D4: 4f550f56 | E4: 1 | F4: repbiofarco | G4: dispositivosbiofarco@gmail.com
A5: f756aed9 | B5: f470f649 | D5: eeac8176 | E5: 2 | F5: repbiofarco | G5: dispositivosbiofarco@gmail.com
A6: d482b40a | B6: f470f649 | D6: PRO-007 | E6: 2 | F6: repbiofarco | G6: dispositivosbiofarco@gmail.com
A7: 6908964b | B7: f470f649 | D7: PRO-032 | E7: 2 | F7: repbiofarco | G7: dispositivosbiofarco@gmail.com
A8: 3a013bd2 | B8: f470f649 | D8: PRO-032 | E8: 2 | F8: repbiofarco | G8: dispositivosbiofarco@gmail.com

Sheet Drogueria
A1: ID_Drogueria | B1: NombreDrogueria | C1: Codigo_Drogueria | D1: Contacto | E1: Telefono | F1: ID_Usuario | G1: SUBMITTED BY
A2: 1 | B2: DroNena | F2: repbiofarco | G2: dispositivosbiofarco@gmail.com
A3: 2 | B3: VitalClinic | F3: repbiofarco | G3: dispositivosbiofarco@gmail.com
A4: 3 | B4: COBECA | F4: repbiofarco | G4: dispositivosbiofarco@gmail.com
A5: 4 | B5: DrovenCentro | F5: repbiofarco | G5: dispositivosbiofarco@gmail.com
A6: 5 | B6: Dromega | F6: repbiofarco | G6: dispositivosbiofarco@gmail.com
A7: 6 | B7: Crismedical | F7: repbiofarco | G7: dispositivosbiofarco@gmail.com
A8: 7 | B8: VIOVAC | F8: repbiofarco | G8: dispositivosbiofarco@gmail.com
A9: 8 | B9: Insuaminca | F9: repbiofarco | G9: dispositivosbiofarco@gmail.com
A10: 9c0db263 | B10: Bsm Medical | F10: repbiofarco | G10: dispositivosbiofarco@gmail.com
A11: 78a5496c | B11: Zaki Pharma | F11: repbiofarco | G11: dispositivosbiofarco@gmail.com
A12: 65f15348 | B12: Insuaminca | F12: repbiofarco | G12: dispositivosbiofarco@gmail.com
A13: 061dbd83 | B13: DrovenCentro | F13: repbiofarco | G13: dispositivosbiofarco@gmail.com
A14: 061dbd84 | B14: BIOFARCO | F14: repbiofarco | G14: dispositivosbiofarco@gmail.com

Sheet Drogueria_Inventario
A1: ID_Inventario | B1: ID_Drogueria | C1: Codigo_Barras | D1: ID_Producto | E1: CantidadDisponible | F1: Precio | G1: FechaActualizacion | H1: ID_Usuario | I1: SUBMITTED BY
A2: 1 | B2: 1 | C2: 1759161600039 | D2: {=IFERROR(XLOOKUP(TRIM(C2&""), TRIM(Productos!B:B), Productos!A:A), XLOOKUP(TRIM(RIGHT(C2, LEN(C2)-1)&""), TRIM(Productos!B:B), Productos!A:A, " "))} -> PRO-004 | E2: 8 | F2: 26.247937 | G2: 46111 | H2: repbiofarco | I2: dispositivosbiofarco@gmail.com
A3: 2 | B3: 1 | C3: 7591616002272 | D3: {=IFERROR(XLOOKUP(TRIM(C3&""), TRIM(Productos!B:B), Productos!A:A), XLOOKUP(TRIM(RIGHT(C3, LEN(C3)-1)&""), TRIM(Productos!B:B), Productos!A:A, " "))} -> PRO-017 | E3: 23 | F3: 5.2296211 | G3: 46111 | H3: repbiofarco | I3: dispositivosbiofarco@gmail.com
A4: 3 | B4: 1 | C4: 7591616000056 | D4: {=IFERROR(XLOOKUP(TRIM(C4&""), TRIM(Productos!B:B), Productos!A:A), XLOOKUP(TRIM(RIGHT(C4, LEN(C4)-1)&""), TRIM(Productos!B:B), Productos!A:A, " "))} -> PRO-052 | E4: 72 | F4: 3.1238105 | G4: 46111 | H4: repbiofarco | I4: dispositivosbiofarco@gmail.com
A5: 4 | B5: 1 | C5: 7591616000162 | D5: {=IFERROR(XLOOKUP(TRIM(C5&""), TRIM(Productos!B:B), Productos!A:A), XLOOKUP(TRIM(RIGHT(C5, LEN(C5)-1)&""), TRIM(Productos!B:B), Productos!A:A, " "))} -> PRO-005 | E5: 164 | F5: 2.1058316 | G5: 46111 | H5: repbiofarco | I5: dispositivosbiofarco@gmail.com
A6: 5 | B6: 1 | C6: 17591616000138 | D6: {=IFERROR(XLOOKUP(TRIM(C6&""), TRIM(Productos!B:B), Productos!A:A), XLOOKUP(TRIM(RIGHT(C6, LEN(C6)-1)&""), TRIM(Productos!B:B), Productos!A:A, " "))} -> PRO-006 | E6: 23 | F6: 46.906968 | G6: 46111 | H6: repbiofarco | I6: dispositivosbiofarco@gmail.com
A7: 6 | B7: 1 | C7: 7591616002142 | D7: {=IFERROR(XLOOKUP(TRIM(C7&""), TRIM(Productos!B:B), Productos!A:A), XLOOKUP(TRIM(RIGHT(C7, LEN(C7)-1)&""), TRIM(Productos!B:B), Productos!A:A, " "))} -> PRO-002 | E7: 19 | F7: 3.1238105 | G7: 46111 | H7: repbiofarco | I7: dispositivosbiofarco@gmail.com
A8: 7 | B8: 1 | C8: 17591616001463 | D8: {=IFERROR(XLOOKUP(TRIM(C8&""), TRIM(Productos!B:B), Productos!A:A), XLOOKUP(TRIM(RIGHT(C8, LEN(C8)-1)&""), TRIM(Productos!B:B), Productos!A:A, " "))} -> PRO-003 | E8: 41 | F8: 17.325642 | G8: 46111 | H8: repbiofarco | I8: dispositivosbiofarco@gmail.com
A9: 8 | B9: 1 | C9: 7591616000285 | D9: {=IFERROR(XLOOKUP(TRIM(C9&""), TRIM(Productos!B:B), Productos!A:A), XLOOKUP(TRIM(RIGHT(C9, LEN(C9)-1)&""), TRIM(Productos!B:B), Productos!A:A, " "))} -> PRO-007 | E9: 96 | F9: 4.6208421 | G9: 46111 | H9: repbiofarco | I9: dispositivosbiofarco@gmail.com
A10: 9 | B10: 1 | C10: 7591616000315 | D10: {=IFERROR(XLOOKUP(TRIM(C10&""), TRIM(Productos!B:B), Productos!A:A), XLOOKUP(TRIM(RIGHT(C10, LEN(C10)-1)&""), TRIM(Productos!B:B), Productos!A:A, " "))} -> PRO-007-1 | E10: 402 | F10: 2.1058316 | G10: 46111 | H10: repbiofarco | I10: dispositivosbiofarco@gmail.com
A11: 10 | B11: 1 | C11: 7591616000261 | D11: {=IFERROR(XLOOKUP(TRIM(C11&""), TRIM(Productos!B:B), Productos!A:A), XLOOKUP(TRIM(RIGHT(C11, LEN(C11)-1)&""), TRIM(Productos!B:B), Productos!A:A, " "))} -> PRO-007-2 | E11: 138 | F11: 2.9441684 | G11: 46111 | H11: repbiofarco | I11: dispositivosbiofarco@gmail.com
A12: 11 | B12: 1 | C12: 7591616002111 | D12: {=IFERROR(XLOOKUP(TRIM(C12&""), TRIM(Productos!B:B), Productos!A:A), XLOOKUP(TRIM(RIGHT(C12, LEN(C12)-1)&""), TRIM(Productos!B:B), Productos!A:A, " "))} -> PRO-053 | E12: 60 | F12: 2.4651158 | G12: 46111 | H12: repbiofarco | I12: dispositivosbiofarco@gmail.com
A13: 12 | B13: 1 | C13: 17591616000343 | D13: {=IFERROR(XLOOKUP(TRIM(C13&""), TRIM(Productos!B:B), Productos!A:A), XLOOKUP(TRIM(RIGHT(C13, LEN(C13)-1)&""), TRIM(Productos!B:B), Productos!A:A, " "))} -> PRO-008 | E13: 0 | F13: 2.7463158 | G13: 46041 | H13: repbiofarco | I13: dispositivosbiofarco@gmail.com
... A131: 130 | B131: 3 | C131: 7599558000042 | D131: {=IFERROR(XLOOKUP(TRIM(C131&""), TRIM(Productos!B:B), Productos!A:A), XLOOKUP(TRIM(RIGHT(C131, LEN(C131)-1)&""), TRIM(Productos!B:B), Productos!A:A, " "))} -> PRO-065-1 | E131: 9 | F131: 14.86 | G131: 46119 | H131: repbiofarco | I131: dispositivosbiofarco@gmail.com
A132: 131 | B132: 061dbd83 | C132: 7591616000032 | D132: {=IFERROR(XLOOKUP(TRIM(C132&""), TRIM(Productos!B:B), Productos!A:A), XLOOKUP(TRIM(RIGHT(C132, LEN(C132)-1)&""), TRIM(Productos!B:B), Productos!A:A, " "))} | E132: 12 | F132: 2.19 | G132: 46119 | H132: repbiofarco | I132: dispositivosbiofarco@gmail.com
A133: 132 | B133: 061dbd83 | C133: 7591616000162 | D133: {=IFERROR(XLOOKUP(TRIM(C133&""), TRIM(Productos!B:B), Productos!A:A), XLOOKUP(TRIM(RIGHT(C133, LEN(C133)-1)&""), TRIM(Productos!B:B), Productos!A:A, " "))} -> PRO-005 | E133: 222 | F133: 2.11 | G133: 46119 | H133: repbiofarco | I133: dispositivosbiofarco@gmail.com
A134: 133 | B134: 061dbd83 | C134: 7591616001466 | D134: {=IFERROR(XLOOKUP(TRIM(C134&""), TRIM(Productos!B:B), Productos!A:A), XLOOKUP(TRIM(RIGHT(C134, LEN(C134)-1)&""), TRIM(Productos!B:B), Productos!A:A, " "))} | E134: 9 | F134: 1.43 | G134: 46119 | H134: repbiofarco | I134: dispositivosbiofarco@gmail.com
A135: 134 | B135: 061dbd83 | C135: 7591616000285 | D135: {=IFERROR(XLOOKUP(TRIM(C135&""), TRIM(Productos!B:B), Productos!A:A), XLOOKUP(TRIM(RIGHT(C135, LEN(C135)-1)&""), TRIM(Productos!B:B), Productos!A:A, " "))} -> PRO-007 | E135: 61 | F135: 4.64 | G135: 46119 | H135: repbiofarco | I135: dispositivosbiofarco@gmail.com
A136: 135 | B136: 061dbd83 | C136: 7591616002111 | D136: {=IFERROR(XLOOKUP(TRIM(C136&""), TRIM(Productos!B:B), Productos!A:A), XLOOKUP(TRIM(RIGHT(C136, LEN(C136)-1)&""), TRIM(Productos!B:B), Productos!A:A, " "))} -> PRO-053 | E136: 12 | F136: 2.44 | G136: 46119 | H136: repbiofarco | I136: dispositivosbiofarco@gmail.com
A137: 136 | B137: 061dbd83 | C137: 7591616000346 | D137: {=IFERROR(XLOOKUP(TRIM(C137&""), TRIM(Productos!B:B), Productos!A:A), XLOOKUP(TRIM(RIGHT(C137, LEN(C137)-1)&""), TRIM(Productos!B:B), Productos!A:A, " "))} | E137: 30 | F137: 3.54 | G137: 46119 | H137: repbiofarco | I137: dispositivosbiofarco@gmail.com
A138: 137 | B138: 061dbd83 | C138: 7591616001480 | D138: {=IFERROR(XLOOKUP(TRIM(C138&""), TRIM(Productos!B:B), Productos!A:A), XLOOKUP(TRIM(RIGHT(C138, LEN(C138)-1)&""), TRIM(Productos!B:B), Productos!A:A, " "))} | E138: 14 | F138: 1.26 | G138: 46119 | H138: repbiofarco | I138: dispositivosbiofarco@gmail.com
A139: 138 | B139: 061dbd83 | C139: 7591616001510 | D139: {=IFERROR(XLOOKUP(TRIM(C139&""), TRIM(Productos!B:B), Productos!A:A), XLOOKUP(TRIM(RIGHT(C139, LEN(C139)-1)&""), TRIM(Productos!B:B), Productos!A:A, " "))} | E139: 51 | F139: 1.18 | G139: 46119 | H139: repbiofarco | I139: dispositivosbiofarco@gmail.com
A140: 139 | B140: 061dbd83 | C140: 7591616000360 | D140: {=IFERROR(XLOOKUP(TRIM(C140&""), TRIM(Productos!B:B), Productos!A:A), XLOOKUP(TRIM(RIGHT(C140, LEN(C140)-1)&""), TRIM(Productos!B:B), Productos!A:A, " "))} -> PRO-010 | E140: 5 | F140: 1.6 | G140: 46119 | H140: repbiofarco | I140: dispositivosbiofarco@gmail.com
A141: 140 | B141: 061dbd83 | C141: 7591616002227 | D141: {=IFERROR(XLOOKUP(TRIM(C141&""), TRIM(Productos!B:B), Productos!A:A), XLOOKUP(TRIM(RIGHT(C141, LEN(C141)-1)&""), TRIM(Productos!B:B), Productos!A:A, " "))} -> PRO-028 | E141: 39 | F141: 4.89 | G141: 46119 | H141: repbiofarco | I141: dispositivosbiofarco@gmail.com
A142: 141 | B142: 061dbd83 | C142: 7591616000704 | D142: {=IFERROR(XLOOKUP(TRIM(C142&""), TRIM(Productos!B:B), Productos!A:A), XLOOKUP(TRIM(RIGHT(C142, LEN(C142)-1)&""), TRIM(Productos!B:B), Productos!A:A, " "))} -> PRO-015 | E142: 36 | F142: 10.03 | G142: 46119 | H142: repbiofarco | I142: dispositivosbiofarco@gmail.com
A143: 142 | B143: 061dbd83 | C143: 7591616002937 | D143: {=IFERROR(XLOOKUP(TRIM(C143&""), TRIM(Productos!B:B), Productos!A:A), XLOOKUP(TRIM(RIGHT(C143, LEN(C143)-1)&""), TRIM(Productos!B:B), Productos!A:A, " "))} -> PRO-015-1 | E143: 41 | F143: 7.25 | G143: 46119 | H143: repbiofarco | I143: dispositivosbiofarco@gmail.com
... A153: 152 | B153: 061dbd83 | C153: 7591616001916 | D153: {=IFERROR(XLOOKUP(TRIM(C153&""), TRIM(Productos!B:B), Productos!A:A), XLOOKUP(TRIM(RIGHT(C153, LEN(C153)-1)&""), TRIM(Productos!B:B), Productos!A:A, " "))} -> PRO-043 | E153: 23 | F153: 5.02 | G153: 46119 | H153: repbiofarco | I153: dispositivosbiofarco@gmail.com
A154: 153 | B154: 78a5496c | C154: 7591616002272 | D154: {=IFERROR(XLOOKUP(TRIM(C154&""), TRIM(Productos!B:B), Productos!A:A), XLOOKUP(TRIM(RIGHT(C154, LEN(C154)-1)&""), TRIM(Productos!B:B), Productos!A:A, " "))} -> PRO-017 | F154: 5.07 | G154: 46119 | H154: repbiofarco | I154: dispositivosbiofarco@gmail.com
A155: 154 | B155: 78a5496c | C155: 7591616000131 | D155: {=IFERROR(XLOOKUP(TRIM(C155&""), TRIM(Productos!B:B), Productos!A:A), XLOOKUP(TRIM(RIGHT(C155, LEN(C155)-1)&""), TRIM(Productos!B:B), Productos!A:A, " "))} | F155: 3.79 | G155: 46119 | H155: repbiofarco | I155: dispositivosbiofarco@gmail.com
A156: 155 | B156: 78a5496c | C156: 7591616000162 | D156: {=IFERROR(XLOOKUP(TRIM(C156&""), TRIM(Productos!B:B), Productos!A:A), XLOOKUP(TRIM(RIGHT(C156, LEN(C156)-1)&""), TRIM(Productos!B:B), Productos!A:A, " "))} -> PRO-005 | F156: 2.04 | G156: 46119 | H156: repbiofarco | I156: dispositivosbiofarco@gmail.com
A157: 156 | B157: 78a5496c | C157: 7591616002142 | D157: {=IFERROR(XLOOKUP(TRIM(C157&""), TRIM(Productos!B:B), Productos!A:A), XLOOKUP(TRIM(RIGHT(C157, LEN(C157)-1)&""), TRIM(Productos!B:B), Productos!A:A, " "))} -> PRO-002 | F157: 3.16 | G157: 46119 | H157: repbiofarco | I157: dispositivosbiofarco@gmail.com
A158: 157 | B158: 78a5496c | C158: 7591616001466 | D158: {=IFERROR(XLOOKUP(TRIM(C158&""), TRIM(Productos!B:B), Productos!A:A), XLOOKUP(TRIM(RIGHT(C158, LEN(C158)-1)&""), TRIM(Productos!B:B), Productos!A:A, " "))} | F158: 1.47 | G158: 46119 | H158: repbiofarco | I158: dispositivosbiofarco@gmail.com
A159: 158 | B159: 78a5496c | C159: 7591616001480 | D159: {=IFERROR(XLOOKUP(TRIM(C159&""), TRIM(Productos!B:B), Productos!A:A), XLOOKUP(TRIM(RIGHT(C159, LEN(C159)-1)&""), TRIM(Productos!B:B), Productos!A:A, " "))} | F159: 1.23 | G159: 46119 | H159: repbiofarco | I159: dispositivosbiofarco@gmail.com
A160: 159 | B160: 78a5496c | C160: 7591616000360 | D160: {=IFERROR(XLOOKUP(TRIM(C160&""), TRIM(Productos!B:B), Productos!A:A), XLOOKUP(TRIM(RIGHT(C160, LEN(C160)-1)&""), TRIM(Productos!B:B), Productos!A:A, " "))} -> PRO-010 | F160: 2.16 | G160: 46119 | H160: repbiofarco | I160: dispositivosbiofarco@gmail.com
A161: 160 | B161: 78a5496c | C161: 7591616002227 | D161: {=IFERROR(XLOOKUP(TRIM(C161&""), TRIM(Productos!B:B), Productos!A:A), XLOOKUP(TRIM(RIGHT(C161, LEN(C161)-1)&""), TRIM(Productos!B:B), Productos!A:A, " "))} -> PRO-028 | F161: 4.72 | G161: 46119 | H161: repbiofarco | I161: dispositivosbiofarco@gmail.com
A162: 161 | B162: 78a5496c | C162: 7591616002234 | D162: {=IFERROR(XLOOKUP(TRIM(C162&""), TRIM(Productos!B:B), Productos!A:A), XLOOKUP(TRIM(RIGHT(C162, LEN(C162)-1)&""), TRIM(Productos!B:B), Productos!A:A, " "))} -> PRO-028-1 | F162: 6.71 | G162: 46119 | H162: repbiofarco | I162: dispositivosbiofarco@gmail.com
A163: 162 | B163: 78a5496c | C163: 7591616002159 | D163: {=IFERROR(XLOOKUP(TRIM(C163&""), TRIM(Productos!B:B), Productos!A:A), XLOOKUP(TRIM(RIGHT(C163, LEN(C163)-1)&""), TRIM(Productos!B:B), Productos!A:A, " "))} -> PRO-013 | F163: 6.3 | G163: 46119 | H163: repbiofarco | I163: dispositivosbiofarco@gmail.com
A164: 163 | B164: 78a5496c | C164: 7591616002944 | D164: {=IFERROR(XLOOKUP(TRIM(C164&""), TRIM(Productos!B:B), Productos!A:A), XLOOKUP(TRIM(RIGHT(C164, LEN(C164)-1)&""), TRIM(Productos!B:B), Productos!A:A, " "))} -> PRO-016-1 | F164: 7.4 | G164: 46119 | H164: repbiofarco | I164: dispositivosbiofarco@gmail.com
A165: 164 | B165: 78a5496c | C165: 7591616002951 | D165: {=IFERROR(XLOOKUP(TRIM(C165&""), TRIM(Productos!B:B), Productos!A:A), XLOOKUP(TRIM(RIGHT(C165, LEN(C165)-1)&""), TRIM(Productos!B:B), Productos!A:A, " "))} -> PRO-016 | F165: 6.06 | G165: 46119 | H165: repbiofarco | I165: dispositivosbiofarco@gmail.com
... A188: 187 | B188: 78a5496c | C188: 7591616002135 | D188: {=IFERROR(XLOOKUP(TRIM(C188&""), TRIM(Productos!B:B), Productos!A:A), XLOOKUP(TRIM(RIGHT(C188, LEN(C188)-1)&""), TRIM(Productos!B:B), Productos!A:A, " "))} -> PRO-048 | F188: 3.2 | G188: 46119 | H188: repbiofarco | I188: dispositivosbiofarco@gmail.com
A189: 188 | B189: 061dbd84 | C189: 1759161600039 | D189: {=IFERROR(XLOOKUP(TRIM(C189&""), TRIM(Productos!B:B), Productos!A:A), XLOOKUP(TRIM(RIGHT(C189, LEN(C189)-1)&""), TRIM(Productos!B:B), Productos!A:A, " "))} -> PRO-004 | E189: 8 | F189: 26.247937 | G189: 46147 | H189: repbiofarco | I189: dispositivosbiofarco@gmail.com
A190: 189 | B190: 061dbd84 | C190: 7591616002272 | D190: {=IFERROR(XLOOKUP(TRIM(C190&""), TRIM(Productos!B:B), Productos!A:A), XLOOKUP(TRIM(RIGHT(C190, LEN(C190)-1)&""), TRIM(Productos!B:B), Productos!A:A, " "))} -> PRO-017 | E190: 23 | F190: 5.2296211 | G190: 46147 | H190: repbiofarco | I190: dispositivosbiofarco@gmail.com
A191: 190 | B191: 061dbd84 | C191: 7591616000056 | D191: {=IFERROR(XLOOKUP(TRIM(C191&""), TRIM(Productos!B:B), Productos!A:A), XLOOKUP(TRIM(RIGHT(C191, LEN(C191)-1)&""), TRIM(Productos!B:B), Productos!A:A, " "))} -> PRO-052 | E191: 72 | F191: 3.1238105 | G191: 46147 | H191: repbiofarco | I191: dispositivosbiofarco@gmail.com
A192: 191 | B192: 061dbd84 | C192: 7591616000162 | D192: {=IFERROR(XLOOKUP(TRIM(C192&""), TRIM(Productos!B:B), Productos!A:A), XLOOKUP(TRIM(RIGHT(C192, LEN(C192)-1)&""), TRIM(Productos!B:B), Productos!A:A, " "))} -> PRO-005 | E192: 164 | F192: 2.1058316 | G192: 46147 | H192: repbiofarco | I192: dispositivosbiofarco@gmail.com
A193: 192 | B193: 061dbd84 | C193: 17591616000138 | D193: {=IFERROR(XLOOKUP(TRIM(C193&""), TRIM(Productos!B:B), Productos!A:A), XLOOKUP(TRIM(RIGHT(C193, LEN(C193)-1)&""), TRIM(Productos!B:B), Productos!A:A, " "))} -> PRO-006 | E193: 23 | F193: 46.906968 | G193: 46147 | H193: repbiofarco | I193: dispositivosbiofarco@gmail.com
A194: 193 | B194: 061dbd84 | C194: 7591616002142 | D194: {=IFERROR(XLOOKUP(TRIM(C194&""), TRIM(Productos!B:B), Productos!A:A), XLOOKUP(TRIM(RIGHT(C194, LEN(C194)-1)&""), TRIM(Productos!B:B), Productos!A:A, " "))} -> PRO-002 | E194: 19 | F194: 3.1238105 | G194: 46147 | H194: repbiofarco | I194: dispositivosbiofarco@gmail.com
A195: 194 | B195: 061dbd84 | C195: 17591616001463 | D195: {=IFERROR(XLOOKUP(TRIM(C195&""), TRIM(Productos!B:B), Productos!A:A), XLOOKUP(TRIM(RIGHT(C195, LEN(C195)-1)&""), TRIM(Productos!B:B), Productos!A:A, " "))} -> PRO-003 | E195: 41 | F195: 17.325642 | G195: 46147 | H195: repbiofarco | I195: dispositivosbiofarco@gmail.com
A196: 195 | B196: 061dbd84 | C196: 7591616000285 | D196: {=IFERROR(XLOOKUP(TRIM(C196&""), TRIM(Productos!B:B), Productos!A:A), XLOOKUP(TRIM(RIGHT(C196, LEN(C196)-1)&""), TRIM(Productos!B:B), Productos!A:A, " "))} -> PRO-007 | E196: 96 | F196: 4.6208421 | G196: 46147 | H196: repbiofarco | I196: dispositivosbiofarco@gmail.com
A197: 196 | B197: 061dbd84 | C197: 7591616000315 | D197: {=IFERROR(XLOOKUP(TRIM(C197&""), TRIM(Productos!B:B), Productos!A:A), XLOOKUP(TRIM(RIGHT(C197, LEN(C197)-1)&""), TRIM(Productos!B:B), Productos!A:A, " "))} -> PRO-007-1 | E197: 402 | F197: 2.1058316 | G197: 46147 | H197: repbiofarco | I197: dispositivosbiofarco@gmail.com
A198: 197 | B198: 061dbd84 | C198: 7591616000261 | D198: {=IFERROR(XLOOKUP(TRIM(C198&""), TRIM(Productos!B:B), Productos!A:A), XLOOKUP(TRIM(RIGHT(C198, LEN(C198)-1)&""), TRIM(Productos!B:B), Productos!A:A, " "))} -> PRO-007-2 | E198: 138 | F198: 2.9441684 | G198: 46147 | H198: repbiofarco | I198: dispositivosbiofarco@gmail.com
A199: 198 | B199: 061dbd84 | C199: 7591616002111 | D199: {=IFERROR(XLOOKUP(TRIM(C199&""), TRIM(Productos!B:B), Productos!A:A), XLOOKUP(TRIM(RIGHT(C199, LEN(C199)-1)&""), TRIM(Productos!B:B), Productos!A:A, " "))} -> PRO-053 | E199: 60 | F199: 2.4651158 | G199: 46147 | H199: repbiofarco | I199: dispositivosbiofarco@gmail.com
A200: 199 | B200: 061dbd84 | C200: 17591616000343 | D200: {=IFERROR(XLOOKUP(TRIM(C200&""), TRIM(Productos!B:B), Productos!A:A), XLOOKUP(TRIM(RIGHT(C200, LEN(C200)-1)&""), TRIM(Productos!B:B), Productos!A:A, " "))} -> PRO-008 | E200: 0 | F200: 2.7463158 | G200: 46147 | H200: repbiofarco | I200: dispositivosbiofarco@gmail.com
... A236: 235 | B236: 061dbd84 | C236: 7599558000103 | D236: {=IFERROR(XLOOKUP(TRIM(C236&""), TRIM(Productos!B:B), Productos!A:A), XLOOKUP(TRIM(RIGHT(C236, LEN(C236)-1)&""), TRIM(Productos!B:B), Productos!A:A, " "))} -> PRO-051 | E236: 212 | F236: 4.7006737 | G236: 46147 | H236: repbiofarco | I236: dispositivosbiofarco@gmail.com

Sheet Farmacias_X_Droguerias
A1: ID_Relacion | B1: ID_Farmacia | C1: ID_Drogueria | D1: CodigoAsignado
A2: a7a9a363 | B2: f470f649 | C2: 1 | D2: E573
A3: cb264920 | B3: 48e9fe71 | C3: 2 | D3: 1296
A4: 29d05331 | B4: 67a0121b | C4: 1 | D4: E542
A5: 4f2027f7 | B5: cfaf6844 | C5: 1 | D5: D635
A6: 2c0c7031 | B6: 22 | C6: 1 | D6: Centro +157
A7: a3e550f3 | B7: 18ea49b4 | C7: 1 | D7: C686
A8: 5e2426f0 | B8: 964789a9 | C8: 1 | D8: D006
A9: 123376ed | B9: 137cdbda | C9: 1 | D9: 6050
A10: 72fdc652 | B10: 4fde48bf | C10: 1 | D10: 7633
A11: 5ce59900 | B11: 4fde48bf | C11: 3 | D11: R28711
A12: ff7bc8e3 | B12: 4fde48bf | C12: 4 | D12: 600010
... A22: 93c99e23 | B22: 69b36f13 | C22: 3 | D22: 28929
A23: 7475c5a7 | B23: bc2518f8 | C23: 9c0db263
A24: 001c5c7e | B24: bc2518f8 | C24: 78a5496c
A25: 7b387f93 | B25: 2cb82336 | C25: 4 | D25: 600445
A26: 6a33e24a | B26: 2cb82336 | C26: 8 | D26: 03345
A27: 7b387f94 | B27: 0b9ea836 | C27: 061dbd84 | D27: Harissa05052026

Sheet Contactos
A1: ID_Contacto | B1: Tipo Contacto | C1: Nombre Completo | D1: Dirección | E1: Ciudad | F1: Estado | G1: Teléfono Principal | H1: Email | I1: Notas Adicionales | J1: Última Visita | K1: Foto del Contacto | L1: Fecha de Nacimiento | M1: Instagram | N1: ID_Usuario | O1: SUBMITTED BY

Sheet Asistencia
A1: AsistenciaID | B1: UsuarioID | C1: EventoID | D1: AsistenciaFechaHora | E1: AsistenciaFecha | F1: AsistenciaHora | G1: AsistenciaGPS | H1: ID_Visita | I1: AsistenciaComentario | J1: ID_Usuario | K1: SUBMITTED BY
A2: 16dc9a8a | B2: cascanior | C2: Entrada | D2: 45911.9 | E2: 45911 | F2: 0.90039352 | G2: 10.227042, -67.603884 | J2: repbiofarco | K2: dispositivosbiofarco@gmail.com
A3: 6406aa1d | B3: cascanior | C3: Entrada | D3: 45912.355 | E3: 45912 | F3: 0.35525463 | G3: 10.267768, -67.587984 | J3: repbiofarco | K3: dispositivosbiofarco@gmail.com
A4: 6999a397 | B4: cascanior | C4: Salida | D4: 45912.747 | E4: 45912 | F4: 0.74674769 | G4: 0.000000, 0.000000 | J4: repbiofarco | K4: dispositivosbiofarco@gmail.com
A5: ec2d42af | B5: cascanior | C5: Entrada | D5: 45915.509 | E5: 45915 | F5: 0.50895833 | G5: 10.251565, -67.599711 | J5: repbiofarco | K5: dispositivosbiofarco@gmail.com
A6: 4f074ccc | B6: cascanior | C6: Entrada | D6: 45922.403 | E6: 45922 | F6: 0.40267361 | G6: 10.170435, -67.580060 | J6: repbiofarco | K6: dispositivosbiofarco@gmail.com
A7: d77d4ce3 | B7: cascanior | C7: Salida | D7: 45922.68 | E7: 45922 | F7: 0.6802662 | G7: 10.227046, -67.603888 | J7: repbiofarco | K7: dispositivosbiofarco@gmail.com
A8: 7b234c5f | B8: cascanior | C8: Entrada | D8: 45923.542 | E8: 45923 | F8: 0.54175926 | G8: 10.227048, -67.603889 | J8: repbiofarco | K8: dispositivosbiofarco@gmail.com
A9: b853d0ee | B9: cascanior | C9: Salida | D9: 45923.704 | E9: 45923 | F9: 0.70405093 | G9: 10.227051, -67.603897 | J9: repbiofarco | K9: dispositivosbiofarco@gmail.com
A10: 1a49fa53 | B10: cascanior | C10: Entrada | D10: 45925.518 | E10: 45925 | F10: 0.51798611 | G10: 10.227061, -67.603883 | J10: repbiofarco | K10: dispositivosbiofarco@gmail.com
A11: 023e9dc8 | B11: cascanior | C11: Entrada | D11: 45929.601 | E11: 45929 | F11: 0.60056713 | G11: 10.254965, -67.597007 | J11: repbiofarco | K11: dispositivosbiofarco@gmail.com
A12: fba244bf | B12: cascanior | C12: Entrada | D12: 45931.304 | E12: 45931 | F12: 0.30440972 | G12: 10.273820, -67.588342 | J12: repbiofarco | K12: dispositivosbiofarco@gmail.com
A13: 7e0cdb2b | B13: cascanior | C13: Entrada | D13: 45933.478 | E13: 45933 | F13: 0.47792824 | G13: 10.256186, -67.598374 | J13: repbiofarco | K13: dispositivosbiofarco@gmail.com
... A22: abaf5eae | B22: cascanior | C22: Entrada | D22: 46132.389 | E22: 46132 | F22: 0.38871528 | G22: 0.000000, 0.000000 | J22: repbiofarco | K22: dispositivosbiofarco@gmail.com
A23: 68eed71e | B23: cascanior | C23: Visita | D23: 46132.389 | E23: 46132 | F23: 0.3890162 | G23: 0.000000, 0.000000 | H23: 52a79e29 | I23: Auditoría de Inventario | Enfoque: Verificar presencia del portafolio e inducir a transferencias. | J23: repbiofarco | K23: dispositivosbiofarco@gmail.com

Sheet Horario
A1: HorarioID | B1: PerfilID | C1: HorarioEntrada | D1: HorarioSalida | E1: ID_Usuario | F1: SUBMITTED BY

Sheet Eventos
A1: EventoID | B1: Categoria
A2: Entrada | B2: Jornada
A3: Salida | B3: Jornada
A4: Visita | B4: Productividad
A5: Supervisión | B5: Productividad
A6: Charla | B6: Productividad
A7: Día Producto | B7: Productividad
A8: Permiso | B8: Licencia
A9: Vacaciones | B9: Licencia
A10: Inasitencia | B10: Licencia

Sheet Visitas
A1: ID_Visita | B1: FechaHora | C1: Fecha | D1: Hora Llegada | E1: Hora Salida | F1: Tipo Contacto Visitado | G1: Contacto_Visitado_Ref | H1: Medico Visitado Ref | I1: Farmacia Visitada Ref | J1: CondicionCiclo | K1: ObjetivoDeVisita | L1: Productos_Presentados | M1: Lote_Muestra | N1: Muestra Entregada | O1: Materiales Promocionales Entregados | P1: Interés del Médico | Q1: Productos_Prescito | R1: Resultados y Notas | S1: Seguimiento Pendiente | T1: Compromiso_Recetas | U1: Etiquetas_Valor | V1: Próxima Fecha Visita Sugerida | W1: Geolocalización | X1: ZonaID | Y1: Representante | Z1: ActividadRealizada | AA1: ProximoPaso | AB1: ObservacionesFeedback | AC1: ContactoClave | AD1: Estado_Visita | AE1: ActividadCompetencia | AF1: FotoEstanteria | AG1: File | AH1: Driver_Compra | AI1: Motivo_Cierre | AJ1: Reaccion_Contacto | AK1: Motivo_Compra_Detectado | AL1: Objecion_Principal | AM1: Compromiso_Cierre | AN1: ID_Usuario | AO1: SUBMITTED BY
A2: 52a79e29 | B2: 46128.651 | C2: 46128 | D2: 0.65133102 | E2: 0.66869213 | F2: Farmacias | I2: 101 | K2: Impulso jornada | L2: PRO-013 , PRO-026 , PRO-026-1 , PRO-035 , PRO-051 | O2: 8b0715c5 | V2: 46163.651 | W2: 10.234453, -67.595470 | AC2: Dra. Lorena | AD2: Programada | AN2: repbiofarco | AO2: dispositivosbiofarco@gmail.com
A3: 927fcde0 | B3: 46135.446 | C3: 46135 | D3: 0.44577546 | E3: 0.46313657 | F3: Farmacias | I3: 48a0193b | K3: Día Producto | L3: PRO-013 , PRO-026 , PRO-026-1 , PRO-035 , PRO-051 | N3: 1 | O3: 8b0715c5 | V3: 46170.446 | W3: 10.226134, -67.334303 | AD3: Programada | AN3: repbiofarco | AO3: dispositivosbiofarco@gmail.com
A4: b2644066 | B4: 46136.404 | C4: 46136 | D4: 0.40356481 | E4: 0.42092593 | F4: Farmacias | I4: 96 | K4: Inventario | V4: 46164.404 | W4: 10.233301, -67.596599 | AD4: Programada | AN4: repbiofarco | AO4: dispositivosbiofarco@gmail.com
A5: 6bc63a3c | B5: 46139.39 | C5: 46139 | D5: 0.39017361 | E5: 0.40753472 | F5: Farmacias | I5: c3aaef31 | K5: Inauguración sede El limón | V5: 46167.39 | W5: 10.292011, -67.627505 | AC5: Ma Fernanda Montaña 04243077275 | AD5: Programada | AN5: repbiofarco | AO5: dispositivosbiofarco@gmail.com
A6: a444dc99 | B6: 46140.366 | C6: 46140 | D6: 0.36631944 | E6: 0.38368056 | F6: Farmacias | I6: 51 | K6: Inventario | V6: 46168.366 | W6: 10.252805, -67.605656 | AD6: Programada | AO6: dispositivosbiofarco@gmail.com
A7: 4caa45b5 | B7: 46140.368 | C7: 46140 | D7: 0.36834491 | E7: 0.38570602 | F7: Farmacias | I7: 52 | V7: 46168.368 | W7: 10.252733, -67.605628 | AD7: Programada | AO7: dispositivosbiofarco@gmail.com
A8: 988a6802 | B8: 46140.37 | C8: 46140 | D8: 0.36975694 | E8: 0.38711806 | F8: Farmacias | I8: 40c45c41 | V8: 46168.37 | W8: 10.252559, -67.604576 | AD8: Programada | AO8: dispositivosbiofarco@gmail.com
A9: 7d0dd48f | B9: 46140.371 | C9: 46140 | D9: 0.37145833 | E9: 0.38881944 | F9: Farmacias | I9: 708d54e0 | V9: 46168.371 | W9: 10.252421, -67.603963 | AD9: Programada | AO9: dispositivosbiofarco@gmail.com
A10: 293b9e81 | B10: 46140.374 | C10: 46140 | D10: 0.37407407 | E10: 0.39143519 | F10: Farmacias | I10: 67a0121b | V10: 46168.374 | W10: 10.252326, -67.603788 | AD10: Programada | AO10: dispositivosbiofarco@gmail.com
A11: 71609c27 | B11: 46140.378 | C11: 46140 | D11: 0.37835648 | E11: 0.39571759 | F11: Farmacias | G11: 67a0121b | I11: 67a0121b | V11: 46168.378 | W11: 10.253542, -67.603517 | AD11: Programada | AO11: dispositivosbiofarco@gmail.com
A12: aaa533ec | B12: 46147.715 | C12: 46147 | D12: 0.71520833 | E12: 0.73256944 | F12: Droguerías | G12: 0b9ea836 | I12: 0b9ea836 | K12: Generar pedido | V12: 46175.715 | W12: 0.000000, 0.000000 | AD12: Programada | AN12: cascanio | AO12: cesar.ascanio@gmail.com

Sheet PlanificacionSemanal
A1: ID_Plan | B1: ID_Ciclo | C1: Semana | D1: FechaInicio | E1: FechaFin | F1: Estado | G1: ID_Usuario | H1: SUBMITTED BY
A2: abr. 43 | B2: 46116 | C2: 16 | D2: 46125 | E2: 46129 | F2: Vigente | G2: repbiofarco | H2: dispositivosbiofarco@gmail.com
A3: abr. 44 | B3: 46116 | C3: 17 | D3: 46132 | E3: 46136 | F3: Pendiente | G3: repbiofarco | H3: dispositivosbiofarco@gmail.com
A4: abr. 45 | B4: 46116 | C4: 18 | D4: 46139 | E4: 46143 | F4: Pendiente | G4: repbiofarco | H4: dispositivosbiofarco@gmail.com

Sheet DetallePlanificacion
A1: ID_DetallePlan | B1: ID_Plan | C1: Fecha | D1: DiaSemana | E1: Jornada | F1: TipoActividad | G1: ID_Fichero | H1: Servicio | I1: ObjetivoEstrategico | J1: Farmacia_Relacionada | K1: ID_Usuario | L1: SUBMITTED BY

Sheet Actividades
A1: ID_Actividad | B1: Tipo_Actividad | C1: Fecha | D1: Hospital_Ref | E1: Participantes | F1: Comision_Monto | G1: ID_Ciclo_Activo | H1: ID_Usuario | I1: SUBMITTED BY

Sheet Evento
A1: ID_Evento | B1: NombreEvento | C1: TipoEvento | D1: FechaPropuesta | E1: ID_FicheroAsociado | F1: PublicoObjetivo | G1: ObjetivosCiclo | H1: Estado | I1: PropuestoPor | J1: FechaAprobacion | K1: AprobadoPor | L1: NumeroAsistentes | M1: ResultadosClave | N1: ID_Usuario | O1: SUBMITTED BY
A2: 05d4ab7a | B2: Día de Impulso Farmacias Mundo Total | C2: Actividad en Farmacia | D2: 45961 | F2: Particulares en tienda | G2: Realizar impulso de los productos BIOFARCO existentes en la farmacia | H2: Aprobado | I2: cesarascaniofp.us@gmail.com | J2: 45957 | K2: gtebiofarco | L2: 100 | N2: repbiofarco | O2: dispositivosbiofarco@gmail.com
A3: 7c812b80 | B3: Charla Mundo Pharma Av. Bolívar | C3: Actividad Académica | D3: 46140 | F3: Personal de mostrador | G3: Refrescamiento de marca y productos | H3: Aprobado | I3: dispositivosbiofarco@gmail.com | J3: 46132 | K3: gtebiofarco | L3: 6 | N3: repbiofarco | O3: dispositivosbiofarco@gmail.com

Sheet Recursos_Solicitados
A1: ID_SolicitudRecurso | B1: ID_Evento | C1: TipoRecurso | D1: ID_Producto | E1: Cantidad | F1: Descripcion | G1: EstadoRecurso | H1: ID_Usuario | I1: SUBMITTED BY
A2: 057ec1d8 | B2: 05d4ab7a | C2: Material POP | E2: 100 | F2: Para entregar a los asistentes | G2: Aprobado | H2: repbiofarco | I2: dispositivosbiofarco@gmail.com
A3: 6a31f2ff | B3: 05d4ab7a | C3: Muestras Médicas | D3: PRO-002 | E3: 12 | G3: Aprobado | H3: repbiofarco | I3: dispositivosbiofarco@gmail.com
A4: fa7a94f5 | B4: 7c812b80 | C4: Coffee Break | E4: 9 | F4: Donas | G4: Aprobado | H4: repbiofarco | I4: dispositivosbiofarco@gmail.com

Sheet Comision_Control
A1: ID_Ciclo | B1: Monto_Base | C1: Val_Visita_Medico | D1: Val_Visita_Farmacia | E1: Val_Act_Hospital | F1: Val_Impulso_Farm | G1: ID_Usuario | H1: SUBMITTED BY

Sheet FicheroGeneral
A1: ID_Fichero | B1: Tipo | C1: Nombre | D1: Direccion | E1: Ciudad | F1: Estado | G1: Sector_Zona | H1: Teléfono_1 | I1: Teléfono_2 | J1: Email | K1: Instagram | L1: Potencial | M1: Última_Visita | N1: ID_RepresentanteAsignado | O1: Status | P1: ID_Usuario | Q1: SUBMITTED BY | R1: Especialidad | S1: Fecha de Nacimiento | T1: MSDS | U1: CM | V1: Centro de Salud | W1: Días_Atención | X1: Hora Inicio | Y1: Hora Fin | Z1: Observación | AA1: RIF | AB1: Contacto Principal | AC1: Cargo Contacto | AD1: Segmentacion | AE1: Productos Promocionados | AF1: Producto_Interes | AG1: Acción de Seguimiento
A2: 1 | B2: Medicos | C2: Adriana M. Di Loreto G. | D2: Calle Los Sauces, Maracay 2101, Aragua, Venezuela | E2: MCY | F2: ARA | H2: (0243) 232.04.89 | I2: 0412-241.41.40 | J2: adrianadiloretog@gmail.com | L2: Líder de Opinión , Alto Potencial Prescriptor | M2: 45987.777 | N2: dispositivosbiofarco@gmail.com | O2: Activo | P2: repbiofarco | Q2: dispositivosbiofarco@gmail.com | R2: 3 | T2: 62239 | U2: 7470 | V2: 2 | W2: Lun , Jue , Vie | X2: 9:00 a. m. | Y2: 2:00 p. m.
A3: 2 | B3: Medicos | C3: Adriana Mejía Montañez | D3: Calle Comercio, Maracay 2101, Aragua, Venezuela | E3: MCY | F3: ARA | I3: 0412-890.25.40 | J3: adripatimemo88@gmail.com | L3: Alto Potencial Prescriptor | M3: 45869 | N3: dispositivosbiofarco@gmail.com | O3: Activo | P3: repbiofarco | Q3: dispositivosbiofarco@gmail.com | R3: 5 | V3: 5 | W3: Lun, Jue | X3: 8:00 a. m. | Y3: 12:00 p. m.
A4: 3 | B4: Medicos | C4: Adrianys Rivas | D4: 7C32+94C, Maracay 2101, Aragua, Venezuela | E4: MCY | F4: ARA | I4: 0416-6465376 | J4: adrianysrivas@hotmail.com | L4: Alto Potencial Prescriptor | M4: 45987.737 | N4: dispositivosbiofarco@gmail.com | O4: Activo | P4: repbiofarco | Q4: dispositivosbiofarco@gmail.com | R4: 3 | T4: 54984 | U4: 6388 | V4: 21 | W4: Lun, Mar, Mie, Jue, Vie | X4: 7:30 a. m. | Y4: 11:30 a. m.
A5: 4 | B5: Medicos | C5: Alejandro Crespo | D5: Urb La Floresta Calle Comercio Maternidad La Floresta Maracay | E5: MCY | F5: ARA | I5: 0412-4347262 | J5: acrespof@gmail.com | L5: Líder de Opinión , Alto Potencial Prescriptor | M5: 45987.747 | N5: dispositivosbiofarco@gmail.com | O5: Activo | P5: repbiofarco | Q5: dispositivosbiofarco@gmail.com | R5: 1 | T5: 103632 | U5: 10330 | V5: 5 | W5: Lun, Mar, Mie, Jue, Vie | X5: 0.58333333 | Y5: 0.75
A6: 5 | B6: Medicos | C6: Ana Albella | D6: Centro Médico Maracay | E6: MCY | F6: ARA | H6: 0243-2003700 | I6: 0414-5943985 | J6: anaalbella46@gmail.com | L6: Alto Potencial Prescriptor | M6: 45987.74 | N6: dispositivosbiofarco@gmail.com | O6: Activo | P6: repbiofarco | Q6: dispositivosbiofarco@gmail.com | R6: 6 | T6: 45076 | U6: 4171 | V6: 2 | W6: Lun, Mar, Mie, Jue, Vie | X6: 2:00 p. m. | Y6: 6:00 p. m.
A7: 6 | B7: Medicos | C7: Ana Vasquez | D7: Urb La Floresta Calle Comercio Maternidad La Floresta Maracay | E7: MCY | F7: ARA | I7: 0414-4439179 | J7: analvasquezr68@gmail.com | L7: Alto Potencial Prescriptor | M7: 45987.61 | N7: dispositivosbiofarco@gmail.com | O7: Activo | P7: repbiofarco | Q7: dispositivosbiofarco@gmail.com | R7: 1 | T7: 60244 | U7: 4969 | V7: 5 | W7: Lun, Mar, Mie, Jue, Vie | X7: 8:00 a. m. | Y7: 12:00 p. m.
A8: 7 | B8: Medicos | C8: Andrea A. Nogales G. | D8: Urb. Calicanto, Edif. Rincón De Los Toro, Piso 2 Consultorio 24 | E8: MCY | F8: ARA | I8: 0414-4514270 | J8: nogalesandrea@hotmail.com | L8: Líder de Opinión , Alto Potencial Prescriptor | M8: 45854 | N8: dispositivosbiofarco@gmail.com | O8: Activo | P8: repbiofarco | Q8: dispositivosbiofarco@gmail.com | R8: 3 | T8: 64994 | U8: 7530 | V8: 29 | W8: Lun, Mie, Vie | X8: 8:00 a. m. | Y8: 5:00 p. m.
A9: 8 | B9: Medicos | C9: Angélica Landaeta | D9: Av. Ramón Narváez Norte, Edif. Policlínica Coromoto, Planta Baja. Frente Al Parque Santos Michelena | E9: MCY | F9: ARA | H9: 0243-554.10.02 Ext. 110 | I9: 0412-420.16.65 | J9: angelmar411@yahoo.com | L9: Alto Potencial Prescriptor | M9: 45987.735 | N9: dispositivosbiofarco@gmail.com | O9: Activo | P9: repbiofarco | Q9: dispositivosbiofarco@gmail.com | R9: 1 | T9: 70858 | U9: 8252 | V9: 15 | W9: Lun , Jue | X9: 8:00 a. m. | Y9: 12:00 p. m. | Z9: Viernes 2:30pm paso consulta en Crecer Sanito
A10: 9 | B10: Medicos | C10: Arelis Salazar | D10: Av. 19 de Abril, Maracay 2101, Aragua, Venezuela | E10: MCY | F10: ARA | I10: 0414-9460149 | J10: dra.salazar.internista@gmail.com | L10: Alto Potencial Prescriptor | M10: 45987.736 | N10: dispositivosbiofarco@gmail.com | O10: Activo | P10: repbiofarco | Q10: dispositivosbiofarco@gmail.com | R10: 6 | T10: 75051 | U10: 9049 | V10: 31 | W10: Lun, Mar, Mie, Jue, Vie | X10: 8:00 a. m. | Y10: 12:00 p. m. | Z10: Centro Profesional Plaza PH2 previa cita
A11: 10 | B11: Medicos | C11: Arlene Montilla | D11: Calle Monsenor Feliciano Gonzalez Urb La Floresta Maracay | E11: MCY | F11: ARA | I11: 0414-4751487 | J11: arleneavila295@gmail.com | L11: Alto Potencial Prescriptor | M11: 45987.734 | N11: dispositivosbiofarco@gmail.com | O11: Activo | P11: repbiofarco | Q11: dispositivosbiofarco@gmail.com | R11: 2 | T11: 116309 | U11: 11420 | V11: 26 | W11: Lun, Mar, Mie, Jue, Vie | X11: 8:00 a. m. | Y11: 12:00 p. m.
A12: 11 | B12: Medicos | C12: Arnaldo Rondón | D12: Av. 19 de Abril, Maracay 2101, Aragua, Venezuela | E12: MCY | F12: ARA | I12: 0424-3344484 | J12: arnaldorondon2017@gmail.com | L12: Alto Potencial Prescriptor | M12: 45987.655 | N12: dispositivosbiofarco@gmail.com | O12: Activo | P12: repbiofarco | Q12: dispositivosbiofarco@gmail.com | R12: 3 | T12: 49298 | U12: 6051 | V12: 31 | W12: Lun, Mar, Mie, Jue, Vie | X12: 1:00 p. m. | Y12: 5:00 p. m.
A13: 12 | B13: Medicos | C13: Carlos Rondon | D13: Calle Los Sauces, Maracay 2101, Aragua, Venezuela | E13: MCY | F13: ARA | I13: 0412-4509974 | J13: rondoncarlosneo@gmail.com | L13: Líder de Opinión , Alto Potencial Prescriptor | M13: 45987.766 | N13: dispositivosbiofarco@gmail.com | O13: Activo | P13: repbiofarco | Q13: dispositivosbiofarco@gmail.com | R13: 1 | T13: 63632 | U13: 7747 | V13: 2 | W13: Lun, Mar, Mie, Jue, Vie | X13: 8:00 a. m. | Y13: 12:00 p. m. | Z13: ProbioconZinc
A14: 13 | B14: Medicos | C14: Carlos Volcan | D14: Calle Coromoto cruce con 2da Transversal, Edificio Clínica Guadalupe, Maracay ZP2101, Aragua, Venezuela | E14: MCY | F14: ARA | I14: 0414-9439548 | J14: carlosvolcan@rocketmail.com | L14: Alto Potencial Prescriptor | M14: 45987.738 | N14: dispositivosbiofarco@gmail.com | O14: Activo | P14: repbiofarco | Q14: dispositivosbiofarco@gmail.com | R14: 3 | T14: 100508 | U14: 10129 | V14: 25 | W14: Jue | X14: 8:00 a. m. | Y14: 12:00 p. m.
A15: 14 | B15: Medicos | C15: Carmen Sarmiento | D15: 7C32+4P4, Avenida 19 de Abril, Maracay 2101, Aragua, Venezuela | E15: MCY | F15: ARA | I15: 0412-0431115 | J15: kikirecabal@gmail.com | L15: Alto Potencial Prescriptor | M15: 45902 | N15: dispositivosbiofarco@gmail.com | O15: Activo | P15: repbiofarco | Q15: dispositivosbiofarco@gmail.com | R15: 2 | T15: 38815 | U15: 3481 | V15: 31 | W15: Lun , Mar , Mie , Jue | X15: 8:00 a. m. | Y15: 12:00 p. m.
A16: 15 | B16: Medicos | C16: Carolina Bedoya | D16: Calle Coromoto cruce con 2da Transversal, Edificio Clínica Guadalupe, Maracay ZP2101, Aragua, Venezuela | E16: MCY | F16: ARA | I16: 0414-4596803 | J16: cbedoya11@gmail.com | L16: Líder de Opinión , Alto Potencial Prescriptor | M16: 45901 | N16: dispositivosbiofarco@gmail.com | O16: Activo | P16: repbiofarco | Q16: dispositivosbiofarco@gmail.com | R16: 1 | T16: 31964 | U16: 2441 | V16: 25 | W16: Lun, Mar, Mie, Jue, Vie | X16: 0.58333333 | Y16: 0.76736111
A17: 16 | B17: Medicos | C17: Carolina Gil | D17: Calle Lopez Aveledo Urb Calicanto | E17: MCY | F17: ARA | I17: 0412-7537978 | J17: carolinagil@hotmail.com | L17: Alto Potencial Prescriptor | M17: 45987.75 | N17: dispositivosbiofarco@gmail.com | O17: Activo | P17: repbiofarco | Q17: dispositivosbiofarco@gmail.com | R17: 3 | T17: 49424 | U17: 4832 | V17: 27 | W17: Lun, Mar, Mie, Jue, Vie | X17: 8:00 a. m. | Y17: 0.70833333 | Z17: Lunes y Martes en el HCM
A18: 17 | B18: Medicos | C18: Joselyn Castro | D18: Torre Sindoni Piso 5 Maracay | E18: MCY | F18: ARA | I18: 0414-5909855 | J18: joselyncg20@gmail.com | L18: Alto Potencial Prescriptor | M18: 45987.746 | N18: dispositivosbiofarco@gmail.com | O18: Activo | P18: repbiofarco | Q18: dispositivosbiofarco@gmail.com | R18: 3 | T18: 63548 | U18: 7395 | V18: 49 | W18: Jue | X18: 0.41666667 | Y18: 0.66666667
A19: 18 | B19: Medicos | C19: Juan Alvarez | D19: Centro Empresarial Europa, Avenida Las Delicias, Maracay 2101, Aragua, Venezuela | E19: MCY | F19: ARA | I19: 0424-3670117 | J19: alvarezbarco@gmail.com | L19: Líder de Opinión , Alto Potencial Prescriptor | M19: 45987.629 | N19: dispositivosbiofarco@gmail.com | O19: Activo | P19: repbiofarco | Q19: dispositivosbiofarco@gmail.com | R19: 1 | T19: 64195 | U19: 64195 | V19: 28 | W19: Lun , Mar , Mie , Jue , Vie | X19: 0.375 | Y19: 0.66666667
A20: 19 | B20: Medicos | C20: Dendy Hernández | D20: Urb. Calicanto, Calle López Aveledo, C/C Av. 19 De Abril, Centro De Especialidades Calicanto, Piso 4 Consultorio 405 | E20: MCY | F20: ARA | I20: 0424-366.75.51 | J20: dendyhp@hotmail.com | L20: Líder de Opinión , Alto Potencial Prescriptor | M20: 45987.7 | N20: dispositivosbiofarco@gmail.com | O20: Activo | P20: repbiofarco | Q20: dispositivosbiofarco@gmail.com | R20: 1 | T20: 79022 | U20: 9674 | V20: 21 | W20: Lun, Mar, Mie, Jue, Vie | X20: 7:00 a. m. | Y20: 1:00 p. m.
A21: 20 | B21: Medicos | C21: Juana Cortez | D21: 7C55+WR4, Maracay 2101, Aragua, Venezuela | E21: MCY | F21: ARA | H21: 0416-6463254 | I21: 0424-3441048 | J21: juanmaricortez@hotmail.com | L21: Líder de Opinión , Alto Potencial Prescriptor | M21: 45987.627 | N21: dispositivosbiofarco@gmail.com | O21: Activo | P21: repbiofarco | Q21: dispositivosbiofarco@gmail.com | R21: 3 | T21: 28855 | U21: 3311 | V21: 65 | W21: Lun, Mar, Mie, Jue, Vie | X21: 0.33333333 | Y21: 0.5
A22: 21 | B22: Medicos | C22: Dina Goncalves | D22: Av Principal Las Delicias Edif Centro Medico Maracay | E22: MCY | F22: ARA | I22: 0414-4562190 | J22: dinagoncalvesf@hotmail.com | L22: Alto Potencial Prescriptor | M22: 45987.614 | N22: dispositivosbiofarco@gmail.com | O22: Activo | P22: repbiofarco | Q22: dispositivosbiofarco@gmail.com | R22: 1 | T22: 8040 | U22: 68369 | V22: 2 | W22: Lun, Mar, Mie, Jue, Vie | X22: 8:00 a. m. | Y22: 12:00 p. m.
A23: 22 | B23: Medicos | C23: Elymar Santiago | D23: Av Principal Las Delicias Edif Centro Medico Maracay | E23: MCY | F23: ARA | I23: 0412-0359641 | J23: elymar79@gmail.com | L23: Alto Potencial Prescriptor | M23: 45987.617 | N23: dispositivosbiofarco@gmail.com | O23: Activo | P23: repbiofarco | Q23: dispositivosbiofarco@gmail.com | R23: 1 | S23: 45674 | T23: 7844 | U23: 66867 | V23: 2 | W23: Lun, Mar, Mie, Jue, Vie | X23: 1:00 p. m. | Y23: 6:00 p. m.
A24: 24 | B24: Medicos | C24: Elizabeth Parra | D24: Calle Los Sauces, Maracay 2101, Aragua, Venezuela | E24: MCY | F24: ARA | H24: 0243-2003700 | I24: 0414-0479395 | J24: eliparra_@hotmail.com | L24: Líder de Opinión , Alto Potencial Prescriptor | M24: 45987.763 | N24: dispositivosbiofarco@gmail.com | O24: Activo | P24: repbiofarco | Q24: dispositivosbiofarco@gmail.com | R24: 1 | T24: 61641 | U24: 7306 | V24: 2 | W24: Lun, Mar, Mie, Jue, Vie | X24: 8:00 a. m. | Y24: 12:00 p. m.
A25: 26 | B25: Medicos | C25: Emma Rodriguez | D25: Av Principal Las Delicias Edif Centro Medico Maracay | E25: MCY | F25: ARA | I25: 0414-4566372 | J25: rodriguezemma.69@hotmail.com | L25: Alto Potencial Prescriptor | M25: 45987.632 | N25: dispositivosbiofarco@gmail.com | O25: Activo | P25: repbiofarco | Q25: dispositivosbiofarco@gmail.com | R25: 6 | T25: 60978 | U25: 7012 | V25: 2 | W25: Lun , Mar , Jue , Vie | X25: 0.58333333 | Y25: 0.75
A26: 27 | B26: Medicos | C26: Estyvales Curbata | D26: Av. Sucre, Urb. La Floresta. Edif. Anexo Al Hospital Central De Maracay | E26: MCY | F26: ARA | I26: 0412-134.36.49 | J26: esty9124@gmail.com | L26: Alto Potencial Prescriptor | M26: 45987.733 | N26: dispositivosbiofarco@gmail.com | O26: Activo | P26: repbiofarco | Q26: dispositivosbiofarco@gmail.com | R26: 3 | T26: 114847 | U26: 11674 | V26: 13 | W26: Vie | X26: 7:00 a. m. | Y26: 4:00 p. m.
A27: 28 | B27: Medicos | C27: Fabiola Mosqueda | D27: Av Principal Las Delicias Edif Centro Medico Maracay | E27: MCY | F27: ARA | I27: 0412-8847080 | J27: fabiolamosquedanigual@gmail.com | K27: @fabiolafabiolamisquedar | L27: Alto Potencial Prescriptor | M27: 45839 | N27: dispositivosbiofarco@gmail.com | O27: Activo | P27: repbiofarco | Q27: dispositivosbiofarco@gmail.com | R27: 6 | S27: 45916 | T27: 61661 | U27: 7203 | V27: 2 | W27: Lun, Mar, Mie, Jue, Vie | X27: 7:00 a. m. | Y27: 12:00 p. m.
A28: 29 | B28: Medicos | C28: Feder Alvarez | D28: Urb La Floresta Calle Comercio Maternidad La Floresta Maracay | E28: MCY | F28: ARA | I28: 0424-3705828 | J28: federt.alvarez@gmail.com | L28: Líder de Opinión , Alto Potencial Prescriptor | M28: 45987.637 | N28: dispositivosbiofarco@gmail.com | O28: Activo | P28: repbiofarco | Q28: dispositivosbiofarco@gmail.com | R28: 1 | T28: 100553 | U28: 8799 | V28: 5 | W28: Lun, Mar, Mie, Jue, Vie | X28: 2:00 p. m. | Y28: 6:00 p. m.
A29: 30 | B29: Medicos | C29: Francis Ortega Vásquez | D29: Urb. Calicanto, Calle López Aveledo Norte, Torre Calicanto, Piso 5 Consultorio 5-1, Diagonal A La Panadería Royal | E29: MCY | F29: ARA | I29: 0412-5003776 | J29: drafrancisneuroPediatría@gmail.com | L29: Líder de Opinión , Alto Potencial Prescriptor | M29: 45987.792 | N29: dispositivosbiofarco@gmail.com | O29: Activo | P29: repbiofarco | Q29: dispositivosbiofarco@gmail.com | R29: 1 | T29: 72757 | U29: 8535 | V29: 69 | W29: Lun, Mar, Mie, Jue, Vie | X29: 8:00 a. m. | Y29: 12:00 p. m.
A30: 31 | B30: Medicos | C30: Francisco Guzmán | D30: Urb. Calicanto, Calle López Aveledo, Torre Calicanto, Piso 2 Consultorio 02, Diagonal A La Panadería Royal | E30: MCY | F30: ARA | I30: 0412-9726375 | J30: frankguztar@gmail.com | L30: Alto Potencial Prescriptor | M30: 45842 | N30: dispositivosbiofarco@gmail.com | O30: Activo | P30: repbiofarco | Q30: dispositivosbiofarco@gmail.com | R30: 3 | T30: 7706 | U30: 64174 | V30: 69 | W30: Lun, Mar, Mie, Jue, Vie | X30: 8:30 a. m. | Y30: 4:00 p. m.
A31: 32 | B31: Medicos | C31: Froilan A. Gómez P. | D31: Urb. Calicanto, Av. Sucre Nº 41, Al Lado De Clínica Calicanto | E31: MCY | F31: ARA | H31: 0412-386.11.40 | I31: 0414-415.58.77 | J31: froilanalexandergomezperez@gmail.com | L31: Líder de Opinión , Alto Potencial Prescriptor | M31: 45987.78 | N31: dispositivosbiofarco@gmail.com | O31: Activo | P31: repbiofarco | Q31: dispositivosbiofarco@gmail.com | R31: 4 | T31: 43913 | U31: 4000 | V31: 34 | W31: Lun, Mar, Mie, Jue, Vie | X31: 9:00 a. m. | Y31: 5:00 p. m.
A32: 33 | B32: Medicos | C32: Geraldine Duran | D32: Calle Los Sauces, Maracay 2101, Aragua, Venezuela | E32: MCY | F32: ARA | H32: 0412-6032395 | I32: 0414-5653474 | J32: geraldineduran18@hotmail.com | L32: Alto Potencial Prescriptor | M32: 45987.743 | N32: dispositivosbiofarco@gmail.com | O32: Activo | P32: repbiofarco | Q32: dispositivosbiofarco@gmail.com | R32: 3 | T32: 107516 | U32: 10624 | V32: 2 | W32: Vie | X32: 0.33333333
A33: 34 | B33: Medicos | C33: Gilma Gil | D33: 7C32+4P4, Avenida 19 de Abril, Maracay 2101, Aragua, Venezuela | E33: MCY | F33: ARA | I33: 0424-3590452 | J33: gilmagil50@gmail.com | L33: Alto Potencial Prescriptor | M33: 45817 | N33: dispositivosbiofarco@gmail.com | O33: Activo | P33: repbiofarco | Q33: dispositivosbiofarco@gmail.com | R33: 1 | T33: 18689 | U33: 1380 | V33: 31 | W33: Lun , Jue , Vie | X33: 8:00 a. m. | Y33: 12:00 p. m.
A34: 35 | B34: Medicos | C34: Gloria De Abreu | D34: Urb. Calicanto, Maracay 2101, Aragua, Venezuela | E34: MCY | F34: ARA | I34: 0412-4322746 | J34: dra.abreugloria4@gmail.com | L34: Líder de Opinión , Alto Potencial Prescriptor | M34: 45987.718 | N34: dispositivosbiofarco@gmail.com | O34: Activo | P34: repbiofarco | Q34: dispositivosbiofarco@gmail.com | R34: 1 | S34: 34428 | T34: 140817 | U34: 12652 | V34: 33 | W34: Lun, Mar, Mie, Jue, Vie | X34: 8:00 a. m. | Y34: 12:00 p. m.
A35: 36 | B35: Medicos | C35: Graca Rodrígues | D35: Urb. La Floresta, Calle Comercio N° 1, Centro Profesional La Floresta (Maternidad La Floresta) Piso 2 Consultorio 209 | E35: MCY | F35: ARA | I35: 0414-997.55.56 | J35: gracarodrigues@hotmail.com | L35: Alto Potencial Prescriptor | M35: 45902 | N35: dispositivosbiofarco@gmail.com | O35: Activo | P35: repbiofarco | Q35: dispositivosbiofarco@gmail.com | R35: 1 | V35: 5 | W35: Mar | X35: 1:00 p. m.
A36: 37 | B36: Medicos | C36: Gustavo Fernandez | D36: Av 19 De Abril Edif Clinica Lugo Maracay | E36: MCY | F36: ARA | I36: 0414-7040689 | J36: gustavo_fernandez@hotmail.com | L36: Alto Potencial Prescriptor | M36: 45987.724 | N36: dispositivosbiofarco@gmail.com | O36: Activo | P36: repbiofarco | Q36: dispositivosbiofarco@gmail.com | R36: 3 | T36: 56537 | U36: 8662 | V36: 14 | W36: Lun, Mar, Mie, Jue, Vie | X36: 7:00 a. m. | Y36: 4:00 p. m.
A37: 38 | B37: Medicos | C37: Hector Yepez | D37: C. López Aveledo, Maracay 2101, Aragua, Venezuela | E37: MCY | F37: ARA | I37: 0416-4475928 | J37: hectoryepez@hotmail.com | L37: Alto Potencial Prescriptor | M37: 45987.739 | N37: dispositivosbiofarco@gmail.com | O37: Activo | P37: repbiofarco | Q37: dispositivosbiofarco@gmail.com | R37: 5 | T37: 20959 | U37: 1266 | V37: 47 | W37: Lun, Mar, Mie, Jue, Vie | X37: 8:00 a. m. | Y37: 12:00 p. m.
A38: 39 | B38: Medicos | C38: Jennie Martens | D38: Calle Comercio, Maracay 2101, Aragua, Venezuela | E38: MCY | F38: ARA | H38: 0243-244.02.33 | I38: 0414-446.11.07 | J38: martensjdc@gmail.com | L38: Alto Potencial Prescriptor | M38: 45987.722 | N38: dispositivosbiofarco@gmail.com | O38: Activo | P38: repbiofarco | Q38: dispositivosbiofarco@gmail.com | R38: 1 | T38: 29456 | U38: 1575 | V38: 5 | W38: Lun, Mar, Mie, Jue, Vie | X38: 8:30 a. m. | Y38: 2:30 p. m.
A39: 40 | B39: Medicos | C39: Jiroska Morán Fernández | D39: Calle Comercio, Maracay 2101, Aragua, Venezuela | E39: MCY | F39: ARA | H39: 0412-8840837 | I39: 0412-9400468 | J39: mjiroska@gmail.com | L39: Alto Potencial Prescriptor | M39: 45987.724 | N39: dispositivosbiofarco@gmail.com | O39: Activo | P39: repbiofarco | Q39: dispositivosbiofarco@gmail.com | R39: 3 | T39: 91346 | U39: 4395 | V39: 5 | W39: Jue , Vie | X39: 0.33333333 | Y39: 6:00 p. m. | Z39: Viernes de 1pm a 6pm
A40: 42 | B40: Medicos | C40: Josefina Caruso | D40: 69VV+M96, Maracay 2103, Aragua, Venezuela | E40: MCY | F40: ARA | H40: 0414-4531979 | I40: 0414-4531979 | L40: Alto Potencial Prescriptor | M40: 45854 | N40: dispositivosbiofarco@gmail.com | O40: Activo | P40: repbiofarco | Q40: dispositivosbiofarco@gmail.com | R40: 1 | T40: 33982 | V40: 29 | W40: Lun, Mar, Mie, Jue, Vie | X40: 0.33333333 | Y40: 0.5
A41: 45 | B41: Medicos | C41: Juana Martínez Soto | D41: Urb. Calicanto, Edif. Rincón De Los Toros, Piso 4 Consultorio 49 | E41: MCY | F41: ARA | H41: (0243) 245.57.52 | I41: 0414-476.21.37 | J41: jjmarti1@gmail.com | L41: Líder de Opinión , Alto Potencial Prescriptor | M41: 45987.72 | N41: dispositivosbiofarco@gmail.com | O41: Activo | P41: repbiofarco | Q41: dispositivosbiofarco@gmail.com | R41: 5 | T41: 33972 | U41: 3073 | V41: 29 | W41: Lun, Mar, Mie, Jue, Vie | X41: 8:00 a. m. | Y41: 12:00 p. m.
A42: 46 | B42: Medicos | C42: Kathering Castillo | D42: Av Lopez Aveledo Urb Calicanto | E42: MCY | F42: ARA | I42: 0412-8956085 | J42: katy.castillo60@yahoo.com | L42: Alto Potencial Prescriptor | M42: 45987.626 | N42: dispositivosbiofarco@gmail.com | O42: Activo | P42: repbiofarco | Q42: dispositivosbiofarco@gmail.com | R42: 6 | T42: 000288 | U42: 140177 | V42: 33 | W42: Lun, Mar, Mie, Jue, Vie | X42: 8:00 a. m. | Y42: 12:00 p. m.
A43: 47 | B43: Medicos | C43: Keila Rivero | D43: Av Principal Las Delicias Edif Centro Medico Maracay | E43: MCY | F43: ARA | I43: 0416-1467824 | J43: krivero@uc.edu.ve | L43: Líder de Opinión , Alto Potencial Prescriptor | M43: 45987.634 | N43: dispositivosbiofarco@gmail.com | O43: Activo | P43: repbiofarco | Q43: dispositivosbiofarco@gmail.com | R43: 1 | T43: 52764 | U43: 5449 | V43: 2 | W43: Lun , Mar , Jue | X43: 8:00 a. m. | Y43: 12:00 p. m.
A44: 48 | B44: Medicos | C44: Lisdrelys Hernandez | D44: Urb La Floresta Calle Comercio Maternidad La Floresta Maracay | E44: MCY | F44: ARA | I44: 0414-4916271 | J44: lisdrelyshs18@gmail.com | L44: Alto Potencial Prescriptor | M44: 45987.728 | N44: dispositivosbiofarco@gmail.com | O44: Activo | P44: repbiofarco | Q44: dispositivosbiofarco@gmail.com | R44: 1 | T44: 63437 | U44: 7320 | V44: 5 | W44: Lun, Mar, Mie, Jue, Vie | X44: 8:00 a. m. | Y44: 12:00 p. m.
A45: 50 | B45: Medicos | C45: Lucymar García | D45: Calle Los Sauces, Maracay 2101, Aragua, Venezuela | E45: MCY | F45: ARA | H45: 0414-4488005 | I45: 0412-4235714 | J45: lucy.garcia0127@gmail.com | L45: Alto Potencial Prescriptor | M45: 45839 | N45: dispositivosbiofarco@gmail.com | O45: Activo | P45: repbiofarco | Q45: dispositivosbiofarco@gmail.com | R45: 3 | T45: 77488 | U45: 9193 | V45: 2 | W45: Lun, Mar, Mie, Jue, Vie | X45: 1:00 p. m. | Y45: 7:00 p. m.
A46: 51 | B46: Medicos | C46: Luis Alfredo Mosquera | D46: 18 Avenida 19 de Abril, Maracay 2101, Aragua, Venezuela | E46: MCY | F46: ARA | I46: 0412-1310019 | J46: luism2711@hotmail.com | L46: Alto Potencial Prescriptor | M46: 45987.731 | N46: dispositivosbiofarco@gmail.com | O46: Activo | P46: repbiofarco | Q46: dispositivosbiofarco@gmail.com | R46: 3 | T46: 94468 | U46: 33704 | V46: 62 | W46: Lun, Mar, Mie, Jue, Vie | X46: 1:00 p. m. | Y46: 5:00 p. m.
A47: 52 | B47: Medicos | C47: Marbelia Venegas | D47: Av Sucre Urb Calicanto | E47: MCY | F47: ARA | I47: 0414-4558659 | J47: marbeliavenegas@hotmail.com | L47: Alto Potencial Prescriptor | M47: 45834 | N47: dispositivosbiofarco@gmail.com | O47: Activo | P47: repbiofarco | Q47: dispositivosbiofarco@gmail.com | R47: 6 | T47: 25135 | U47: 25135 | V47: 47 | W47: Lun, Mar, Mie, Jue, Vie | X47: 0.33333333 | Y47: 0.58333333 | Z47: Gastro
A48: 53 | B48: Medicos | C48: Maria Griman | D48: Av. 19 de Abril, Maracay 2101, Aragua, Venezuela | E48: MCY | F48: ARA | I48: 0424-3574507 | J48: mariagriman_112@hotmail.com | L48: Alto Potencial Prescriptor | M48: 45841 | N48: dispositivosbiofarco@gmail.com | O48: Activo | P48: repbiofarco | Q48: dispositivosbiofarco@gmail.com | R48: 6 | T48: 39868 | U48: 3566 | V48: 31 | W48: Mie , Jue , Vie | X48: 0.29166667 | Y48: 0.5
A49: 54 | B49: Medicos | C49: María Montiel | D49: Urb. Calicanto, Edificio Rincón De Los Toro, Piso 1, Consultorio #18 - Urb. Calicanto, Calle Coromoto Con 2da. Transversal, #14 | E49: MCY | F49: ARA | I49: 0414-6824421 | J49: montielram@hotmail.com | L49: Alto Potencial Prescriptor | M49: 45987.747 | N49: dispositivosbiofarco@gmail.com | O49: Activo | P49: repbiofarco | Q49: dispositivosbiofarco@gmail.com | R49: 4 | T49: 52695 | U49: 2777 | V49: 25 | W49: Lun, Mar, Mie, Jue, Vie | X49: 8:00 a. m. | Y49: 12:00 p. m. | Z49: Previa cita. Pasa consulta en el HCM y SAEA
A50: 55 | B50: Medicos | C50: Maria Perez | D50: Av. 19 de Abril, Maracay 2101, Aragua, Venezuela | E50: MCY | F50: ARA | I50: 0414-4905089 | J50: mperezcolmenares@hotmail.com | L50: Alto Potencial Prescriptor | M50: 45987.612 | N50: dispositivosbiofarco@gmail.com | O50: Activo | P50: repbiofarco | Q50: dispositivosbiofarco@gmail.com | R50: 1 | T50: 37633 | U50: 3373 | V50: 31 | W50: Lun, Mar, Mie, Jue, Vie | X50: 8:00 a. m. | Y50: 12:00 p. m.
A51: 57 | B51: Medicos | C51: Mariela Salomon | D51: Hospital de Clínicas Las Delicias | E51: MCY | F51: ARA | H51: 0424-3432168 | I51: 0424-8762904 | J51: mariela_237@hotmail.com | K51: @dra.marielasalomon | L51: Alto Potencial Prescriptor | M51: 45987.795 | N51: dispositivosbiofarco@gmail.com | O51: Activo | P51: repbiofarco | Q51: dispositivosbiofarco@gmail.com | R51: 3 | T51: 52662 | U51: 52662 | V51: 61 | W51: Lun, Mar, Mie, Jue, Vie | X51: 8:00 a. m. | Y51: 0.66666667
A52: 59 | B52: Medicos | C52: Aquino Alinest | D52: Calle Coromoto cruce con 2da Transversal, Edificio Clínica Guadalupe, Maracay ZP2101, Aragua, Venezuela | E52: MCY | F52: ARA | I52: 0424-3307745 | L52: Alto Potencial Prescriptor | M52: 45855 | N52: dispositivosbiofarco@gmail.com | O52: Activo | P52: repbiofarco | Q52: dispositivosbiofarco@gmail.com | R52: 6 | T52: 65028 | U52: 3145 | V52: 25 | W52: Lun , Jue , Vie | X52: 0.83333333 | Y52: 0.5
A53: 61 | B53: Medicos | C53: Monica Segnini | D53: Av. Miranda & C. Mariño, Maracay 2103, Aragua, Venezuela | E53: MCY | F53: ARA | I53: 0424-4575469 | J53: monicaalexandrasegnini@gmail.com | L53: Alto Potencial Prescriptor | M53: 45852 | N53: dispositivosbiofarco@gmail.com | O53: Activo | P53: repbiofarco | Q53: dispositivosbiofarco@gmail.com | R53: 1 | T53: 116902 | U53: 11629 | V53: 82 | W53: Vie | X53: 0.33333333 | Y53: 0.58333333 | Z53: Viernes Torre Cosmopolitan
A54: 63 | B54: Medicos | C54: Nefertiti Daulabani | D54: Prolongación de Perez Almarza, entre Paez y Negro Primero, Maracay. al lado del Banco de Venezuela y Diagonal al Centro Comercial de la Economía Informal, 69XW+P68, Blvd. Pérez Almarza, Maracay 2103, Aragua, Venezuela | E54: MCY | F54: ARA | I54: 0424-3024776 | J54: nefertitidaulabani@hotmail.com | L54: Alto Potencial Prescriptor | M54: 45924 | N54: dispositivosbiofarco@gmail.com | O54: Activo | P54: repbiofarco | Q54: dispositivosbiofarco@gmail.com | R54: 3 | T54: 1 | U54: 8915 | V54: 52 | W54: Lun, Mar, Mie, Jue, Vie | X54: 0.33333333 | Y54: 0.58333333
A55: 65 | B55: Medicos | C55: Nelly De Lucas | D55: Av. 19 de Abril, Torre Cosmopolitan, Maracay 2101, Aragua, Venezuela | E55: MCY | F55: ARA | I55: 0414-5986854 | J55: nellydelucas@hotmail.com | L55: Líder de Opinión , Alto Potencial Prescriptor | M55: 45987.624 | N55: dispositivosbiofarco@gmail.com | O55: Activo | P55: repbiofarco | Q55: dispositivosbiofarco@gmail.com | R55: 1 | T55: 100394 | U55: 10397 | V55: 40 | W55: Lun, Mar, Mie, Jue, Vie | X55: 8:00 a. m. | Y55: 12:00 p. m.
A56: 68 | B56: Medicos | C56: Nena Alvarado | D56: Calle San Miguel, Local 39 Santa Rosa, Maracay Edo. Aragua | E56: MCY | F56: ARA | I56: 4243168007 | J56: nenaalvarado134@hotmail.com | L56: Alto Potencial Prescriptor | M56: 45854 | N56: dispositivosbiofarco@gmail.com | O56: Activo | P56: repbiofarco | Q56: dispositivosbiofarco@gmail.com | R56: 6 | T56: 63797 | U56: 7554 | V56: 4 | W56: Lun, Mar, Mie, Jue, Vie | X56: 0.33333333 | Y56: 0.58333333
A57: 70 | B57: Medicos | C57: Néstor M. Pinto F. | D57: Calle Los Sauces, Maracay 2101, Aragua, Venezuela | E57: MCY | F57: ARA | H57: 0243-2336687 | I57: 0424-3410745 | J57: merlo38@hotmail.com | L57: Alto Potencial Prescriptor | M57: 45987.765 | N57: dispositivosbiofarco@gmail.com | O57: Activo | P57: repbiofarco | Q57: dispositivosbiofarco@gmail.com | R57: 4 | T57: 57941 | U57: 6636 | V57: 35 | W57: Lun, Mar, Mie, Jue, Vie | X57: 8:00 a. m. | Y57: 12:00 p. m.
A58: 73 | B58: Medicos | C58: Gloria Colmenares | D58: 6CQ7+MC8, Av. Fuerzas Aéreas, Maracay 2103, Aragua, Venezuela | E58: MCY | F58: ARA | I58: 0416-6439019 | L58: Alto Potencial Prescriptor | M58: 45987.772 | N58: dispositivosbiofarco@gmail.com | O58: Activo | P58: repbiofarco | Q58: dispositivosbiofarco@gmail.com | R58: 1 | T58: 29284 | U58: 2321 | V58: 17 | W58: Lun, Mar, Mie, Jue, Vie | X58: 0.41666667 | Y58: 0.625
A59: 74 | B59: Medicos | C59: Halina Martinez | D59: 7C32+4P4, Avenida 19 de Abril, Maracay 2101, Aragua, Venezuela | E59: MCY | F59: ARA | H59: 0416-5430880 | I59: 0416-5430880 | L59: Alto Potencial Prescriptor | M59: 45987.648 | N59: dispositivosbiofarco@gmail.com | O59: Activo | P59: repbiofarco | Q59: dispositivosbiofarco@gmail.com | R59: 2 | T59: 35931 | U59: 3279 | V59: 31 | W59: Lun , Mar | X59: 0.33333333 | Y59: 0.58333333
A60: 77 | B60: Medicos | C60: Oscar Noguera | D60: Avenida 19 De Abril, Maracay 2103, Aragua, Venezuela | E60: MCY | F60: ARA | I60: 0424-3072026 | J60: doanh@gmail.com | L60: Alto Potencial Prescriptor | M60: 45987.656 | N60: dispositivosbiofarco@gmail.com | O60: Activo | P60: repbiofarco | Q60: dispositivosbiofarco@gmail.com | R60: 6 | T60: 64712 | U60: 726 | V60: 14 | W60: Lun, Mar, Mie, Jue, Vie | X60: 7:00 a. m. | Y60: 12:00 p. m.
A61: 81 | B61: Medicos | C61: Priscila Espinoza | D61: Av Principal Las Delicias Edif Centro Medico Maracay | E61: MCY | F61: ARA | I61: 0424-3694527 | J61: priscilaespinoza5@gmail.com | L61: Alto Potencial Prescriptor | M61: 45987.616 | N61: dispositivosbiofarco@gmail.com | O61: Activo | P61: repbiofarco | Q61: dispositivosbiofarco@gmail.com | R61: 6 | T61: 68871 | U61: 68971 | V61: 2 | W61: Lun , Mie , Vie | X61: 0.58333333 | Y61: 0.75
A62: 84 | B62: Medicos | C62: Joymer Fernández | D62: Avenida 19 De Abril, Maracay 2101, Aragua, Venezuela | E62: MCY | F62: ARA | I62: 0414-5423228 | L62: Alto Potencial Prescriptor | M62: 45987.622 | N62: dispositivosbiofarco@gmail.com | O62: Activo | P62: repbiofarco | Q62: dispositivosbiofarco@gmail.com | R62: 1 | T62: 41187 | U62: 3741 | V62: 14 | W62: Lun, Mar, Mie, Jue, Vie | X62: 0.33333333 | Y62: 0.58333333
A63: 85 | B63: Medicos | C63: Reinaldo Aguilar P. | D63: Av. Las Delicias, Urb. El Bosque, Centro Médico Maracay, Torre C, Piso 1 Consultorio 1-05 | E63: MCY | F63: ARA | H63: 0243-232.12.77 (Directo) | I63: 0424-374.92.17 | J63: reinaldo_urologia@yahoo.es | L63: Alto Potencial Prescriptor | M63: 45987.701 | N63: dispositivosbiofarco@gmail.com | O63: Activo | P63: repbiofarco | Q63: dispositivosbiofarco@gmail.com | R63: 4 | T63: 49315 | U63: 4922 | V63: 2 | W63: Lun , Mie , Vie | X63: 8:00 a. m. | Y63: 0.5 | Z63: Previa cita
A64: 89 | B64: Medicos | C64: Roberto Ferrara | D64: Av. Principal El Limón #70 - Urb. Calicanto, Calle López Aveledo, Policlínica Maracay | E64: MCY | F64: ARA | H64: (0243) 935.22.44 | I64: 0414-461.49.65 | J64: robertoferrarahurtado@gmail.com | L64: Alto Potencial Prescriptor | M64: 45987.782 | N64: dispositivosbiofarco@gmail.com | O64: Activo | P64: repbiofarco | Q64: dispositivosbiofarco@gmail.com | R64: 3 | T64: 17760 | U64: 17760 | V64: 47 | W64: Lun, Mie, Vie | X64: 7:00 a. m. | Y64: 12:00 p. m.
A65: 91 | B65: Medicos | C65: María Angelica Celis | D65: Calle Los Sauces, Maracay 2101, Aragua, Venezuela | E65: MCY | F65: ARA | I65: 0412-1466313 | L65: Alto Potencial Prescriptor | M65: 45849 | N65: dispositivosbiofarco@gmail.com | O65: Activo | P65: repbiofarco | Q65: dispositivosbiofarco@gmail.com | R65: 1 | T65: 67491 | U65: 10965 | V65: 2 | W65: Lun, Mar, Mie, Jue, Vie | X65: 0.33333333 | Y65: 0.58333333
A66: 92 | B66: Medicos | C66: María Díaz | D66: Calle Los Sauces, Maracay 2101, Aragua, Venezuela | E66: MCY | F66: ARA | I66: 0414-2977411 | L66: Alto Potencial Prescriptor | M66: 45909 | N66: dispositivosbiofarco@gmail.com | O66: Activo | P66: repbiofarco | Q66: dispositivosbiofarco@gmail.com | R66: 6 | T66: 1 | U66: 1 | V66: 2 | W66: Lun, Mar, Mie, Jue, Vie | X66: 0.33333333 | Y66: 0.58333333
A67: 93 | B67: Medicos | C67: Rosa María Saporiti | D67: Urb. Calicanto, Calle López Aveledo Norte, Policlínica Maracay, Piso 1 Consultorio 1-12 | E67: MCY | F67: ARA | I67: 0414-4606666 | J67: rosasaporiti@gmail.com | L67: Alto Potencial Prescriptor | M67: 45987.77 | N67: dispositivosbiofarco@gmail.com | O67: Activo | P67: repbiofarco | Q67: dispositivosbiofarco@gmail.com | R67: 3 | T67: 16776 | U67: 2152 | V67: 47 | W67: Mar, Mie, Jue | X67: 8:30 a. m. | Y67: 12:30 p. m.
A68: 95 | B68: Medicos | C68: María Teresa Ramos | E68: MCY | F68: ARA | H68: 0424-5685490 | I68: 0424-5685490 | L68: Alto Potencial Prescriptor | M68: 45981.971 | N68: dispositivosbiofarco@gmail.com | O68: Activo | P68: repbiofarco | Q68: dispositivosbiofarco@gmail.com | R68: 1 | T68: 47449 | U68: 4050 | V68: 2 | W68: Lun , Mar | X68: 0.29166667 | Y68: 0.5
A69: 96 | B69: Medicos | C69: Rosirys Velasquez | D69: Calle Comercio, Maracay 2101, Aragua, Venezuela | E69: MCY | F69: ARA | I69: 0424-3801545 | J69: rosirysvelasquezsalazar@hotmail.com | L69: Alto Potencial Prescriptor | M69: 45821 | N69: dispositivosbiofarco@gmail.com | O69: Activo | P69: repbiofarco | Q69: dispositivosbiofarco@gmail.com | R69: 6 | T69: 32255 | U69: 2455 | V69: 5 | W69: Lun, Mar, Mie, Jue, Vie | X69: 8:00 a. m. | Y69: 12:00 p. m.
A70: 97 | B70: Medicos | C70: Maribell Ferreira | D70: 45 Av. Sucre, Maracay 2101, Aragua, Venezuela | E70: MCY | F70: ARA | H70: 0424-3163377 | I70: 0424-3163377 | L70: Líder de Opinión , Alto Potencial Prescriptor | M70: 45981.972 | N70: dispositivosbiofarco@gmail.com | O70: Activo | P70: repbiofarco | Q70: dispositivosbiofarco@gmail.com | R70: 1 | T70: 47040 | U70: 4325 | V70: 60 | W70: Lun, Mar, Mie, Jue, Vie | X70: 0.41666667 | Y70: 0.54166667
A71: 98 | B71: Medicos | C71: Rusmar Suárez | D71: Av. Fuerzas Aéreas, C/C Calle Los Cedros, Centro Médico San José, Piso 1 Consultorio 7 | E71: MCY | F71: ARA | H71: 0412-853.91.34 | I71: 0414-149.12.70 | J71: rusmar88@hotmail.com | L71: Líder de Opinión , Alto Potencial Prescriptor | M71: 45782 | N71: dispositivosbiofarco@gmail.com | O71: Activo | P71: repbiofarco | Q71: dispositivosbiofarco@gmail.com | R71: 1 | V71: 17 | W71: Mar, Jue | X71: 8:00 a. m. | Y71: 12:00 p. m. | Z71: Jefe del Servicio de Pediatría en el Hospital de los Samanes
A72: 101 | B72: Medicos | C72: Marilyn González | E72: MCY | F72: ARA | H72: 0243-7119452 | I72: 0412-4355850 | L72: Alto Potencial Prescriptor | M72: 45987.651 | N72: dispositivosbiofarco@gmail.com | O72: Activo | P72: repbiofarco | Q72: dispositivosbiofarco@gmail.com | R72: 6 | T72: 52679 | U72: 52679 | V72: 27 | W72: Lun, Mar, Mie, Jue, Vie | X72: 0.29166667 | Y72: 0
A73: 102 | B73: Medicos | C73: Sikiu Navarro | D73: Av Principal Las Delicias Edif Centro Medico Maracay | E73: MCY | F73: ARA | H73: 0243-2003700 | I73: 0424-3696925 | J73: sikiu_navarrortiz@yahoo.com | L73: Alto Potencial Prescriptor | M73: 45915 | N73: dispositivosbiofarco@gmail.com | O73: Activo | P73: repbiofarco | Q73: dispositivosbiofarco@gmail.com | R73: 6 | U73: 59723 | V73: 2 | W73: Lun, Mar, Mie, Jue, Vie | X73: 0.375 | Y73: 0.58333333
A74: 103 | B74: Medicos | C74: Marlil Romero | D74: Aragua, Venezuela | E74: MCY | F74: ARA | H74: 0424-3125313 | I74: 0424-3125313 | L74: Líder de Opinión , Alto Potencial Prescriptor | M74: 45981.973 | N74: dispositivosbiofarco@gmail.com | O74: Activo | P74: repbiofarco | Q74: dispositivosbiofarco@gmail.com | R74: 1 | T74: 1 | U74: 1 | V74: 5 | W74: Vie | X74: 0.58333333 | Y74: 0.75
A75: 104 | B75: Medicos | C75: Migdalys Gómez | D75: Calle Coromoto cruce con 2da Transversal, Edificio Clínica Guadalupe, Maracay ZP2101, Aragua, Venezuela | E75: MCY | F75: ARA | I75: 0412-8736250 | L75: Alto Potencial Prescriptor | M75: 45848 | N75: dispositivosbiofarco@gmail.com | O75: Activo | P75: repbiofarco | Q75: dispositivosbiofarco@gmail.com | R75: 5 | T75: 57352 | U75: 6506 | V75: 25 | W75: Jue | X75: 0.41666667 | Y75: 0.58333333
A76: 108 | B76: Medicos | C76: Tanymar Salazar | D76: Urb La Floresta Calle Comercio Maternidad La Floresta Maracay | E76: MCY | F76: ARA | H76: 0412-4614480 | I76: 0424-3765599 | J76: tanysr91@gmail.com | L76: Alto Potencial Prescriptor | M76: 45796 | N76: dispositivosbiofarco@gmail.com | O76: Activo | P76: repbiofarco | Q76: dispositivosbiofarco@gmail.com | R76: 3 | T76: 1 | U76: 110495 | V76: 5 | W76: Lun, Mar, Mie, Jue, Vie | X76: 0.33333333 | Y76: 0.5
A77: 109 | B77: Medicos | C77: Onorlis Gallardo | D77: Urb. La Floresta, Maracay 2101, Aragua, Venezuela | E77: MCY | F77: ARA | I77: 0424-3773337 | L77: Alto Potencial Prescriptor | M77: 45849 | N77: dispositivosbiofarco@gmail.com | O77: Activo | P77: repbiofarco | Q77: dispositivosbiofarco@gmail.com | R77: 6 | T77: 140311 | U77: 140311 | V77: 26 | W77: Lun, Mar, Mie, Jue, Vie | X77: 0.33333333 | Y77: 0.58333333
A78: 110 | B78: Medicos | C78: Jhonycel Martínez | D78: Calle Coromoto cruce con 2da Transversal, Edificio Clínica Guadalupe, Maracay ZP2101, Aragua, Venezuela | E78: MCY | F78: ARA | I78: 0424-3101138 | L78: Alto Potencial Prescriptor | M78: 45987.653 | N78: dispositivosbiofarco@gmail.com | O78: Activo | P78: repbiofarco | Q78: dispositivosbiofarco@gmail.com | R78: 6 | T78: 50801 | U78: 4958 | V78: 25 | W78: Lun, Mar, Mie, Jue, Vie | X78: 0.33333333 | Y78: 0.58333333
A79: 111 | B79: Medicos | C79: Vanessa Alas R. | D79: Centro Médico Maracay | E79: MCY | F79: ARA | I79: 0414-4691018 | J79: vane_25_92@hotmail.com | L79: Alto Potencial Prescriptor | M79: 45987.794 | N79: dispositivosbiofarco@gmail.com | O79: Activo | P79: repbiofarco | Q79: dispositivosbiofarco@gmail.com | R79: 3 | T79: 114391 | U79: 11642 | V79: 2 | W79: Mie | X79: 8:00 a. m. | Z79: Gatro-Pediatra
A80: 112 | B80: Medicos | C80: Pedro L. Santa Cruz V. | D80: Calle Los Sauces, Maracay 2101, Aragua, Venezuela | E80: MCY | F80: ARA | I80: 0424-3838107 | L80: Alto Potencial Prescriptor | M80: 45987.742 | N80: dispositivosbiofarco@gmail.com | O80: Activo | P80: repbiofarco | Q80: dispositivosbiofarco@gmail.com | R80: 6 | T80: 71206 | U80: 8345 | V80: 2 | W80: Lun, Mar, Mie, Jue, Vie | X80: 0.58333333 | Y80: 0.75
A81: 113 | B81: Medicos | C81: Rafael Navas | D81: Calle Los Sauces, Maracay 2101, Aragua, Venezuela | E81: MCY | F81: ARA | H81: 0416-1467936 | I81: 0416-1467936 | L81: Líder de Opinión , Alto Potencial Prescriptor | M81: 45987.635 | N81: dispositivosbiofarco@gmail.com | O81: Activo | P81: repbiofarco | Q81: dispositivosbiofarco@gmail.com | R81: 1 | T81: 5585 | U81: 5585 | V81: 2 | W81: Lun , Mie , Vie | X81: 0.41666667 | Y81: 0.66666667
A82: 114 | B82: Medicos | C82: Stefanny Colmenarez | D82: 43 Av. Sucre, Maracay 2101, Aragua, Venezuela | E82: MCY | F82: ARA | I82: 0424-3589660 | L82: Alto Potencial Prescriptor | M82: 45855 | N82: dispositivosbiofarco@gmail.com | O82: Activo | P82: repbiofarco | Q82: dispositivosbiofarco@gmail.com | R82: 1 | T82: 132274 | U82: 12394 | V82: 10 | W82: Jue | X82: 0.41666667 | Y82: 0.66666667
A83: 115 | B83: Medicos | C83: Suhail Tovar | D83: Centro Médico Maracay | E83: MCY | F83: ARA | I83: 0412-4003237 | L83: Alto Potencial Prescriptor | M83: 45853 | N83: dispositivosbiofarco@gmail.com | O83: Activo | P83: repbiofarco | Q83: dispositivosbiofarco@gmail.com | R83: 6 | V83: 2 | W83: Lun, Mar, Mie, Jue, Vie | X83: 0.58333333 | Y83: 0.75
A84: 116 | B84: Medicos | C84: Yenit Mujica | D84: Av Principal Las Delicias Edif Centro Medico Maracay | E84: MCY | F84: ARA | I84: 0414-2647671 | J84: yenitmujica@gmail.com | L84: Alto Potencial Prescriptor | M84: 45987.618 | N84: dispositivosbiofarco@gmail.com | O84: Activo | P84: repbiofarco | Q84: dispositivosbiofarco@gmail.com | R84: 1 | T84: 23302 | U84: 6593 | V84: 2 | W84: Lun, Mar, Mie, Jue, Vie | X84: 8:00 a. m. | Y84: 12:00 p. m.
A85: 117 | B85: Medicos | C85: Yennifer Socorro | D85: Av Principal Las Delicias Edif Centro Medico Maracay | E85: MCY | F85: ARA | I85: 0424-2451790 | J85: ymsp2203@gmail.com | L85: Alto Potencial Prescriptor | M85: 45987.776 | N85: dispositivosbiofarco@gmail.com | O85: Activo | P85: repbiofarco | Q85: dispositivosbiofarco@gmail.com | R85: 3 | S85: 45738 | T85: 103474 | U85: 10659 | V85: 2 | W85: Lun, Mar, Mie, Jue, Vie | X85: 2:00 p. m. | Y85: 6:00 p. m.
A86: 118 | B86: Medicos | C86: Yosmary Marchena | D86: Av. 19 de Abril, Maracay 2101, Aragua, Venezuela | E86: MCY | F86: ARA | I86: 0414-4613309 | J86: yosmarygisel63@gmail.com | L86: Alto Potencial Prescriptor | M86: 45987.61 | N86: dispositivosbiofarco@gmail.com | O86: Activo | P86: repbiofarco | Q86: dispositivosbiofarco@gmail.com | R86: 1 | T86: 40050 | U86: 3624 | V86: 31 | W86: Lun, Mar, Mie, Jue, Vie | X86: 8:00 a. m. | Y86: 12:00 p. m.
A87: 119 | B87: Medicos | C87: Yris Cardozo | D87: Av Principal Las Delicias Edif Centro Medico Maracay | E87: MCY | F87: ARA | I87: 0416-6117403 | J87: yriscardozo3108@gmail.com | K87: @dra.yriscardozo | L87: Líder de Opinión , Alto Potencial Prescriptor | M87: 45839 | N87: dispositivosbiofarco@gmail.com | O87: Activo | P87: repbiofarco | Q87: dispositivosbiofarco@gmail.com | R87: 6 | T87: 59724 | U87: 6952 | V87: 2 | W87: Lun , Mar , Jue , Vie | X87: 0.33333333 | Y87: 0.5 | Z87: Miercoles en emergencias CCM
A88: 120 | B88: Medicos | C88: Zulma Alvarado | D88: Urb. La Floresta, Maracay 2101, Aragua, Venezuela | E88: MCY | F88: ARA | H88: 0412-831.84.04 | I88: 0424-379.77.84 | J88: zalavaradom@gmail.com | L88: Alto Potencial Prescriptor | M88: 45987.753 | N88: dispositivosbiofarco@gmail.com | O88: Activo | P88: repbiofarco | Q88: dispositivosbiofarco@gmail.com | R88: 3 | T88: 103458 | U88: 10785 | V88: 26 | W88: Mie, Jue, Vie | X88: 8:30 a. m.
A89: 123 | B89: Medicos | C89: Enza Vitale | D89: Centro Empresarial Europa, Avenida Las Delicias, Maracay 2101, Aragua, Venezuela | E89: MCY | F89: ARA | I89: 0414-4945521 | L89: Alto Potencial Prescriptor | M89: 45987.723 | N89: dispositivosbiofarco@gmail.com | O89: Activo | P89: repbiofarco | Q89: dispositivosbiofarco@gmail.com | R89: 3 | T89: 77070 | U89: 9304 | V89: 28 | W89: Vie | X89: 1:00 p. m. | Y89: 5:00 p. m.
A90: 125 | B90: Medicos | C90: Yasenka Arias | D90: 6CQ7+MC8, Av. Fuerzas Aéreas, Maracay 2103, Aragua, Venezuela | E90: MCY | F90: ARA | I90: 0414-4602902 | L90: Alto Potencial Prescriptor | M90: 45987.791 | N90: dispositivosbiofarco@gmail.com | O90: Activo | P90: repbiofarco | Q90: dispositivosbiofarco@gmail.com | R90: 1 | S90: 45824 | T90: 66115 | U90: 7694 | V90: 17 | W90: Lun, Mar, Mie, Jue, Vie | X90: 0.3125 | Y90: 0.41666667
A91: 126 | B91: Medicos | C91: Zulma Ramírez | D91: Torre Cosmopolitan, Piso 1, Av.19 De Abril | E91: MCY | F91: ARA | I91: 0414-4627768 | J91: zulmart12@hotmail.com | L91: Alto Potencial Prescriptor | M91: 45854 | N91: dispositivosbiofarco@gmail.com | O91: Activo | P91: repbiofarco | Q91: dispositivosbiofarco@gmail.com | R91: 3 | V91: 40 | W91: Lun, Mar, Mie, Jue, Vie | X91: 0.3125 | Y91: 0.41666667 | Z91: Lunes y Miercoles en el HCM
A92: 127 | B92: Medicos | C92: Yoadelis De Armas | D92: Calle Los Sauces, Maracay 2101, Aragua, Venezuela | E92: MCY | F92: ARA | I92: 0414-4616648 | L92: Alto Potencial Prescriptor | M92: 45987.744 | N92: dispositivosbiofarco@gmail.com | O92: Activo | P92: repbiofarco | Q92: dispositivosbiofarco@gmail.com | R92: 6 | T92: 79101 | U92: 5394 | V92: 2 | W92: Lun, Mar, Mie, Jue, Vie | X92: 8:00 a. m. | Y92: 12:00 p. m.
A93: 128 | B93: Medicos | C93: Claudia Mosquera | D93: Urb. La Floresta, Maracay 2101, Aragua, Venezuela | E93: MCY | F93: ARA | I93: 0424-3335050 | L93: Alto Potencial Prescriptor | M93: 45987.639 | N93: dispositivosbiofarco@gmail.com | O93: Activo | P93: repbiofarco | Q93: dispositivosbiofarco@gmail.com | R93: 6 | T93: 17337 | U93: 8449 | V93: 26 | W93: Lun, Mar, Mie, Jue, Vie | X93: 7:00 a. m. | Y93: 12:00 p. m.
A94: 129 | B94: Medicos | C94: Gloria Gutiérrez | D94: CMM | E94: MCY | F94: ARA | H94: 0424-4335071 | I94: 0424-4335071 | L94: Alto Potencial Prescriptor | M94: 45987.615 | N94: dispositivosbiofarco@gmail.com | O94: Activo | P94: repbiofarco | Q94: dispositivosbiofarco@gmail.com | R94: 1 | S94: 45818 | T94: 61720 | U94: 7121 | V94: 2 | W94: Lun , Mar | X94: 3:03 p. m. | Y94: 3:03 p. m.
A95: 130 | B95: Medicos | C95: Dayana Muñoz | D95: Centro Médico Maracay Piso 5 Consultorio 33 | E95: MCY | F95: ARA | H95: 0412-8851818 | I95: 0412-8851818 | L95: Alto Potencial Prescriptor | M95: 45987.716 | N95: dispositivosbiofarco@gmail.com | O95: Activo | P95: repbiofarco | Q95: dispositivosbiofarco@gmail.com | R95: 5 | S95: 45819 | T95: 90599 | U95: 9499 | V95: 2 | W95: Lun , Mie , Vie | X95: 8:00 a. m. | Y95: 12:00 p. m.
A96: 131 | B96: Medicos | C96: Crisnel Hernández M. | D96: Calle Comercio, Maracay 2101, Aragua, Venezuela | E96: MCY | F96: ARA | I96: 0416-6439412 | L96: Líder de Opinión , Alto Potencial Prescriptor | M96: 45848 | N96: dispositivosbiofarco@gmail.com | O96: Activo | P96: repbiofarco | Q96: dispositivosbiofarco@gmail.com | R96: 1 | S96: 45821 | T96: 66998 | U96: 7867 | V96: 5 | W96: Lun, Mar, Mie, Jue, Vie | X96: 7:34 a. m. | Y96: 7:34 a. m. | Z96: Nefrólogo Pediatra
A97: 132 | B97: Medicos | C97: Emiberth Torres | D97: Calle Comercio, Maracay 2101, Aragua, Venezuela | E97: MCY | F97: ARA | I97: 0416-6400367 | L97: Líder de Opinión , Alto Potencial Prescriptor | M97: 45912 | N97: dispositivosbiofarco@gmail.com | O97: Activo | P97: repbiofarco | Q97: dispositivosbiofarco@gmail.com | R97: 1 | S97: 45821 | T97: 43086 | U97: 3983 | V97: 5 | W97: Lun , Mie , Vie | X97: 7:36 a. m. | Y97: 12:00 p. m. | Z97: Neumología Pediátrica
A98: 133 | B98: Medicos | C98: Andy Lai Ferreira | D98: Avenida 19 De Abril, Maracay 2103, Aragua, Venezuela | E98: MCY | F98: ARA | I98: 0412-8917042 | L98: Alto Potencial Prescriptor | M98: 45845 | N98: dispositivosbiofarco@gmail.com | O98: Activo | P98: repbiofarco | Q98: dispositivosbiofarco@gmail.com | R98: 4 | S98: 45824 | T98: 1 | U98: 1 | V98: 14 | W98: Lun, Mar, Mie, Jue, Vie | X98: 8:00 a. m. | Y98: 0.5
A99: 134 | B99: Medicos | C99: Rafael E. Velásquez S. | D99: Avenida 19 De Abril, Maracay 2103, Aragua, Venezuela | E99: MCY | F99: ARA | I99: 0412-3195488 | L99: Alto Potencial Prescriptor | M99: 45987.726 | N99: dispositivosbiofarco@gmail.com | O99: Activo | P99: repbiofarco | Q99: dispositivosbiofarco@gmail.com | R99: 6 | S99: 45824 | T99: 26455 | U99: 1873 | V99: 14 | W99: Lun, Mar, Mie, Jue, Vie | X99: 8:48 a. m. | Y99: 12:00 p. m.
A100: 135 | B100: Medicos | C100: Jean Carlos Molina | D100: Clínica Lugo | E100: MCY | F100: ARA | H100: 0243-2002129 | I100: 0414-1446538 | K100: @dr.jcmolina | L100: Alto Potencial Prescriptor | M100: 45987.656 | N100: dispositivosbiofarco@gmail.com | O100: Activo | P100: repbiofarco | Q100: dispositivosbiofarco@gmail.com | R100: 6 | S100: 45824 | T100: 103046 | U100: 10968 | V100: 14 | W100: Lun, Mar, Mie, Jue, Vie | X100: 9:41 a. m. | Y100: 0.58333333
...

Sheet Inicio
A1: ID
A2: 1

Sheet Ciclo
A1: ID_Ciclo | B1: NombreCiclo | C1: FechaInicio | D1: FechaFin | E1: Estado | F1: ID_Usuario | G1: SUBMITTED BY
A2: 9 | B2: Septiembre | C2: 45901 | D2: 45930 | E2: Pasado | F2: repbiofarco | G2: dispositivosbiofarco@gmail.com
A3: 10 | B3: Octubre | C3: 45931 | D3: 45961 | E3: Pasado | F3: repbiofarco | G3: dispositivosbiofarco@gmail.com
A4: 11 | B4: Noviembre | C4: 45962 | D4: 45991 | E4: Pasado | F4: repbiofarco | G4: dispositivosbiofarco@gmail.com
A5: 12 | B5: Diciembre | C5: 45992 | D5: 46022 | E5: Pasado | F5: repbiofarco | G5: dispositivosbiofarco@gmail.com
A6: 4 | B6: Abril | C6: 46113 | D6: 46142 | E6: Vigente | F6: repbiofarco | G6: dispositivosbiofarco@gmail.com
A7: 5 | B7: Mayo | C7: 46143 | D7: 46173 | E7: Pendiente | F7: repbiofarco | G7: dispositivosbiofarco@gmail.com

Sheet Estrategia_Ciclo
A1: ID_Ciclo | B1: ID_Estrategia | C1: Semana_Numero | D1: Dia_Semana | E1: Actividad_Clave | F1: Zona_Objetivo | G1: Enfoque_Estrategico | H1: ID_Usuario | I1: SUBMITTED BY
A2: 4 | B2: EST-17-LUN | C2: 17 | D2: Lunes | E2: Auditoría de Inventario | F2: Santa Rita (Sureste) | G2: Verificar presencia del portafolio e inducir a transferencias. | H2: repbiofarco | I2: dispositivosbiofarco@gmail.com
A3: 4 | B3: EST-17-MAR | C3: 17 | D3: Martes | E3: Fidelización | F3: Casco Central Maracay I | G3: Foco en FarmaVital y Farmatodo. Ventaja del Citrato de Calcio (Calzinc D). | H3: repbiofarco | I3: dispositivosbiofarco@gmail.com
A4: 4 | B4: EST-17-MIE | C4: 17 | D4: Miércoles | E4: Rotación | F4: SurOeste (Limón/Coromoto) | G4: Monitorear desplazamiento de línea pediátrica y gastro. | H4: repbiofarco | I4: dispositivosbiofarco@gmail.com
A5: 4 | B5: EST-17-JUE | C5: 17 | D5: Jueves | E5: Jornada de Impulso | F5: Farmatodo Delta | G5: Línea Gastro (10:00-14:00). Promoción directa de Neutrox. | H5: repbiofarco | I5: dispositivosbiofarco@gmail.com
A6: 4 | B6: EST-17-VIE | C6: 17 | D6: Viernes | E6: Entorno 360 | F6: Zona Norte (HCM) | G6: Asegurar stock de Zincosol en farmacias cercanas al hospital. | H6: repbiofarco | I6: dispositivosbiofarco@gmail.com
A7: 4 | B7: EST-18-LUN | C7: 18 | D7: Lunes | E7: Cobertura Independientes | F7: Casco Central | G7: Visitar Mini Cadenas y farmacias de barrio. | H7: repbiofarco | I7: dispositivosbiofarco@gmail.com
A8: 4 | B8: EST-18-MAR | C8: 18 | D8: Martes | E8: Charla Reinducción | F8: Maracay II | G8: Mundo Total (10:00 AM). Refrescar marca BIOFARCO. | H8: repbiofarco | I8: dispositivosbiofarco@gmail.com
A9: 4 | B9: EST-18-MIE | C9: 18 | D9: Miércoles | E9: Gestión de Transferencias | F9: Ciudad de Cagua | G9: Detectar fallas y coordinar con DroNena/COBECA. | H9: repbiofarco | I9: dispositivosbiofarco@gmail.com

Sheet Objetivos
A1: ID_Objetivo | B1: ID_Ciclo | C1: ID_Usuario | D1: Meta_Farmacias | E1: Meta_Eventos | F1: Meta_Venta_Unidades | G1: Meta_Venta_Valor | H1: Foco_Producto_Mes | I1: Meta_Cobertura_Foco | J1: SUBMITTED BY
A2: 1 | B2: 9 | C2: cascanior | D2: 100 | E2: 2 | J2: dispositivosbiofarco@gmail.com
A3: 5 | B3: 10 | C3: cascanior | D3: 100 | E3: 2 | J3: dispositivosbiofarco@gmail.com
A4: 9 | B4: 11 | C4: cascanior | D4: 100 | E4: 2 | J4: dispositivosbiofarco@gmail.com
A5: 13 | B5: 12 | C5: cascanior | D5: 100 | E5: 2 | J5: dispositivosbiofarco@gmail.com
A6: 4 | B6: 4 | C6: cascanior | D6: 100 | F6: 1000 | J6: dispositivosbiofarco@gmail.com

Sheet Objetivos_Especialidad
A1: ID_Obj_Esp | B1: ID_Objetivo | C1: ID_Especialidad | D1: Meta_Visitas_Medicas

Sheet Control
A1: ID_Control
A2: 1

Sheet Filtro
A1: Usuario | B1: Fecha Inicial | C1: Fecha Final | D1: Tipo Contacto Visitado | E1: Medico Visitado Ref | F1: Farmacia Visitada Ref | G1: ID_Usuario | H1: SUBMITTED BY
A2: cesarascaniofp.us@gmail.com | B2: 45870 | C2: 45899 | D2: Farmacias | G2: repbiofarco | H2: dispositivosbiofarco@gmail.com

Sheet FiltroReporteGerencial
A1: ID_Filtro | B1: Mes | C1: Año
A2: 1 | B2: Septiembre | C2: 2025

Sheet Productos
A1: ID_Producto | B1: Codigo_Barras | C1: Nombre | D1: Principio(s) Activo(s) | E1: Composición / Presentación Principal | F1: Concentracion_mg_mL | G1: Dosis_mg_kg | H1: Stock_Seguridad | I1: Indicaciones (Consolidado) | J1: Especialidad(es) Médica(s) (Según Manual) | K1: Mensaje Clave (Según Manual) | L1: Dosificación / Aplicación (Según Información Disponible) | M1: Seguridad (Contraind. / Precauciones Clave) | N1: Categoría | O1: Imagen | P1: Link_PDF | Q1: Es_Papeleta | R1: Status
A2: PRO-004 | B2: 1759161600039 | C2: Aceite de Almendras Dulces | D2: Aceite de almendras dulces | E2: Frasco 30 mL | I2: Emoliente, humectante y suavizante de manos y piel. | J2: Dermatología, Cosmética | K2: Hidratación natural para pieles secas y sensibles. | L2: Aplicar directamente sobre la piel limpia y seca, masajeando. Usar según necesidad. | M2: Precaución en alergia a frutos secos. Uso externo. | N2: Productos Oficinales | O2: Productos_Images/PRO-004.Imagen.185006.png | Q2: FALSE | R2: Activo
A3: PRO-052 | B3: 7591616000056 | C3: Aceite de Coco | D3: Aceite de coco grado USP | E3: Frasco 30 mL | I3: Emoliente, vehículo bronceador. | J3: Dermatología, Cosmética | K3: Emoliente natural y base para bronceadores. | L3: Aplicar sobre la piel según necesidad. | M3: Generalmente bien tolerado. Puede ser comedogénico en pieles propensas al acné. | O3: Productos_Images/PRO-052.Imagen.231220.png | Q3: FALSE | R3: Activo
A4: PRO-006 | B4: 17591616000138 | C4: Aceite de Ricino | D4: Aceite de Ricino | E4: Frasco 30 mL | I4: Laxante natural y digestivo. Usos capilares y cuidado de barba/pestañas. | J4: Gastroenterología, Cosmética | K4: Doble uso: Laxante natural efectivo y nutriente cosmético para cabello y pestañas. | L4: Como laxante: Dosis oral no especificada. Uso tópico capilar/pestañas: aplicar pequeña cantidad. | M4: No usar de forma crónica como laxante. Contraindicado en embarazo (vía oral) ya que puede inducir contracciones uterinas. | N4: Productos Oficinales | O4: Productos_Images/PRO-006.Imagen.185058.png | Q4: FALSE | R4: Activo
A5: PRO-017 | B5: 7591616002272 | C5: Aceite de Castor | D5: Aceite de Castor | E5: Frasco 30 mL | I5: Laxante natural y digestivo. Usos capilares y cuidado de barba/pestañas. | J5: Gastroenterología, Cosmética | K5: Doble uso: Laxante natural efectivo y nutriente cosmético para cabello y pestañas. | L5: Como laxante: Dosis oral no especificada. Uso tópico capilar/pestañas: aplicar pequeña cantidad. | M5: No usar de forma crónica como laxante. Contraindicado en embarazo (vía oral) ya que puede inducir contracciones uterinas. | N5: Productos Oficinales | O5: Productos_Images/PRO-006.Imagen.185058.png | Q5: FALSE | R5: Activo
A6: PRO-005 | B6: 7591616000162 | C6: Aceite Mineral | D6: Aceite mineral NF | E6: Frasco 30 mL | I6: Emoliente y suavizante de manos y piel, lubricante, vehículo farmacéutico. | J6: Dermatología, Farmacia | K6: Emoliente y lubricante de alta pureza para el cuidado de la piel. | L6: Aplicar sobre la piel según necesidad. | M6: Puede ser comedogénico en algunas personas. Uso externo principalmente. | N6: Productos Oficinales | O6: Productos_Images/PRO-005.Imagen.185029.png | Q6: FALSE | R6: Activo
A7: PRO-001 | B7: 7591616002418 | C7: Acetaclor Jarabe | D7: Acetaminofén, Clorfeniramina Maleato | E7: Jarabe 120 mL (5 mL: 125 mg Acetaminofén, 0.5 mg Clorfeniramina) | F7: 25 | G7: 15 | H7: 12 | I7: Tratamiento sintomático del resfriado común. Uso pediátrico. | J7: Pediatría, Medicina General | K7: Alivio de los síntomas del resfriado común (fiebre, dolor, secreción nasal) en una fórmula pediátrica. | L7: Dosis 5 mL contienen 125 mg Acetaminofén, 0.5 mg Clorfeniramina. Dosificación por edad/peso no detallada. | M7: Precaución en asma/problemas respiratorios. No usar con otros productos con Acetaminofén. Puede causar somnolencia. | N7: Jarabes Respiratorios | O7: Productos_Images/PRO-001.Imagen.184816.png | Q7: FALSE | R7: Activo
A8: PRO-002 | B8: 7591616002142 | C8: Acetaten Forte | D8: Acetaminofén (Paracetamol) | E8: Suspensión 120 ml (180 mg/5 ml) | F8: 36 | G8: 15 | H8: 10 | I8: Alivio de dolor leve a moderado y fiebre. | J8: Medicina General, Pediatría | K8: Seguridad y eficacia comprobada, incluso en niños. Dosificación precisa y sabor neutro. Orgullo Biofarco. | L8: Dosis diaria aprox. 60 mg/kg/día, dividida en 4-6 tomas. | M8: Evitar sobredosis por riesgo de hepatotoxicidad. Precaución en daño hepático/renal. | N8: Analgésicos | O8: Productos_Images/PRO-002.Imagen.184922.png | Q8: FALSE | R8: Activo
A9: PRO-003 | B9: 17591616001463 | C9: Ácido Bórico (Polvo Uso Externo) | D9: Ácido Bórico USP | E9: Sobre 20 g | I9: Antiséptico de uso tópico, preparación de agua boricada para lavados vaginales y limpieza de cutis en acné. | J9: Ginecología, Dermatología | K9: Antiséptico suave para preparaciones tópicas personalizadas. | L9: Disolver el polvo en agua para preparar la solución. | M9: No usar en piel dañada/quemaduras/heridas abiertas, ni en el área del pañal en bebés. Evitar ingestión. | N9: Productos Oficinales | O9: Productos_Images/PRO-003.Imagen.184942.png | Q9: TRUE | R9: Activo
A10: PRO-007 | B10: 7591616000285 | C10: Alcohol Absoluto (98° GL) 240 ml | D10: Alcohol etílico desnaturalizado 98° GL | E10: Frascos: 240 ml | I10: Cicatrizante y astringente. Empleado en la cicatrización del ombligo en neonatos. | J10: Neonatología, Pediatría | K10: Rápida y efectiva cicatrización del ombligo en neonatos. | L10: Aplicar directamente sobre la base del cordón umbilical en cada cambio de pañal. | M10: Altamente inflamable. Uso externo. Evitar ojos/mucosas. | N10: Productos Oficinales | O10: Productos_Images/PRO-007.Imagen.185127.png | Q10: FALSE | R10: Activo
A11: PRO-007-1 | B11: 7591616000315 | C11: Alcohol Absoluto (98° GL) 60 ml | D11: Alcohol etílico desnaturalizado 98° GL | E11: Frascos: 60 ml | I11: Cicatrizante y astringente. Empleado en la cicatrización del ombligo en neonatos. | J11: Neonatología, Pediatría | K11: Rápida y efectiva cicatrización del ombligo en neonatos. | L11: Aplicar directamente sobre la base del cordón umbilical en cada cambio de pañal. | M11: Altamente inflamable. Uso externo. Evitar ojos/mucosas. | N11: Productos Oficinales | O11: Productos_Images/PRO-007.Imagen.185127.png | Q11: FALSE | R11: Activo
